[
  {
    "web-scraper-order": "1629124512-103",
    "web-scraper-start-url": "https://www2.hm.com/en_in/men/shop-by-product/trousers.html",
    "link": "Slim Fit Sports joggers",
    "link-href": "https://www2.hm.com/en_in/productpage.0995680001.html",
    "name": "Slim Fit Sports joggers",
    "description": "Jersey joggers for indoor and outdoor workouts. Covered elastication and a drawstring at the waist, zipped side pockets for safe storage of valuables and a mesh panel at the crotch for increased air permeability. Cuffed hems.",
    "review_count": null,
    "details": "Details\n\t\n\t\tSizeInside leg: Length: 73.5 cm (Size L/L)LengthLongWaist RiseRegular waistFitSlim fitStyleJoggersCompositionShell: Cotton 58%, Polyester 38%, Elastane 4%Mesh: Polyester 100%Care instructionsMachine wash at 40°Sports activityTrainingDescriptionGrey marlNice to knowConsciousPrice (MRP)Rs. 1,999 incl. of all taxesCountry of productionCambodiaCommon generic nameTrousersNet quantity1 NMarketed or imported byH&M Hennes & Mauritz Retail Pvt. Ltd. A-wing, D-3, 2nd Floor District Centre Saket New Delhi -110017 IndiaDate of import08-2021Date of manufactureN/AManufactured byN/ACustomer serviceIn case of consumer complaint, write to H&M Hennes & Mauritz Retail PVT. Ltd, A Wing, D3, 2nd Floor, District Center, Saket, New Delhi 110017, India or call Telephone: 0008000501633. For online and store complaints email customerservice.in@hm.com.DisclaimerThis information is based on sample of the product displayed on website. There may be change in the information on label attached to the product delivered to the customer due to size chosen, date of import, name of manufacturer (in case of manufacturing in India), country of manufacture, etc. The exact detail relevant to the product delivered to the customer will reflect in the label attached to the product so deliveredArt. No.0995680001",
    "img1-src": "//lp2.hm.com/hmgoepprod?set=quality%5B79%5D%2Csource%5B%2Fd6%2F2a%2Fd62aef7c6a075ca12c8b96a06aea6cec206eb4ef.jpg%5D%2Corigin%5Bdam%5D%2Ccategory%5B%5D%2Ctype%5BLOOKBOOK%5D%2Cres%5Bm%5D%2Chmver%5B1%5D&call=url[file:/product/main]",
    "img2-src": "//lp2.hm.com/hmgoepprod?set=quality%5B79%5D%2Csource%5B%2Ff0%2Fb7%2Ff0b7f6a15f20052880608ec8e044f80ff9d3b692.jpg%5D%2Corigin%5Bdam%5D%2Ccategory%5B%5D%2Ctype%5BLOOKBOOK%5D%2Cres%5Bm%5D%2Chmver%5B1%5D&call=url[file:/product/main]",
    "style": "Joggers",
    "generic name": "Trousers",
    "colors": "Grey marl",
    "descript": "Mesh: Polyester 100%",
    "item__price": "Rs. 1,999",
    "Fit": "Slim fit",
    "Composition": "Shell: Cotton 58%, Polyester 38%, Elastane 4%Mesh: Polyester 100%"
  },
  {
    "web-scraper-order": "1629124351-55",
    "web-scraper-start-url": "https://www2.hm.com/en_in/men/shop-by-product/trousers.html",
    "link": "Suit trousers Slim Fit",
    "link-href": "https://www2.hm.com/en_in/productpage.0714026030.html",
    "name": "Suit trousers Slim Fit",
    "description": "Suit trousers in woven fabric with a concealed hook-and-eye fastening and zip fly. Side pockets, jetted back pockets and legs with creases. Slim Fit – a fit that is close-fitting at the thighs, knees and ankles to create a fitted silhouette.",
    "review_count": null,
    "details": "Details\n\t\n\t\tLengthLongFitSlim fitStyleSuit trousersCompositionShell: Polyester 64%, Viscose 34%, Elastane 2%Pocket lining: Polyester 91%, Cotton 9%Care instructionsMachine wash at 30°DescriptionDark grey/GreyCheckedConceptH&M MANNice to knowConsciousPrice (MRP)Rs. 2,299 incl. of all taxesCountry of productionBangladeshCommon generic nameTrousersNet quantity1 NMarketed or imported byH&M Hennes & Mauritz Retail Pvt. Ltd. A-wing, D-3, 2nd Floor District Centre Saket New Delhi -110017 IndiaDate of import08-2021Date of manufactureN/AManufactured byN/ACustomer serviceIn case of consumer complaint, write to H&M Hennes & Mauritz Retail PVT. Ltd, A Wing, D3, 2nd Floor, District Center, Saket, New Delhi 110017, India or call Telephone: 0008000501633. For online and store complaints email customerservice.in@hm.com.DisclaimerThis information is based on sample of the product displayed on website. There may be change in the information on label attached to the product delivered to the customer due to size chosen, date of import, name of manufacturer (in case of manufacturing in India), country of manufacture, etc. The exact detail relevant to the product delivered to the customer will reflect in the label attached to the product so deliveredArt. No.0714026030",
    "img1-src": "//lp2.hm.com/hmgoepprod?set=quality%5B79%5D%2Csource%5B%2F15%2F13%2F15131c558d816e98a746d43aa55bcb870eda34ec.jpg%5D%2Corigin%5Bdam%5D%2Ccategory%5B%5D%2Ctype%5BLOOKBOOK%5D%2Cres%5Bm%5D%2Chmver%5B1%5D&call=url[file:/product/main]",
    "img2-src": "//lp2.hm.com/hmgoepprod?set=quality%5B79%5D%2Csource%5B%2F72%2F2c%2F722c4fa30b92252307c5091fb2e5dd11d6b011ed.jpg%5D%2Corigin%5Bdam%5D%2Ccategory%5B%5D%2Ctype%5BLOOKBOOK%5D%2Cres%5Bm%5D%2Chmver%5B1%5D&call=url[file:/product/main]",
    "style": "Suit trousers",
    "generic name": "Trousers",
    "colors": "Dark grey/Grey",
    "descript": "Checked",
    "item__price": "Rs. 2,299",
    "Fit": "Slim fit",
    "Composition": "Shell: Polyester 64%, Viscose 34%, Elastane 2%Pocket lining: Polyester 91%, Cotton 9%"
  },
  {
    "web-scraper-order": "1629124313-42",
    "web-scraper-start-url": "https://www2.hm.com/en_in/men/shop-by-product/trousers.html",
    "link": "Regular Fit Cropped joggers",
    "link-href": "https://www2.hm.com/en_in/productpage.0965012002.html",
    "name": "Regular Fit Cropped joggers",
    "description": "Cropped joggers in soft twill made from a lyocell and cotton blend with covered elastication and a concealed drawstring at the waist, zip fly and button, diagonal side pockets and open back pockets. Regular Fit – a classic fit with good room for movement over the thighs and knees to create a comfortable, straight silhouette.",
    "review_count": null,
    "details": "Details\n\t\n\t\tSizeInside leg: Length: 72.5 cm (Size 52L)LengthAnkle lengthWaist RiseRegular waistFitRegular fitStyleJoggersCompositionPocket lining: Polyester 89%, Cotton 11%Shell: Cotton 50%, Lyocell 50%Care instructionsLine dryOnly non-chlorine bleach when neededMedium ironMachine wash at 30°Can be dry cleanedDescriptionBeigeSolid colourConceptH&M MANNice to knowConsciousPrice (MRP)Rs. 2,299 incl. of all taxesCountry of productionChinaCommon generic nameTrousersNet quantity1 NMarketed or imported byH&M Hennes & Mauritz Retail Pvt. Ltd. A-wing, D-3, 2nd Floor District Centre Saket New Delhi -110017 IndiaDate of import01-2021Date of manufactureN/AManufactured byN/ACustomer serviceIn case of consumer complaint, write to H&M Hennes & Mauritz Retail PVT. Ltd, A Wing, D3, 2nd Floor, District Center, Saket, New Delhi 110017, India or call Telephone: 0008000501633. For online and store complaints email customerservice.in@hm.com.DisclaimerThis information is based on sample of the product displayed on website. There may be change in the information on label attached to the product delivered to the customer due to size chosen, date of import, name of manufacturer (in case of manufacturing in India), country of manufacture, etc. The exact detail relevant to the product delivered to the customer will reflect in the label attached to the product so deliveredArt. No.0965012002",
    "img1-src": "//lp2.hm.com/hmgoepprod?set=quality%5B79%5D%2Csource%5B%2F14%2F99%2F14992ee7b9bcdc5a59e5314eaf0b36c8cfe489a4.jpg%5D%2Corigin%5Bdam%5D%2Ccategory%5B%5D%2Ctype%5BLOOKBOOK%5D%2Cres%5Bm%5D%2Chmver%5B1%5D&call=url[file:/product/main]",
    "img2-src": "//lp2.hm.com/hmgoepprod?set=quality%5B79%5D%2Csource%5B%2F4c%2F85%2F4c85520de8b0c2a0fc55bac934864e2f6239d255.jpg%5D%2Corigin%5Bdam%5D%2Ccategory%5B%5D%2Ctype%5BLOOKBOOK%5D%2Cres%5Bm%5D%2Chmver%5B1%5D&call=url[file:/product/main]",
    "style": "Joggers",
    "generic name": "Trousers",
    "colors": "Beige",
    "descript": "Shell: Cotton 50%, Lyocell 50%",
    "item__price": "Rs. 2,299",
    "Fit": "Regular fit",
    "Composition": "Pocket lining: Polyester 89%, Cotton 11%Shell: Cotton 50%, Lyocell 50%"
  },
  {
    "web-scraper-order": "1629124297-37",
    "web-scraper-start-url": "https://www2.hm.com/en_in/men/shop-by-product/trousers.html",
    "link": "Sweatpants Regular Fit",
    "link-href": "https://www2.hm.com/en_in/productpage.0763988004.html",
    "name": "Sweatpants Regular Fit",
    "description": "Sweatpants with an elasticated drawstring waist in a relaxed style with a slightly lower crotch, pockets in the side seams and tapered legs with ribbed hems. Soft brushed inside. Regular fit.",
    "review_count": null,
    "details": "Details\n\t\n\t\tSizeInside leg: Length: 76.8 cm (Size L/L)LengthLongFitRegular fitStyleSweatpantsCompositionCotton 73%, Polyester 23%, Viscose 4%Care instructionsMachine wash at 40°DescriptionLight grey marlSolid colourConceptBASICSPrice (MRP)Rs. 1,299 incl. of all taxesCountry of productionBangladeshCommon generic nameTrousersNet quantity1 NMarketed or imported byH&M Hennes & Mauritz Retail Pvt. Ltd. A-wing, D-3, 2nd Floor District Centre Saket New Delhi -110017 IndiaDate of import02-2021Date of manufactureN/AManufactured byN/ACustomer serviceIn case of consumer complaint, write to H&M Hennes & Mauritz Retail PVT. Ltd, A Wing, D3, 2nd Floor, District Center, Saket, New Delhi 110017, India or call Telephone: 0008000501633. For online and store complaints email customerservice.in@hm.com.DisclaimerThis information is based on sample of the product displayed on website. There may be change in the information on label attached to the product delivered to the customer due to size chosen, date of import, name of manufacturer (in case of manufacturing in India), country of manufacture, etc. The exact detail relevant to the product delivered to the customer will reflect in the label attached to the product so deliveredArt. No.0763988004",
    "img1-src": "//lp2.hm.com/hmgoepprod?set=quality%5B79%5D%2Csource%5B%2F06%2F72%2F0672184afea073e10909d642463e03724b1d7a12.jpg%5D%2Corigin%5Bdam%5D%2Ccategory%5Bmen_trousers_joggers%5D%2Ctype%5BDESCRIPTIVESTILLLIFE%5D%2Cres%5Bm%5D%2Chmver%5B2%5D&call=url[file:/product/main]",
    "img2-src": "//lp2.hm.com/hmgoepprod?set=quality%5B79%5D%2Csource%5B%2F48%2F7c%2F487c1ab67d48c5e6a648ac4604d1fb5f6a8f1fa5.jpg%5D%2Corigin%5Bdam%5D%2Ccategory%5Bmen_trousers_joggers%5D%2Ctype%5BDESCRIPTIVEDETAIL%5D%2Cres%5Bm%5D%2Chmver%5B2%5D&call=url[file:/product/main]",
    "style": "Sweatpants",
    "generic name": "Trousers",
    "colors": "Light grey marl",
    "descript": null,
    "item__price": "Rs. 1,299",
    "Fit": "Regular fit",
    "Composition": "Cotton 73%, Polyester 23%, Viscose 4%"
  },
  {
    "web-scraper-order": "1629124422-76",
    "web-scraper-start-url": "https://www2.hm.com/en_in/men/shop-by-product/trousers.html",
    "link": "Skinny Fit Cargo joggers",
    "link-href": "https://www2.hm.com/en_in/productpage.0997065005.html",
    "name": "Skinny Fit Cargo joggers",
    "description": "Joggers in cotton twill with an elasticated, drawstring waist, side pockets, and leg and back pockets with a flap and concealed press-studs. Tapered legs with seams at the knees and cuffed hems. Skinny Fit – a fit with slightly shorter legs that is close-fitting at the thighs, knees and ankles to create a completely fitted silhouette.",
    "review_count": null,
    "details": "Details\n\t\n\t\tSizeInside leg: Length: 76.5 cm (Size M/L)LengthLongWaist RiseRegular waistFitSkinny fitStyleCargoJoggersCompositionShell: Cotton 98%, Elastane 2%Pocket lining: Cotton 100%Care instructionsMachine wash at 40°MaterialCottonDescriptionDark green/Dark brownPatternedNice to knowConsciousPrice (MRP)Rs. 2,299 incl. of all taxesCountry of productionBangladeshCommon generic nameTrousersNet quantity1 NMarketed or imported byH&M Hennes & Mauritz Retail Pvt. Ltd. A-wing, D-3, 2nd Floor District Centre Saket New Delhi -110017 IndiaDate of import06-2021Date of manufactureN/AManufactured byN/ACustomer serviceIn case of consumer complaint, write to H&M Hennes & Mauritz Retail PVT. Ltd, A Wing, D3, 2nd Floor, District Center, Saket, New Delhi 110017, India or call Telephone: 0008000501633. For online and store complaints email customerservice.in@hm.com.DisclaimerThis information is based on sample of the product displayed on website. There may be change in the information on label attached to the product delivered to the customer due to size chosen, date of import, name of manufacturer (in case of manufacturing in India), country of manufacture, etc. The exact detail relevant to the product delivered to the customer will reflect in the label attached to the product so deliveredArt. No.0997065005",
    "img1-src": "//lp2.hm.com/hmgoepprod?set=quality%5B79%5D%2Csource%5B%2F7f%2F4a%2F7f4a656f05b0a09f69fe663972d209bf4847f69b.jpg%5D%2Corigin%5Bdam%5D%2Ccategory%5B%5D%2Ctype%5BLOOKBOOK%5D%2Cres%5Bm%5D%2Chmver%5B1%5D&call=url[file:/product/main]",
    "img2-src": "//lp2.hm.com/hmgoepprod?set=quality%5B79%5D%2Csource%5B%2F49%2Fcf%2F49cf57dc019d4d42dce71d10b2866f144da67ae6.jpg%5D%2Corigin%5Bdam%5D%2Ccategory%5B%5D%2Ctype%5BLOOKBOOK%5D%2Cres%5Bm%5D%2Chmver%5B1%5D&call=url[file:/product/main]",
    "style": "Cargo",
    "generic name": "Trousers",
    "colors": "Dark green/Dark brown",
    "descript": "Pocket lining: Cotton 100%",
    "item__price": "Rs. 2,299",
    "Fit": "Skinny fit",
    "Composition": "Shell: Cotton 98%, Elastane 2%Pocket lining: Cotton 100%"
  },
  {
    "web-scraper-order": "1629124382-64",
    "web-scraper-start-url": "https://www2.hm.com/en_in/men/shop-by-product/trousers.html",
    "link": "Linen suit trousers Slim Fit",
    "link-href": "https://www2.hm.com/en_in/productpage.0761501016.html",
    "name": "Linen suit trousers Slim Fit",
    "description": "Ankle-length suit trousers in airy linen with a hook-and-eye fastening and zip fly. Side pockets, welt back pockets and tapered legs with creases. Slim Fit – a fit that is close-fitting at the thighs, knees and ankles to create a fitted silhouette.",
    "review_count": null,
    "details": "Details\n\t\n\t\tSizeWaist: Circumference: 93.5 cm (Size 52L)Inside leg: Length: 77.0 cm (Size 52L)LengthAnkle lengthWaist RiseRegular waistFitSlim fitStyleSuit trousersCompositionLinen 100%Pocket lining: Polyester 80%, Cotton 20%Care instructionsMachine wash at 30°MaterialLinenDescriptionDark greenSolid colourConceptH&M MANNice to knowPremium SelectionPrice (MRP)Rs. 2,299 incl. of all taxesCountry of productionMyanmarCommon generic nameTrousersNet quantity1 NMarketed or imported byH&M Hennes & Mauritz Retail Pvt. Ltd. A-wing, D-3, 2nd Floor District Centre Saket New Delhi -110017 IndiaDate of import03-2021Date of manufactureN/AManufactured byN/ACustomer serviceIn case of consumer complaint, write to H&M Hennes & Mauritz Retail PVT. Ltd, A Wing, D3, 2nd Floor, District Center, Saket, New Delhi 110017, India or call Telephone: 0008000501633. For online and store complaints email customerservice.in@hm.com.DisclaimerThis information is based on sample of the product displayed on website. There may be change in the information on label attached to the product delivered to the customer due to size chosen, date of import, name of manufacturer (in case of manufacturing in India), country of manufacture, etc. The exact detail relevant to the product delivered to the customer will reflect in the label attached to the product so deliveredArt. No.0761501016",
    "img1-src": "//lp2.hm.com/hmgoepprod?set=quality%5B79%5D%2Csource%5B%2Fb9%2Fc1%2Fb9c14836e94eb6d353d3596ff094fd35905ed2e4.jpg%5D%2Corigin%5Bdam%5D%2Ccategory%5Bmen_blazerssuits_trousers%5D%2Ctype%5BLOOKBOOK%5D%2Cres%5Bm%5D%2Chmver%5B1%5D&call=url[file:/product/main]",
    "img2-src": "//lp2.hm.com/hmgoepprod?set=quality%5B79%5D%2Csource%5B%2F7c%2F9c%2F7c9c6354c5a6b9c59c40072451aa2b1e0fb88550.jpg%5D%2Corigin%5Bdam%5D%2Ccategory%5Bmen_blazerssuits_trousers%5D%2Ctype%5BLOOKBOOK%5D%2Cres%5Bm%5D%2Chmver%5B1%5D&call=url[file:/product/main]",
    "style": "Suit trousers",
    "generic name": "Trousers",
    "colors": "Dark green",
    "descript": "Pocket lining: Polyester 80%, Cotton 20%",
    "item__price": "Rs. 2,299",
    "Fit": "Slim fit",
    "Composition": "Linen 100%Pocket lining: Polyester 80%, Cotton 20%"
  },
  {
    "web-scraper-order": "1629124408-72",
    "web-scraper-start-url": "https://www2.hm.com/en_in/men/shop-by-product/trousers.html",
    "link": "Regular Fit Cargo joggers",
    "link-href": "https://www2.hm.com/en_in/productpage.0966284003.html",
    "name": "Regular Fit Cargo joggers",
    "description": "Joggers in stretch nylon with covered elastication at the waist and a zip fly and button. Side, back and leg pockets with a concealed zip. Shaping seams at the knees and a concealed, elasticated drawstring at the hems. Regular Fit – a classic fit with good room for movement over the thighs and knees to create a comfortable, straight silhouette.",
    "review_count": null,
    "details": "Details\n\t\n\t\tLengthLongWaist RiseRegular waistFitRegular fitStyleCargoJoggersCompositionShell: Polyamide 89%, Elastane 11%Pocket lining: Polyester 100%Care instructionsMachine wash at 40°DescriptionBlackSolid colourConceptDIVIDEDPrice (MRP)Rs. 2,299 incl. of all taxesCountry of productionChinaCommon generic nameTrousersNet quantity1 NMarketed or imported byH&M Hennes & Mauritz Retail Pvt. Ltd. A-wing, D-3, 2nd Floor District Centre Saket New Delhi -110017 IndiaDate of import05-2021Date of manufactureN/AManufactured byN/ACustomer serviceIn case of consumer complaint, write to H&M Hennes & Mauritz Retail PVT. Ltd, A Wing, D3, 2nd Floor, District Center, Saket, New Delhi 110017, India or call Telephone: 0008000501633. For online and store complaints email customerservice.in@hm.com.DisclaimerThis information is based on sample of the product displayed on website. There may be change in the information on label attached to the product delivered to the customer due to size chosen, date of import, name of manufacturer (in case of manufacturing in India), country of manufacture, etc. The exact detail relevant to the product delivered to the customer will reflect in the label attached to the product so deliveredArt. No.0966284003",
    "img1-src": "//lp2.hm.com/hmgoepprod?set=quality%5B79%5D%2Csource%5B%2F70%2F23%2F70236bacb1736eeb081300072356efd348775831.jpg%5D%2Corigin%5Bdam%5D%2Ccategory%5B%5D%2Ctype%5BLOOKBOOK%5D%2Cres%5Bm%5D%2Chmver%5B1%5D&call=url[file:/product/main]",
    "img2-src": "//lp2.hm.com/hmgoepprod?set=quality%5B79%5D%2Csource%5B%2F9c%2F05%2F9c05aceff32707c37457fff1dea4eea33db43904.jpg%5D%2Corigin%5Bdam%5D%2Ccategory%5B%5D%2Ctype%5BLOOKBOOK%5D%2Cres%5Bm%5D%2Chmver%5B1%5D&call=url[file:/product/main]",
    "style": "Cargo",
    "generic name": "Trousers",
    "colors": "Black",
    "descript": null,
    "item__price": "Rs. 2,299",
    "Fit": "Regular fit",
    "Composition": "Shell: Polyamide 89%, Elastane 11%Pocket lining: Polyester 100%"
  },
  {
    "web-scraper-order": "1629124445-83",
    "web-scraper-start-url": "https://www2.hm.com/en_in/men/shop-by-product/trousers.html",
    "link": "Cargo joggers",
    "link-href": "https://www2.hm.com/en_in/productpage.1002227002.html",
    "name": "Cargo joggers",
    "description": "Joggers in a cotton weave with covered elastication and a drawstring at the waist, diagonal side pockets and flap back and leg pockets with concealed press-studs. Tapered legs with seams and darts at the knees and covered elastication at the hems.",
    "review_count": null,
    "details": "Details\n\t\n\t\tSizeInside leg: Length: 75.0 cm (Size L/L)LengthLongWaist RiseRegular waistStyleCargoTaperedJoggersCompositionPocket lining: Cotton 100%Shell: Cotton 98%, Elastane 2%Care instructionsMachine wash at 40°MaterialCottonDescriptionKhaki greenSolid colourNice to knowConsciousPrice (MRP)Rs. 2,699 incl. of all taxesCountry of productionBangladeshCommon generic nameTrousersNet quantity1 NMarketed or imported byH&M Hennes & Mauritz Retail Pvt. Ltd. A-wing, D-3, 2nd Floor District Centre Saket New Delhi -110017 IndiaDate of import07-2021Date of manufactureN/AManufactured byN/ACustomer serviceIn case of consumer complaint, write to H&M Hennes & Mauritz Retail PVT. Ltd, A Wing, D3, 2nd Floor, District Center, Saket, New Delhi 110017, India or call Telephone: 0008000501633. For online and store complaints email customerservice.in@hm.com.DisclaimerThis information is based on sample of the product displayed on website. There may be change in the information on label attached to the product delivered to the customer due to size chosen, date of import, name of manufacturer (in case of manufacturing in India), country of manufacture, etc. The exact detail relevant to the product delivered to the customer will reflect in the label attached to the product so deliveredArt. No.1002227002",
    "img1-src": "//lp2.hm.com/hmgoepprod?set=quality%5B79%5D%2Csource%5B%2F58%2F60%2F586011b8cf1f60c47bd7dbc2365dc49b7be12872.jpg%5D%2Corigin%5Bdam%5D%2Ccategory%5B%5D%2Ctype%5BLOOKBOOK%5D%2Cres%5Bm%5D%2Chmver%5B1%5D&call=url[file:/product/main]",
    "img2-src": "//lp2.hm.com/hmgoepprod?set=quality%5B79%5D%2Csource%5B%2F13%2F96%2F13964b7f564dfc4bb6e8b1effdee878ab5f9023e.jpg%5D%2Corigin%5Bdam%5D%2Ccategory%5B%5D%2Ctype%5BLOOKBOOK%5D%2Cres%5Bm%5D%2Chmver%5B1%5D&call=url[file:/product/main]",
    "style": "Cargo",
    "generic name": "Trousers",
    "colors": "Khaki green",
    "descript": null,
    "item__price": "Rs. 2,699",
    "Fit": null,
    "Composition": "Pocket lining: Cotton 100%Shell: Cotton 98%, Elastane 2%"
  },
  {
    "web-scraper-order": "1629124340-51",
    "web-scraper-start-url": "https://www2.hm.com/en_in/men/shop-by-product/trousers.html",
    "link": "2-pack sweatpants",
    "link-href": "https://www2.hm.com/en_in/productpage.0898045001.html",
    "name": "2-pack sweatpants",
    "description": "Trousers in sweatshirt fabric made from a cotton blend with an elasticated, drawstring waist, pockets in the side seams and ribbed hems. Soft brushed inside.",
    "review_count": null,
    "details": "Details\n\t\n\t\tPieces2LengthLongWaist RiseRegular waistFitRegular fitStyleSweatpantsCompositionPocket lining: Cotton 100%Shell: Cotton 60%, Polyester 40%DescriptionBlack/Grey marlSolid colourConceptBASICSPrice (MRP)Rs. 2,299 incl. of all taxesCountry of productionBangladeshCommon generic nameTrousersNet quantity2 NMarketed or imported byH&M Hennes & Mauritz Retail Pvt. Ltd. A-wing, D-3, 2nd Floor District Centre Saket New Delhi -110017 IndiaDate of import02-2021Date of manufactureN/AManufactured byN/ACustomer serviceIn case of consumer complaint, write to H&M Hennes & Mauritz Retail PVT. Ltd, A Wing, D3, 2nd Floor, District Center, Saket, New Delhi 110017, India or call Telephone: 0008000501633. For online and store complaints email customerservice.in@hm.com.DisclaimerThis information is based on sample of the product displayed on website. There may be change in the information on label attached to the product delivered to the customer due to size chosen, date of import, name of manufacturer (in case of manufacturing in India), country of manufacture, etc. The exact detail relevant to the product delivered to the customer will reflect in the label attached to the product so deliveredArt. No.0898045001",
    "img1-src": "//lp2.hm.com/hmgoepprod?set=quality%5B79%5D%2Csource%5B%2Fa5%2Fa7%2Fa5a796c2024e1f5177b1fa5e3f05c9c6580d62c0.jpg%5D%2Corigin%5Bdam%5D%2Ccategory%5Bmen_trousers_trousers_regular_all%5D%2Ctype%5BDESCRIPTIVESTILLLIFE%5D%2Cres%5Bm%5D%2Chmver%5B1%5D&call=url[file:/product/main]",
    "img2-src": "//lp2.hm.com/hmgoepprod?set=quality%5B79%5D%2Csource%5B%2Ff0%2Fec%2Ff0ec0c118cd6b7bcfd7b98a10b7ffdcbee9f6ff0.jpg%5D%2Corigin%5Bdam%5D%2Ccategory%5Bmen_trousers_trousers_regular_all%5D%2Ctype%5BDESCRIPTIVEDETAIL%5D%2Cres%5Bm%5D%2Chmver%5B1%5D&call=url[file:/product/main]",
    "style": "Sweatpants",
    "generic name": "Trousers",
    "colors": "Black/Grey marl",
    "descript": "Shell: Cotton 60%, Polyester 40%",
    "item__price": "Rs. 2,299",
    "Fit": "Regular fit",
    "Composition": "Pocket lining: Cotton 100%Shell: Cotton 60%, Polyester 40%"
  },
  {
    "web-scraper-order": "1629124388-66",
    "web-scraper-start-url": "https://www2.hm.com/en_in/men/shop-by-product/trousers.html",
    "link": "Suit trousers Slim Fit",
    "link-href": "https://www2.hm.com/en_in/productpage.0714026001.html",
    "name": "Suit trousers Slim Fit",
    "description": "Suit trousers in woven fabric with a concealed hook-and-eye fastening and zip fly. Side pockets, jetted back pockets and legs with creases. Slim Fit – a fit that is close-fitting at the thighs, knees and ankles to create a fitted silhouette.",
    "review_count": "(97)",
    "details": "Details\n\t\n\t\tLengthLongFitSlim fitStyleSuit trousersCompositionPolyester 68%, Viscose 31%, Elastane 1%Care instructionsMachine wash at 30°DescriptionBlackSolid colourConceptH&M MANPrice (MRP)Rs. 2,299 incl. of all taxesCountry of productionBangladeshCommon generic nameTrousersSize: 42LWidth: 76 cmLength: 79 cmSize: 44LWidth: 79 cmLength: 80 cmSize: 46LWidth: 83 cmLength: 80 cmSize: 48LWidth: 87 cmLength: 81 cmSize: 50LWidth: 90 cmLength: 81 cmSize: 52LWidth: 94 cmLength: 82 cmSize: 54LWidth: 97 cmLength: 82 cmNet quantity1 NMarketed or imported byH&M Hennes & Mauritz Retail Pvt. Ltd. A-wing, D-3, 2nd Floor District Centre Saket New Delhi -110017 IndiaDate of import06-2021Date of manufactureN/AManufactured byN/ACustomer serviceIn case of consumer complaint, write to H&M Hennes & Mauritz Retail PVT. Ltd, A Wing, D3, 2nd Floor, District Center, Saket, New Delhi 110017, India or call Telephone: 0008000501633. For online and store complaints email customerservice.in@hm.com.DisclaimerThis information is based on sample of the product displayed on website. There may be change in the information on label attached to the product delivered to the customer due to size chosen, date of import, name of manufacturer (in case of manufacturing in India), country of manufacture, etc. The exact detail relevant to the product delivered to the customer will reflect in the label attached to the product so deliveredArt. No.0714026001",
    "img1-src": "//lp2.hm.com/hmgoepprod?set=quality%5B79%5D%2Csource%5B%2F07%2Fdb%2F07db65015874d40e0b522905a5b06c0c01efd743.jpg%5D%2Corigin%5Bdam%5D%2Ccategory%5Bmen_trousers_dressed%5D%2Ctype%5BLOOKBOOK%5D%2Cres%5Bm%5D%2Chmver%5B1%5D&call=url[file:/product/main]",
    "img2-src": "//lp2.hm.com/hmgoepprod?set=quality%5B79%5D%2Csource%5B%2F44%2F35%2F4435187bd1fffcec706d329976fccacfcd3c90ae.jpg%5D%2Corigin%5Bdam%5D%2Ccategory%5Bmen_trousers_dressed%5D%2Ctype%5BLOOKBOOK%5D%2Cres%5Bm%5D%2Chmver%5B1%5D&call=url[file:/product/main]",
    "style": "Suit trousers",
    "generic name": "Trousers",
    "colors": "Black",
    "descript": "Solid colour",
    "item__price": "Rs. 2,299",
    "Fit": "Slim fit",
    "Composition": "Polyester 68%, Viscose 31%, Elastane 1%"
  },
  {
    "web-scraper-order": "1629124533-109",
    "web-scraper-start-url": "https://www2.hm.com/en_in/men/shop-by-product/trousers.html",
    "link": "Slim Fit Cropped trousers",
    "link-href": "https://www2.hm.com/en_in/productpage.0991309006.html",
    "name": "Slim Fit Cropped trousers",
    "description": "Cropped trousers in woven fabric with a concealed hook-and-eye fastening and button in the waistband and a zip fly. Side pockets, welt back pockets with a button, and legs with creases. Slim Fit – a fit that is close-fitting at the thighs and knees to create a fitted silhouette.",
    "review_count": "(9)",
    "details": "Details\n\t\n\t\tLengthAnkle lengthWaist RiseRegular waistFitSlim fitStyleCigarette trousersCompositionPolyester 82%, Viscose 16%, Elastane 2%Care instructionsMachine wash at 30°DescriptionDark greySolid colourConceptH&M MANNice to knowConsciousPrice (MRP)Rs. 1,499 incl. of all taxesCountry of productionChinaCommon generic nameTrousersNet quantity1 NMarketed or imported byH&M Hennes & Mauritz Retail Pvt. Ltd. A-wing, D-3, 2nd Floor District Centre Saket New Delhi -110017 IndiaDate of import05-2021Date of manufactureN/AManufactured byN/ACustomer serviceIn case of consumer complaint, write to H&M Hennes & Mauritz Retail PVT. Ltd, A Wing, D3, 2nd Floor, District Center, Saket, New Delhi 110017, India or call Telephone: 0008000501633. For online and store complaints email customerservice.in@hm.com.DisclaimerThis information is based on sample of the product displayed on website. There may be change in the information on label attached to the product delivered to the customer due to size chosen, date of import, name of manufacturer (in case of manufacturing in India), country of manufacture, etc. The exact detail relevant to the product delivered to the customer will reflect in the label attached to the product so deliveredArt. No.0991309006",
    "img1-src": "//lp2.hm.com/hmgoepprod?set=quality%5B79%5D%2Csource%5B%2Fdf%2F4e%2Fdf4e9233cfd03afb6350a7658d7f89d1985d3c83.jpg%5D%2Corigin%5Bdam%5D%2Ccategory%5B%5D%2Ctype%5BLOOKBOOK%5D%2Cres%5Bm%5D%2Chmver%5B1%5D&call=url[file:/product/main]",
    "img2-src": "//lp2.hm.com/hmgoepprod?set=quality%5B79%5D%2Csource%5B%2F4c%2F15%2F4c15307a58cf63344edb9d04bb098a3a1ac8270f.jpg%5D%2Corigin%5Bdam%5D%2Ccategory%5B%5D%2Ctype%5BLOOKBOOK%5D%2Cres%5Bm%5D%2Chmver%5B1%5D&call=url[file:/product/main]",
    "style": "Cigarette trousers",
    "generic name": "Trousers",
    "colors": "Dark grey",
    "descript": null,
    "item__price": "Rs. 1,499",
    "Fit": "Slim fit",
    "Composition": "Polyester 82%, Viscose 16%, Elastane 2%"
  },
  {
    "web-scraper-order": "1629124321-45",
    "web-scraper-start-url": "https://www2.hm.com/en_in/men/shop-by-product/trousers.html",
    "link": "Sports trousers Muscle Fit",
    "link-href": "https://www2.hm.com/en_in/productpage.0938220002.html",
    "name": "Sports trousers Muscle Fit",
    "description": "Sports trousers in softly draping stretch jersey with an elasticated, drawstring waist and a slightly lower crotch with a ventilating mesh section. Zipped side pockets for safe storage of valuables.",
    "review_count": null,
    "details": "Details\n\t\n\t\tLengthLongWaist RiseRegular waistFitMuscle fitCompositionPocket lining: Polyester 100%Shell: Cotton 64%, Polyester 31%, Elastane 5%Care instructionsMachine wash at 40°Sports activityTrainingDescriptionLight grey marlSolid colourPrice (MRP)Rs. 1,999 incl. of all taxesCountry of productionChinaCommon generic nameTrousersNet quantity1 NMarketed or imported byH&M Hennes & Mauritz Retail Pvt. Ltd. A-wing, D-3, 2nd Floor District Centre Saket New Delhi -110017 IndiaDate of import12-2020Date of manufactureN/AManufactured byN/ACustomer serviceIn case of consumer complaint, write to H&M Hennes & Mauritz Retail PVT. Ltd, A Wing, D3, 2nd Floor, District Center, Saket, New Delhi 110017, India or call Telephone: 0008000501633. For online and store complaints email customerservice.in@hm.com.DisclaimerThis information is based on sample of the product displayed on website. There may be change in the information on label attached to the product delivered to the customer due to size chosen, date of import, name of manufacturer (in case of manufacturing in India), country of manufacture, etc. The exact detail relevant to the product delivered to the customer will reflect in the label attached to the product so deliveredArt. No.0938220002",
    "img1-src": "//lp2.hm.com/hmgoepprod?set=quality%5B79%5D%2Csource%5B%2F7b%2Fa5%2F7ba56d1d0722763dda28da42b41f69344aec1375.jpg%5D%2Corigin%5Bdam%5D%2Ccategory%5B%5D%2Ctype%5BDESCRIPTIVESTILLLIFE%5D%2Cres%5Bm%5D%2Chmver%5B2%5D&call=url[file:/product/main]",
    "img2-src": "//lp2.hm.com/hmgoepprod?set=quality%5B79%5D%2Csource%5B%2F96%2F25%2F962578f6991d0355f56ab12978effc89b15b3cc4.jpg%5D%2Corigin%5Bdam%5D%2Ccategory%5B%5D%2Ctype%5BDESCRIPTIVEDETAIL%5D%2Cres%5Bm%5D%2Chmver%5B2%5D&call=url[file:/product/main]",
    "style": null,
    "generic name": "Trousers",
    "colors": "Light grey marl",
    "descript": null,
    "item__price": "Rs. 1,999",
    "Fit": "Muscle fit",
    "Composition": "Pocket lining: Polyester 100%Shell: Cotton 64%, Polyester 31%, Elastane 5%"
  },
  {
    "web-scraper-order": "1629124499-99",
    "web-scraper-start-url": "https://www2.hm.com/en_in/men/shop-by-product/trousers.html",
    "link": "Regular Fit Twill joggers",
    "link-href": "https://www2.hm.com/en_in/productpage.0975244002.html",
    "name": "Regular Fit Twill joggers",
    "description": "Joggers in stretch cotton twill with covered elastication and a drawstring at the waist and a fake fly. Side pockets, back pockets with a button and covered elastication at the hems. Regular Fit – a classic fit with good room for movement over the thighs and knees to create a comfortable, straight silhouette.",
    "review_count": null,
    "details": "Details\n\t\n\t\tSizeInside leg: Length: 76.0 cm (Size L/L)LengthLongWaist RiseRegular waistFitRegular fitStyleJoggersCompositionPocket lining: Cotton 100%Shell: Cotton 98%, Elastane 2%Care instructionsMachine wash at 40°MaterialCottonDescriptionBlackSolid colourNice to knowConsciousPrice (MRP)Rs. 1,499 incl. of all taxesCountry of productionBangladeshCommon generic nameTrousersNet quantity1 NMarketed or imported byH&M Hennes & Mauritz Retail Pvt. Ltd. A-wing, D-3, 2nd Floor District Centre Saket New Delhi -110017 IndiaDate of import06-2021Date of manufactureN/AManufactured byN/ACustomer serviceIn case of consumer complaint, write to H&M Hennes & Mauritz Retail PVT. Ltd, A Wing, D3, 2nd Floor, District Center, Saket, New Delhi 110017, India or call Telephone: 0008000501633. For online and store complaints email customerservice.in@hm.com.DisclaimerThis information is based on sample of the product displayed on website. There may be change in the information on label attached to the product delivered to the customer due to size chosen, date of import, name of manufacturer (in case of manufacturing in India), country of manufacture, etc. The exact detail relevant to the product delivered to the customer will reflect in the label attached to the product so deliveredArt. No.0975244002",
    "img1-src": "//lp2.hm.com/hmgoepprod?set=quality%5B79%5D%2Csource%5B%2Fc2%2F32%2Fc232171fa32fca755959d0507284f4d8c0d837e3.jpg%5D%2Corigin%5Bdam%5D%2Ccategory%5B%5D%2Ctype%5BLOOKBOOK%5D%2Cres%5Bm%5D%2Chmver%5B1%5D&call=url[file:/product/main]",
    "img2-src": "//lp2.hm.com/hmgoepprod?set=quality%5B79%5D%2Csource%5B%2F39%2F4d%2F394d71a800a7068a9e0ac8c323c59ddcfd61fba3.jpg%5D%2Corigin%5Bdam%5D%2Ccategory%5B%5D%2Ctype%5BLOOKBOOK%5D%2Cres%5Bm%5D%2Chmver%5B1%5D&call=url[file:/product/main]",
    "style": "Joggers",
    "generic name": "Trousers",
    "colors": "Black",
    "descript": "Shell: Cotton 98%, Elastane 2%",
    "item__price": "Rs. 1,499",
    "Fit": "Regular fit",
    "Composition": "Pocket lining: Cotton 100%Shell: Cotton 98%, Elastane 2%"
  },
  {
    "web-scraper-order": "1629124465-89",
    "web-scraper-start-url": "https://www2.hm.com/en_in/men/shop-by-product/trousers.html",
    "link": "Linen suit trousers Slim Fit",
    "link-href": "https://www2.hm.com/en_in/productpage.0761501012.html",
    "name": "Linen suit trousers Slim Fit",
    "description": "Ankle-length suit trousers in airy linen with a hook-and-eye fastening and zip fly. Side pockets, welt back pockets and tapered legs with creases. Slim Fit – a fit that is close-fitting at the thighs, knees and ankles to create a fitted silhouette.",
    "review_count": null,
    "details": "Details\n\t\n\t\tSizeWaist: Circumference: 93.5 cm (Size 52L)Inside leg: Length: 77.0 cm (Size 52L)LengthAnkle lengthWaist RiseRegular waistFitSlim fitStyleSuit trousersCompositionLinen 100%Pocket lining: Polyester 80%, Cotton 20%Care instructionsMachine wash at 30°MaterialLinenDescriptionSteel blueSolid colourConceptH&M MANNice to knowPremium SelectionPrice (MRP)Rs. 2,299 incl. of all taxesCountry of productionMyanmarCommon generic nameTrousersNet quantity1 NMarketed or imported byH&M Hennes & Mauritz Retail Pvt. Ltd. A-wing, D-3, 2nd Floor District Centre Saket New Delhi -110017 IndiaDate of import03-2021Date of manufactureN/AManufactured byN/ACustomer serviceIn case of consumer complaint, write to H&M Hennes & Mauritz Retail PVT. Ltd, A Wing, D3, 2nd Floor, District Center, Saket, New Delhi 110017, India or call Telephone: 0008000501633. For online and store complaints email customerservice.in@hm.com.DisclaimerThis information is based on sample of the product displayed on website. There may be change in the information on label attached to the product delivered to the customer due to size chosen, date of import, name of manufacturer (in case of manufacturing in India), country of manufacture, etc. The exact detail relevant to the product delivered to the customer will reflect in the label attached to the product so deliveredArt. No.0761501012",
    "img1-src": "//lp2.hm.com/hmgoepprod?set=quality%5B79%5D%2Csource%5B%2F80%2F67%2F8067ac0e0829d0c155f4e6d5038058da737f077c.jpg%5D%2Corigin%5Bdam%5D%2Ccategory%5Bmen_blazerssuits_trousers%5D%2Ctype%5BLOOKBOOK%5D%2Cres%5Bm%5D%2Chmver%5B1%5D&call=url[file:/product/main]",
    "img2-src": "//lp2.hm.com/hmgoepprod?set=quality%5B79%5D%2Csource%5B%2F70%2Fe2%2F70e29d498f04ddfd0c37a4c45cb373c79c752c2f.jpg%5D%2Corigin%5Bdam%5D%2Ccategory%5Bmen_blazerssuits_trousers%5D%2Ctype%5BLOOKBOOK%5D%2Cres%5Bm%5D%2Chmver%5B1%5D&call=url[file:/product/main]",
    "style": "Suit trousers",
    "generic name": "Trousers",
    "colors": "Steel blue",
    "descript": "Pocket lining: Polyester 80%, Cotton 20%",
    "item__price": "Rs. 2,299",
    "Fit": "Slim fit",
    "Composition": "Linen 100%Pocket lining: Polyester 80%, Cotton 20%"
  },
  {
    "web-scraper-order": "1629124502-100",
    "web-scraper-start-url": "https://www2.hm.com/en_in/men/shop-by-product/trousers.html",
    "link": "Cotton joggers",
    "link-href": "https://www2.hm.com/en_in/productpage.0967542002.html",
    "name": "Cotton joggers",
    "description": "Blank Staples is a streetwear collection of minimalistic pieces that are the perfect canvas for your personal style and creativity. These pared-back joggers are made from heavy, 460 g organic cotton sweatshirt fabric for a premium handfeel. They have covered elastication at the waist and hems, jersey-lined pockets in the side seams and an open back pocket.",
    "review_count": null,
    "details": "Details\n\t\n\t\tLengthLongWaist RiseRegular waistStyleJoggersCompositionCotton 100%Care instructionsMachine wash at 40°MaterialCottonDescriptionBlackSolid colourConceptBASICSCollectionBlank StaplesPrice (MRP)Rs. 2,299 incl. of all taxesCountry of productionBangladeshCommon generic nameTrousersNet quantity1 NMarketed or imported byH&M Hennes & Mauritz Retail Pvt. Ltd. A-wing, D-3, 2nd Floor District Centre Saket New Delhi -110017 IndiaDate of import08-2021Date of manufactureN/AManufactured byN/ACustomer serviceIn case of consumer complaint, write to H&M Hennes & Mauritz Retail PVT. Ltd, A Wing, D3, 2nd Floor, District Center, Saket, New Delhi 110017, India or call Telephone: 0008000501633. For online and store complaints email customerservice.in@hm.com.DisclaimerThis information is based on sample of the product displayed on website. There may be change in the information on label attached to the product delivered to the customer due to size chosen, date of import, name of manufacturer (in case of manufacturing in India), country of manufacture, etc. The exact detail relevant to the product delivered to the customer will reflect in the label attached to the product so deliveredArt. No.0967542002",
    "img1-src": "//lp2.hm.com/hmgoepprod?set=quality%5B79%5D%2Csource%5B%2Fa8%2F3a%2Fa83ade25e20c5c1d846bfdf005189f3421d39ec9.jpg%5D%2Corigin%5Bdam%5D%2Ccategory%5B%5D%2Ctype%5BDESCRIPTIVESTILLLIFE%5D%2Cres%5Bm%5D%2Chmver%5B2%5D&call=url[file:/product/main]",
    "img2-src": "//lp2.hm.com/hmgoepprod?set=quality%5B79%5D%2Csource%5B%2F32%2F3b%2F323b189800dcc4a001cd108ce392d21142f02437.jpg%5D%2Corigin%5Bdam%5D%2Ccategory%5B%5D%2Ctype%5BDESCRIPTIVEDETAIL%5D%2Cres%5Bm%5D%2Chmver%5B2%5D&call=url[file:/product/main]",
    "style": "Joggers",
    "generic name": "Trousers",
    "colors": "Black",
    "descript": null,
    "item__price": "Rs. 2,299",
    "Fit": null,
    "Composition": "Cotton 100%"
  },
  {
    "web-scraper-order": "1629124348-54",
    "web-scraper-start-url": "https://www2.hm.com/en_in/men/shop-by-product/trousers.html",
    "link": "Suit trousers Skinny Fit",
    "link-href": "https://www2.hm.com/en_in/productpage.0714032029.html",
    "name": "Suit trousers Skinny Fit",
    "description": "Suit trousers in a stretch weave with a concealed hook-and-eye fastener and zip fly. Side pockets, welt back pockets and legs with creases. Skinny fit – a fit with slightly shorter legs that is close-fitting at the thighs, knees and ankles to create a completely fitted silhouette.",
    "review_count": null,
    "details": "Details\n\t\n\t\tLengthLongFitSkinny fitStyleSuit trousersCompositionPolyester 64%, Viscose 34%, Elastane 2%Pocket: Polyester 80%, Cotton 20%Care instructionsMachine wash at 30°DescriptionBeige/White/BlackCheckedConceptH&M MANNice to knowConsciousPrice (MRP)Rs. 2,299 incl. of all taxesCountry of productionBangladeshCommon generic nameTrousersNet quantity1 NMarketed or imported byH&M Hennes & Mauritz Retail Pvt. Ltd. A-wing, D-3, 2nd Floor District Centre Saket New Delhi -110017 IndiaDate of import06-2021Date of manufactureN/AManufactured byN/ACustomer serviceIn case of consumer complaint, write to H&M Hennes & Mauritz Retail PVT. Ltd, A Wing, D3, 2nd Floor, District Center, Saket, New Delhi 110017, India or call Telephone: 0008000501633. For online and store complaints email customerservice.in@hm.com.DisclaimerThis information is based on sample of the product displayed on website. There may be change in the information on label attached to the product delivered to the customer due to size chosen, date of import, name of manufacturer (in case of manufacturing in India), country of manufacture, etc. The exact detail relevant to the product delivered to the customer will reflect in the label attached to the product so deliveredArt. No.0714032029",
    "img1-src": "//lp2.hm.com/hmgoepprod?set=quality%5B79%5D%2Csource%5B%2Fe1%2F21%2Fe12187013c66c1e038cf654b08b7ff8c5eefd033.jpg%5D%2Corigin%5Bdam%5D%2Ccategory%5B%5D%2Ctype%5BLOOKBOOK%5D%2Cres%5Bm%5D%2Chmver%5B1%5D&call=url[file:/product/main]",
    "img2-src": "//lp2.hm.com/hmgoepprod?set=quality%5B79%5D%2Csource%5B%2Fe1%2F54%2Fe15498d0a992054c564bdd3a7908ea8634562bfc.jpg%5D%2Corigin%5Bdam%5D%2Ccategory%5B%5D%2Ctype%5BLOOKBOOK%5D%2Cres%5Bm%5D%2Chmver%5B1%5D&call=url[file:/product/main]",
    "style": "Suit trousers",
    "generic name": "Trousers",
    "colors": "Beige/White/Black",
    "descript": "Checked",
    "item__price": "Rs. 2,299",
    "Fit": "Skinny fit",
    "Composition": "Polyester 64%, Viscose 34%, Elastane 2%Pocket: Polyester 80%, Cotton 20%"
  },
  {
    "web-scraper-order": "1629124439-81",
    "web-scraper-start-url": "https://www2.hm.com/en_in/men/shop-by-product/trousers.html",
    "link": "Suit trousers Slim Fit",
    "link-href": "https://www2.hm.com/en_in/productpage.0714026029.html",
    "name": "Suit trousers Slim Fit",
    "description": "Suit trousers in woven fabric with a concealed hook-and-eye fastening and zip fly. Side pockets, jetted back pockets and legs with creases. Slim Fit – a fit that is close-fitting at the thighs, knees and ankles to create a fitted silhouette.",
    "review_count": null,
    "details": "Details\n\t\n\t\tLengthLongFitSlim fitStyleSuit trousersCompositionShell: Polyester 83%, Viscose 14%, Elastane 3%Pocket lining: Polyester 80%, Cotton 20%Care instructionsMachine wash at 30°DescriptionDark greySolid colourConceptH&M MANNice to knowConsciousPrice (MRP)Rs. 2,299 incl. of all taxesCountry of productionMyanmarCommon generic nameTrousersNet quantity1 NMarketed or imported byH&M Hennes & Mauritz Retail Pvt. Ltd. A-wing, D-3, 2nd Floor District Centre Saket New Delhi -110017 IndiaDate of import08-2021Date of manufactureN/AManufactured byN/ACustomer serviceIn case of consumer complaint, write to H&M Hennes & Mauritz Retail PVT. Ltd, A Wing, D3, 2nd Floor, District Center, Saket, New Delhi 110017, India or call Telephone: 0008000501633. For online and store complaints email customerservice.in@hm.com.DisclaimerThis information is based on sample of the product displayed on website. There may be change in the information on label attached to the product delivered to the customer due to size chosen, date of import, name of manufacturer (in case of manufacturing in India), country of manufacture, etc. The exact detail relevant to the product delivered to the customer will reflect in the label attached to the product so deliveredArt. No.0714026029",
    "img1-src": "//lp2.hm.com/hmgoepprod?set=quality%5B79%5D%2Csource%5B%2Fe7%2F87%2Fe78752e783d3286ffc2f5566e1a5bd996e27046e.jpg%5D%2Corigin%5Bdam%5D%2Ccategory%5B%5D%2Ctype%5BLOOKBOOK%5D%2Cres%5Bm%5D%2Chmver%5B1%5D&call=url[file:/product/main]",
    "img2-src": "//lp2.hm.com/hmgoepprod?set=quality%5B79%5D%2Csource%5B%2F05%2Fd2%2F05d2e3a522f27155765b706a350c5f6cf3b919e0.jpg%5D%2Corigin%5Bdam%5D%2Ccategory%5B%5D%2Ctype%5BLOOKBOOK%5D%2Cres%5Bm%5D%2Chmver%5B1%5D&call=url[file:/product/main]",
    "style": "Suit trousers",
    "generic name": "Trousers",
    "colors": "Dark grey",
    "descript": "Solid colour",
    "item__price": "Rs. 2,299",
    "Fit": "Slim fit",
    "Composition": "Shell: Polyester 83%, Viscose 14%, Elastane 3%Pocket lining: Polyester 80%, Cotton 20%"
  },
  {
    "web-scraper-order": "1629124529-108",
    "web-scraper-start-url": "https://www2.hm.com/en_in/men/shop-by-product/trousers.html",
    "link": "Skinny Fit Cargo joggers",
    "link-href": "https://www2.hm.com/en_in/productpage.0997065003.html",
    "name": "Skinny Fit Cargo joggers",
    "description": "Joggers in cotton twill with an elasticated, drawstring waist, side pockets, and leg and back pockets with a flap and concealed press-studs. Tapered legs with seams at the knees and cuffed hems. Skinny Fit – a fit with slightly shorter legs that is close-fitting at the thighs, knees and ankles to create a completely fitted silhouette.",
    "review_count": null,
    "details": "Details\n\t\n\t\tSizeInside leg: Length: 76.5 cm (Size M/L)LengthLongWaist RiseRegular waistFitSkinny fitStyleCargoJoggersCompositionShell: Cotton 98%, Elastane 2%Pocket lining: Cotton 100%Care instructionsLine dryOnly non-chlorine bleach when neededMachine wash at 40°Medium ironCan be dry cleanedWash with similar coloursMaterialCottonDescriptionBeigeSolid colourPrice (MRP)Rs. 2,299 incl. of all taxesCountry of productionBangladeshCommon generic nameTrousersNet quantity1 NMarketed or imported byH&M Hennes & Mauritz Retail Pvt. Ltd. A-wing, D-3, 2nd Floor District Centre Saket New Delhi -110017 IndiaDate of import06-2021Date of manufactureN/AManufactured byN/ACustomer serviceIn case of consumer complaint, write to H&M Hennes & Mauritz Retail PVT. Ltd, A Wing, D3, 2nd Floor, District Center, Saket, New Delhi 110017, India or call Telephone: 0008000501633. For online and store complaints email customerservice.in@hm.com.DisclaimerThis information is based on sample of the product displayed on website. There may be change in the information on label attached to the product delivered to the customer due to size chosen, date of import, name of manufacturer (in case of manufacturing in India), country of manufacture, etc. The exact detail relevant to the product delivered to the customer will reflect in the label attached to the product so deliveredArt. No.0997065003",
    "img1-src": "//lp2.hm.com/hmgoepprod?set=quality%5B79%5D%2Csource%5B%2F99%2F21%2F992189e4e5b2cd35a8c70dd8871a588b8e4f344a.jpg%5D%2Corigin%5Bdam%5D%2Ccategory%5B%5D%2Ctype%5BLOOKBOOK%5D%2Cres%5Bm%5D%2Chmver%5B1%5D&call=url[file:/product/main]",
    "img2-src": "//lp2.hm.com/hmgoepprod?set=quality%5B79%5D%2Csource%5B%2Fa2%2Fd4%2Fa2d4c6ee536bd8efaa99829ee7f9b9c66823a057.jpg%5D%2Corigin%5Bdam%5D%2Ccategory%5B%5D%2Ctype%5BLOOKBOOK%5D%2Cres%5Bm%5D%2Chmver%5B1%5D&call=url[file:/product/main]",
    "style": "Cargo",
    "generic name": "Trousers",
    "colors": "Beige",
    "descript": "Pocket lining: Cotton 100%",
    "item__price": "Rs. 2,299",
    "Fit": "Skinny fit",
    "Composition": "Shell: Cotton 98%, Elastane 2%Pocket lining: Cotton 100%"
  },
  {
    "web-scraper-order": "1629124561-119",
    "web-scraper-start-url": "https://www2.hm.com/en_in/men/shop-by-product/trousers.html",
    "link": "Hybrid Regular Tapered Joggers",
    "link-href": "https://www2.hm.com/en_in/productpage.1013317001.html",
    "name": "Hybrid Regular Tapered Joggers",
    "description": "5-pocket joggers in stretch denim. Regular waist with covered elastication and a drawstring, and a zip fly with a button. Gently tapered legs with good room for movement over the thighs and knees, and covered elastication at the hems. Made using Lycra® Hybrid Technology for exceptional softness and comfort without compromising the authentic denim look.",
    "review_count": null,
    "details": "Details\n\t\n\t\tLengthLongWaist RiseRegular waistFitRegular fitStyleTaperedJoggersCompositionCotton 77%, Polyester 21%, Elastane 2%Care instructionsMachine wash at 40°MaterialDenimDescriptionLight denim blueConceptDENIMNice to knowConsciousPrice (MRP)Rs. 2,699 incl. of all taxesCountry of productionIndiaCommon generic nameTrousersNet quantity1 NDate of manufacture07-2021Manufactured byARVIND LIMITED\nNO. 26/2 AND 27/2,, KENCHENAHALLI VILLAGE,KENGERI HOBLI, MYSORE ROAD,, 560059, BANGALORECustomer serviceIn case of consumer complaint, write to H&M Hennes & Mauritz Retail PVT. Ltd, A Wing, D3, 2nd Floor, District Center, Saket, New Delhi 110017, India or call Telephone: 0008000501633. For online and store complaints email customerservice.in@hm.com.DisclaimerThis information is based on sample of the product displayed on website. There may be change in the information on label attached to the product delivered to the customer due to size chosen, date of import, name of manufacturer (in case of manufacturing in India), country of manufacture, etc. The exact detail relevant to the product delivered to the customer will reflect in the label attached to the product so deliveredArt. No.1013317001",
    "img1-src": "//lp2.hm.com/hmgoepprod?set=quality%5B79%5D%2Csource%5B%2Fda%2F8f%2Fda8f697b18f361d7226d09bacad42abbb3fba1be.jpg%5D%2Corigin%5Bdam%5D%2Ccategory%5B%5D%2Ctype%5BLOOKBOOK%5D%2Cres%5Bm%5D%2Chmver%5B1%5D&call=url[file:/product/main]",
    "img2-src": "//lp2.hm.com/hmgoepprod?set=quality%5B79%5D%2Csource%5B%2Fe9%2F61%2Fe961ccc4d44f4d2b82624339405e1d991d78d6e7.jpg%5D%2Corigin%5Bdam%5D%2Ccategory%5B%5D%2Ctype%5BLOOKBOOK%5D%2Cres%5Bm%5D%2Chmver%5B1%5D&call=url[file:/product/main]",
    "style": "Tapered",
    "generic name": "Trousers",
    "colors": "Light denim blue",
    "descript": null,
    "item__price": "Rs. 2,699",
    "Fit": "Regular fit",
    "Composition": "Cotton 77%, Polyester 21%, Elastane 2%"
  },
  {
    "web-scraper-order": "1629124612-135",
    "web-scraper-start-url": "https://www2.hm.com/en_in/men/shop-by-product/trousers.html",
    "link": "Twill trousers Slim Fit",
    "link-href": "https://www2.hm.com/en_in/productpage.0721390034.html",
    "name": "Twill trousers Slim Fit",
    "description": "5-pocket trousers in washed stretch twill with a regular waist and zip fly. Slim fit which is relaxed over the thighs and tapers from the knees down for a relaxed, well-tailored look.",
    "review_count": "(678)",
    "details": "Details\n\t\n\t\tLengthLongWaist RiseRegular waistFitSlim fitCompositionPocket: Cotton 100%Cotton 98%, Elastane 2%Care instructionsMachine wash at 40°MaterialCottonDescriptionBeigeSolid colourConceptH&M MANPrice (MRP)Rs. 1,499 incl. of all taxesCountry of productionBangladeshCommon generic nameTrousersNet quantity1 NMarketed or imported byH&M Hennes & Mauritz Retail Pvt. Ltd. A-wing, D-3, 2nd Floor District Centre Saket New Delhi -110017 IndiaDate of import05-2021Date of manufactureN/AManufactured byN/ACustomer serviceIn case of consumer complaint, write to H&M Hennes & Mauritz Retail PVT. Ltd, A Wing, D3, 2nd Floor, District Center, Saket, New Delhi 110017, India or call Telephone: 0008000501633. For online and store complaints email customerservice.in@hm.com.DisclaimerThis information is based on sample of the product displayed on website. There may be change in the information on label attached to the product delivered to the customer due to size chosen, date of import, name of manufacturer (in case of manufacturing in India), country of manufacture, etc. The exact detail relevant to the product delivered to the customer will reflect in the label attached to the product so deliveredArt. No.0721390034",
    "img1-src": "//lp2.hm.com/hmgoepprod?set=quality%5B79%5D%2Csource%5B%2Ffa%2F5a%2Ffa5aba624c9f9e19042a058808c6bd94f04b4f96.jpg%5D%2Corigin%5Bdam%5D%2Ccategory%5Bmen_trousers_trousers_slim_all%5D%2Ctype%5BLOOKBOOK%5D%2Cres%5Bm%5D%2Chmver%5B1%5D&call=url[file:/product/main]",
    "img2-src": "//lp2.hm.com/hmgoepprod?set=quality%5B79%5D%2Csource%5B%2Fc8%2F4e%2Fc84e4cdec915a34e3dc4ca7f131116c7818c8856.jpg%5D%2Corigin%5Bdam%5D%2Ccategory%5Bmen_trousers_trousers_slim_all%5D%2Ctype%5BLOOKBOOK%5D%2Cres%5Bm%5D%2Chmver%5B1%5D&call=url[file:/product/main]",
    "style": null,
    "generic name": "Trousers",
    "colors": "Beige",
    "descript": null,
    "item__price": "Rs. 1,499",
    "Fit": "Slim fit",
    "Composition": "Pocket: Cotton 100%Cotton 98%, Elastane 2%"
  },
  {
    "web-scraper-order": "1629124385-65",
    "web-scraper-start-url": "https://www2.hm.com/en_in/men/shop-by-product/trousers.html",
    "link": "Slim Fit Trousers",
    "link-href": "https://www2.hm.com/en_in/productpage.0991256002.html",
    "name": "Slim Fit Trousers",
    "description": "Crease-leg trousers in woven fabric with a concealed hook-and-eye fastening and button on the waistband and a zip fly. Diagonal side pockets and jetted back pockets with a button. Slim Fit – a fit that is close-fitting at the thighs and knees to create a fitted silhouette.",
    "review_count": null,
    "details": "Details\n\t\n\t\tLengthLongWaist RiseRegular waistFitSlim fitStyleCigarette trousersCompositionPolyester 67%, Viscose 29%, Elastane 4%Care instructionsMachine wash at 30°DescriptionBlack/WhiteCheckedConceptH&M MANNice to knowConsciousPrice (MRP)Rs. 2,299 incl. of all taxesCountry of productionBangladeshCommon generic nameTrousersNet quantity1 NMarketed or imported byH&M Hennes & Mauritz Retail Pvt. Ltd. A-wing, D-3, 2nd Floor District Centre Saket New Delhi -110017 IndiaDate of import08-2021Date of manufactureN/AManufactured byN/ACustomer serviceIn case of consumer complaint, write to H&M Hennes & Mauritz Retail PVT. Ltd, A Wing, D3, 2nd Floor, District Center, Saket, New Delhi 110017, India or call Telephone: 0008000501633. For online and store complaints email customerservice.in@hm.com.DisclaimerThis information is based on sample of the product displayed on website. There may be change in the information on label attached to the product delivered to the customer due to size chosen, date of import, name of manufacturer (in case of manufacturing in India), country of manufacture, etc. The exact detail relevant to the product delivered to the customer will reflect in the label attached to the product so deliveredArt. No.0991256002",
    "img1-src": "//lp2.hm.com/hmgoepprod?set=quality%5B79%5D%2Csource%5B%2Fdd%2Fb0%2Fddb016b3b6b8c4c1964e27c7ec944b9504880ea2.jpg%5D%2Corigin%5Bdam%5D%2Ccategory%5B%5D%2Ctype%5BLOOKBOOK%5D%2Cres%5Bm%5D%2Chmver%5B1%5D&call=url[file:/product/main]",
    "img2-src": "//lp2.hm.com/hmgoepprod?set=quality%5B79%5D%2Csource%5B%2F13%2Ffb%2F13fbb63dc1aa3c4b4b85a02352e35bb10afd14d7.jpg%5D%2Corigin%5Bdam%5D%2Ccategory%5B%5D%2Ctype%5BLOOKBOOK%5D%2Cres%5Bm%5D%2Chmver%5B1%5D&call=url[file:/product/main]",
    "style": "Cigarette trousers",
    "generic name": "Trousers",
    "colors": "Black/White",
    "descript": null,
    "item__price": "Rs. 2,299",
    "Fit": "Slim fit",
    "Composition": "Polyester 67%, Viscose 29%, Elastane 4%"
  },
  {
    "web-scraper-order": "1629124361-58",
    "web-scraper-start-url": "https://www2.hm.com/en_in/men/shop-by-product/trousers.html",
    "link": "Suit trousers Slim Fit",
    "link-href": "https://www2.hm.com/en_in/productpage.0714026025.html",
    "name": "Suit trousers Slim Fit",
    "description": "Suit trousers in woven fabric with a concealed hook-and-eye fastening and zip fly. Side pockets, jetted back pockets and legs with creases. Slim Fit – a fit that is close-fitting at the thighs, knees and ankles to create a fitted silhouette.",
    "review_count": null,
    "details": "Details\n\t\n\t\tLengthLongFitSlim fitStyleSuit trousersCompositionShell: Polyester 72%, Viscose 27%, Elastane 1%Pocket lining: Polyester 82%, Cotton 18%Care instructionsMachine wash at 30°DescriptionSteel blueSolid colourConceptH&M MANPrice (MRP)Rs. 2,299 incl. of all taxesCountry of productionBangladeshCommon generic nameTrousersNet quantity1 NMarketed or imported byH&M Hennes & Mauritz Retail Pvt. Ltd. A-wing, D-3, 2nd Floor District Centre Saket New Delhi -110017 IndiaDate of import06-2021Date of manufactureN/AManufactured byN/ACustomer serviceIn case of consumer complaint, write to H&M Hennes & Mauritz Retail PVT. Ltd, A Wing, D3, 2nd Floor, District Center, Saket, New Delhi 110017, India or call Telephone: 0008000501633. For online and store complaints email customerservice.in@hm.com.DisclaimerThis information is based on sample of the product displayed on website. There may be change in the information on label attached to the product delivered to the customer due to size chosen, date of import, name of manufacturer (in case of manufacturing in India), country of manufacture, etc. The exact detail relevant to the product delivered to the customer will reflect in the label attached to the product so deliveredArt. No.0714026025",
    "img1-src": "//lp2.hm.com/hmgoepprod?set=quality%5B79%5D%2Csource%5B%2F62%2Fed%2F62edb8b1285986a5595c6e9f60380ebbc094a055.jpg%5D%2Corigin%5Bdam%5D%2Ccategory%5Bmen_trousers_dressed%5D%2Ctype%5BLOOKBOOK%5D%2Cres%5Bm%5D%2Chmver%5B1%5D&call=url[file:/product/main]",
    "img2-src": "//lp2.hm.com/hmgoepprod?set=quality%5B79%5D%2Csource%5B%2F29%2F93%2F2993a14424cbea9cd26828827ed8c59a84567d80.jpg%5D%2Corigin%5Bdam%5D%2Ccategory%5Bmen_trousers_dressed%5D%2Ctype%5BLOOKBOOK%5D%2Cres%5Bm%5D%2Chmver%5B1%5D&call=url[file:/product/main]",
    "style": "Suit trousers",
    "generic name": "Trousers",
    "colors": "Steel blue",
    "descript": "Solid colour",
    "item__price": "Rs. 2,299",
    "Fit": "Slim fit",
    "Composition": "Shell: Polyester 72%, Viscose 27%, Elastane 1%Pocket lining: Polyester 82%, Cotton 18%"
  },
  {
    "web-scraper-order": "1629124398-69",
    "web-scraper-start-url": "https://www2.hm.com/en_in/men/shop-by-product/trousers.html",
    "link": "Suit trousers Skinny Fit",
    "link-href": "https://www2.hm.com/en_in/productpage.0714032024.html",
    "name": "Suit trousers Skinny Fit",
    "description": "Suit trousers in a stretch weave with a concealed hook-and-eye fastener and zip fly. Side pockets, welt back pockets and legs with creases. Skinny fit – a fit with slightly shorter legs that is close-fitting at the thighs, knees and ankles to create a completely fitted silhouette.",
    "review_count": null,
    "details": "Details\n\t\n\t\tLengthLongFitSkinny fitStyleSuit trousersCompositionPocket: Polyester 80%, Cotton 20%Polyester 75%, Viscose 23%, Wool 2%Care instructionsMachine wash at 30°DescriptionGreySolid colourConceptH&M MANPrice (MRP)Rs. 2,299 incl. of all taxesCountry of productionBangladeshCommon generic nameTrousersNet quantity1 NMarketed or imported byH&M Hennes & Mauritz Retail Pvt. Ltd. A-wing, D-3, 2nd Floor District Centre Saket New Delhi -110017 IndiaDate of import06-2021Date of manufactureN/AManufactured byN/ACustomer serviceIn case of consumer complaint, write to H&M Hennes & Mauritz Retail PVT. Ltd, A Wing, D3, 2nd Floor, District Center, Saket, New Delhi 110017, India or call Telephone: 0008000501633. For online and store complaints email customerservice.in@hm.com.DisclaimerThis information is based on sample of the product displayed on website. There may be change in the information on label attached to the product delivered to the customer due to size chosen, date of import, name of manufacturer (in case of manufacturing in India), country of manufacture, etc. The exact detail relevant to the product delivered to the customer will reflect in the label attached to the product so deliveredArt. No.0714032024",
    "img1-src": "//lp2.hm.com/hmgoepprod?set=quality%5B79%5D%2Csource%5B%2F22%2F2e%2F222e86fe4ed0924a5d9dbfe774c54af6ba8d5671.jpg%5D%2Corigin%5Bdam%5D%2Ccategory%5B%5D%2Ctype%5BLOOKBOOK%5D%2Cres%5Bm%5D%2Chmver%5B2%5D&call=url[file:/product/main]",
    "img2-src": "//lp2.hm.com/hmgoepprod?set=quality%5B79%5D%2Csource%5B%2F97%2Ff2%2F97f256de7e7dd2c2a9b9034c906b06fab93ce6d2.jpg%5D%2Corigin%5Bdam%5D%2Ccategory%5B%5D%2Ctype%5BLOOKBOOK%5D%2Cres%5Bm%5D%2Chmver%5B1%5D&call=url[file:/product/main]",
    "style": "Suit trousers",
    "generic name": "Trousers",
    "colors": "Grey",
    "descript": "Solid colour",
    "item__price": "Rs. 2,299",
    "Fit": "Skinny fit",
    "Composition": "Pocket: Polyester 80%, Cotton 20%Polyester 75%, Viscose 23%, Wool 2%"
  },
  {
    "web-scraper-order": "1629124508-102",
    "web-scraper-start-url": "https://www2.hm.com/en_in/men/shop-by-product/trousers.html",
    "link": "Slim Fit Chinos",
    "link-href": "https://www2.hm.com/en_in/productpage.0815456006.html",
    "name": "Slim Fit Chinos",
    "description": "Chinos in extra-stretchy cotton twill with a zip fly, side pockets, a coin pocket and welt back pockets with a button. Slim Fit – a fit that is close-fitting at the thighs, knees and ankles to create a fitted silhouette.",
    "review_count": null,
    "details": "Details\n\t\n\t\tLengthLongFitSlim fitStyleChinosCompositionCotton 98%, Elastane 2%Pocket lining: Cotton 100%Care instructionsMachine wash at 40°MaterialCottonDescriptionDark greySolid colourPrice (MRP)Rs. 1,999 incl. of all taxesCountry of productionBangladeshCommon generic nameTrousersSize: 28/30Width: 79 cmLength: 73 cmSize: 28/32Width: 79 cmLength: 77 cmSize: 29/32Width: 81 cmLength: 78 cmSize: 30/32Width: 84 cmLength: 78 cmSize: 31/32Width: 86 cmLength: 78 cmSize: 32/32Width: 89 cmLength: 79 cmSize: 32/34Width: 89 cmLength: 82 cmSize: 33/32Width: 91 cmLength: 79 cmSize: 34/32Width: 94 cmLength: 80 cmSize: 36/32Width: 99 cmLength: 80 cmSize: 36/34Width: 99 cmLength: 84 cmSize: 38/32Width: 1.04 mLength: 81 cmNet quantity1 NMarketed or imported byH&M Hennes & Mauritz Retail Pvt. Ltd. A-wing, D-3, 2nd Floor District Centre Saket New Delhi -110017 IndiaDate of import06-2021Date of manufactureN/AManufactured byN/ACustomer serviceIn case of consumer complaint, write to H&M Hennes & Mauritz Retail PVT. Ltd, A Wing, D3, 2nd Floor, District Center, Saket, New Delhi 110017, India or call Telephone: 0008000501633. For online and store complaints email customerservice.in@hm.com.DisclaimerThis information is based on sample of the product displayed on website. There may be change in the information on label attached to the product delivered to the customer due to size chosen, date of import, name of manufacturer (in case of manufacturing in India), country of manufacture, etc. The exact detail relevant to the product delivered to the customer will reflect in the label attached to the product so deliveredArt. No.0815456006",
    "img1-src": "//lp2.hm.com/hmgoepprod?set=quality%5B79%5D%2Csource%5B%2F80%2Fd8%2F80d8b137eae6709518c7da9bab76aecbc1c5cdd9.jpg%5D%2Corigin%5Bdam%5D%2Ccategory%5Bmen_trousers_chinos_slim_all%5D%2Ctype%5BLOOKBOOK%5D%2Cres%5Bm%5D%2Chmver%5B1%5D&call=url[file:/product/main]",
    "img2-src": "//lp2.hm.com/hmgoepprod?set=quality%5B79%5D%2Csource%5B%2Fc2%2F4c%2Fc24c9f304326ef6c266177e521e3d83bd05f4e73.jpg%5D%2Corigin%5Bdam%5D%2Ccategory%5Bmen_trousers_chinos_slim_all%5D%2Ctype%5BLOOKBOOK%5D%2Cres%5Bm%5D%2Chmver%5B1%5D&call=url[file:/product/main]",
    "style": "Chinos",
    "generic name": "Trousers",
    "colors": "Dark grey",
    "descript": null,
    "item__price": "Rs. 1,999",
    "Fit": "Slim fit",
    "Composition": "Cotton 98%, Elastane 2%Pocket lining: Cotton 100%"
  },
  {
    "web-scraper-order": "1629124550-115",
    "web-scraper-start-url": "https://www2.hm.com/en_in/men/shop-by-product/trousers.html",
    "link": "Regular Fit Joggers",
    "link-href": "https://www2.hm.com/en_in/productpage.0970817013.html",
    "name": "Regular Fit Joggers",
    "description": "Joggers in sweatshirt fabric made from a cotton blend. Covered elastication and a drawstring at the waist, pockets in the side seams and ribbed hems. Soft brushed inside.",
    "review_count": null,
    "details": "Details\n\t\n\t\tLengthLongWaist RiseRegular waistFitRegular fitStyleJoggersCompositionCotton 70%, Polyester 25%, Viscose 5%Care instructionsMachine wash at 40°DescriptionGrey marlPrice (MRP)Rs. 1,299 incl. of all taxesCountry of productionBangladeshCommon generic nameTrousersNet quantity1 NMarketed or imported byH&M Hennes & Mauritz Retail Pvt. Ltd. A-wing, D-3, 2nd Floor District Centre Saket New Delhi -110017 IndiaDate of import06-2021Date of manufactureN/AManufactured byN/ACustomer serviceIn case of consumer complaint, write to H&M Hennes & Mauritz Retail PVT. Ltd, A Wing, D3, 2nd Floor, District Center, Saket, New Delhi 110017, India or call Telephone: 0008000501633. For online and store complaints email customerservice.in@hm.com.DisclaimerThis information is based on sample of the product displayed on website. There may be change in the information on label attached to the product delivered to the customer due to size chosen, date of import, name of manufacturer (in case of manufacturing in India), country of manufacture, etc. The exact detail relevant to the product delivered to the customer will reflect in the label attached to the product so deliveredArt. No.0970817013",
    "img1-src": "//lp2.hm.com/hmgoepprod?set=quality%5B79%5D%2Csource%5B%2F17%2F10%2F17103754e101e03d1da553d8ce65d5cba5a10384.jpg%5D%2Corigin%5Bdam%5D%2Ccategory%5B%5D%2Ctype%5BLOOKBOOK%5D%2Cres%5Bm%5D%2Chmver%5B1%5D&call=url[file:/product/main]",
    "img2-src": "//lp2.hm.com/hmgoepprod?set=quality%5B79%5D%2Csource%5B%2F24%2F23%2F2423ba8c71717202e3e7ff647cb05e2a9183b2a8.jpg%5D%2Corigin%5Bdam%5D%2Ccategory%5B%5D%2Ctype%5BLOOKBOOK%5D%2Cres%5Bm%5D%2Chmver%5B1%5D&call=url[file:/product/main]",
    "style": "Joggers",
    "generic name": "Trousers",
    "colors": "Grey marl",
    "descript": null,
    "item__price": "Rs. 1,299",
    "Fit": "Regular fit",
    "Composition": "Cotton 70%, Polyester 25%, Viscose 5%"
  },
  {
    "web-scraper-order": "1629124600-131",
    "web-scraper-start-url": "https://www2.hm.com/en_in/men/shop-by-product/trousers.html",
    "link": "Regular Fit Linen-mix trousers",
    "link-href": "https://www2.hm.com/en_in/productpage.0941384002.html",
    "name": "Regular Fit Linen-mix trousers",
    "description": "Trousers in a linen and cotton weave with covered elastication and a drawstring at the waist. Zip fly and button, diagonal side pockets, welt back pockets with a button, and cropped, tapered legs. Regular Fit – a classic fit with good room for movement over the thighs and knees to create a comfortable, straight silhouette.",
    "review_count": null,
    "details": "Details\n\t\n\t\tLengthAnkle lengthWaist RiseRegular waistFitRegular fitStyleTaperedCompositionShell: Linen 55%, Cotton 45%Pocket lining: Cotton 100%Care instructionsMachine wash at 30°MaterialLinenDescriptionBeigeSolid colourPrice (MRP)Rs. 1,999 incl. of all taxesCountry of productionBangladeshCommon generic nameTrousersNet quantity1 NMarketed or imported byH&M Hennes & Mauritz Retail Pvt. Ltd. A-wing, D-3, 2nd Floor District Centre Saket New Delhi -110017 IndiaDate of import04-2021Date of manufactureN/AManufactured byN/ACustomer serviceIn case of consumer complaint, write to H&M Hennes & Mauritz Retail PVT. Ltd, A Wing, D3, 2nd Floor, District Center, Saket, New Delhi 110017, India or call Telephone: 0008000501633. For online and store complaints email customerservice.in@hm.com.DisclaimerThis information is based on sample of the product displayed on website. There may be change in the information on label attached to the product delivered to the customer due to size chosen, date of import, name of manufacturer (in case of manufacturing in India), country of manufacture, etc. The exact detail relevant to the product delivered to the customer will reflect in the label attached to the product so deliveredArt. No.0941384002",
    "img1-src": "//lp2.hm.com/hmgoepprod?set=quality%5B79%5D%2Csource%5B%2F55%2F49%2F5549ee2449ecc11d47e064dbd9751f7a13bb532e.jpg%5D%2Corigin%5Bdam%5D%2Ccategory%5B%5D%2Ctype%5BLOOKBOOK%5D%2Cres%5Bm%5D%2Chmver%5B1%5D&call=url[file:/product/main]",
    "img2-src": "//lp2.hm.com/hmgoepprod?set=quality%5B79%5D%2Csource%5B%2F05%2Fc6%2F05c61679d02f73ee844cbb7d2b75f2a6e3aecbe1.jpg%5D%2Corigin%5Bdam%5D%2Ccategory%5B%5D%2Ctype%5BLOOKBOOK%5D%2Cres%5Bm%5D%2Chmver%5B1%5D&call=url[file:/product/main]",
    "style": "Tapered",
    "generic name": "Trousers",
    "colors": "Beige",
    "descript": null,
    "item__price": "Rs. 1,999",
    "Fit": "Regular fit",
    "Composition": "Shell: Linen 55%, Cotton 45%Pocket lining: Cotton 100%"
  },
  {
    "web-scraper-order": "1629124564-120",
    "web-scraper-start-url": "https://www2.hm.com/en_in/men/shop-by-product/trousers.html",
    "link": "Cargo trousers Regular Fit",
    "link-href": "https://www2.hm.com/en_in/productpage.0903210002.html",
    "name": "Cargo trousers Regular Fit",
    "description": "Trousers in a cotton weave with a zip fly and button, diagonal side pockets and flap leg and back pockets with concealed press-studs. Concealed drawstring at the hems. Regular Fit – a classic fit with good room for movement over the thighs and knees to create a comfortable, straight silhouette.",
    "review_count": null,
    "details": "Details\n\t\n\t\tLengthLongFitRegular fitStyleCargoCompositionPocket lining: Cotton 80%, Polyester 20%Shell: Cotton 100%Care instructionsMachine wash at 40°DescriptionKhaki greenSolid colourPrice (MRP)Rs. 2,299 incl. of all taxesCountry of productionBangladeshCommon generic nameTrousersSize: 28/30Width: 77 cmLength: 71 cmNet quantity1 NMarketed or imported byH&M Hennes & Mauritz Retail Pvt. Ltd. A-wing, D-3, 2nd Floor District Centre Saket New Delhi -110017 IndiaDate of import06-2021Date of manufactureN/AManufactured byN/ACustomer serviceIn case of consumer complaint, write to H&M Hennes & Mauritz Retail PVT. Ltd, A Wing, D3, 2nd Floor, District Center, Saket, New Delhi 110017, India or call Telephone: 0008000501633. For online and store complaints email customerservice.in@hm.com.DisclaimerThis information is based on sample of the product displayed on website. There may be change in the information on label attached to the product delivered to the customer due to size chosen, date of import, name of manufacturer (in case of manufacturing in India), country of manufacture, etc. The exact detail relevant to the product delivered to the customer will reflect in the label attached to the product so deliveredArt. No.0903210002",
    "img1-src": "//lp2.hm.com/hmgoepprod?set=quality%5B79%5D%2Csource%5B%2Ff6%2F6b%2Ff66b1551eacdd3b4e22934839a0fe68ea95d8583.jpg%5D%2Corigin%5Bdam%5D%2Ccategory%5Bmen_trousers_trousers_regular_all%5D%2Ctype%5BLOOKBOOK%5D%2Cres%5Bm%5D%2Chmver%5B1%5D&call=url[file:/product/main]",
    "img2-src": "//lp2.hm.com/hmgoepprod?set=quality%5B79%5D%2Csource%5B%2F4d%2Ff9%2F4df9e0bfdbe83e7f29af576b1939108fbdd0c852.jpg%5D%2Corigin%5Bdam%5D%2Ccategory%5Bmen_trousers_trousers_regular_all%5D%2Ctype%5BLOOKBOOK%5D%2Cres%5Bm%5D%2Chmver%5B1%5D&call=url[file:/product/main]",
    "style": "Cargo",
    "generic name": "Trousers",
    "colors": "Khaki green",
    "descript": "Solid colour",
    "item__price": "Rs. 2,299",
    "Fit": "Regular fit",
    "Composition": "Pocket lining: Cotton 80%, Polyester 20%Shell: Cotton 100%"
  },
  {
    "web-scraper-order": "1629124553-116",
    "web-scraper-start-url": "https://www2.hm.com/en_in/men/shop-by-product/trousers.html",
    "link": "Regular Fit Linen-mix joggers",
    "link-href": "https://www2.hm.com/en_in/productpage.0964500001.html",
    "name": "Regular Fit Linen-mix joggers",
    "description": "Joggers in a linen and cotton weave with covered elastication and a drawstring at the waist. Diagonal side pockets, welt back pockets and covered elastication at the hems. Regular Fit – a classic fit with good room for movement over the thighs and knees to create a comfortable, straight silhouette.",
    "review_count": null,
    "details": "Details\n\t\n\t\tLengthLongWaist RiseRegular waistFitRegular fitStyleJoggersCompositionPocket: Cotton 100%Linen 55%, Cotton 45%Care instructionsMachine wash at 40°MaterialLinenDescriptionKhaki greenSolid colourPrice (MRP)Rs. 1,499 incl. of all taxesCountry of productionMyanmarCommon generic nameTrousersNet quantity1 NMarketed or imported byH&M Hennes & Mauritz Retail Pvt. Ltd. A-wing, D-3, 2nd Floor District Centre Saket New Delhi -110017 IndiaDate of import03-2021Date of manufactureN/AManufactured byN/ACustomer serviceIn case of consumer complaint, write to H&M Hennes & Mauritz Retail PVT. Ltd, A Wing, D3, 2nd Floor, District Center, Saket, New Delhi 110017, India or call Telephone: 0008000501633. For online and store complaints email customerservice.in@hm.com.DisclaimerThis information is based on sample of the product displayed on website. There may be change in the information on label attached to the product delivered to the customer due to size chosen, date of import, name of manufacturer (in case of manufacturing in India), country of manufacture, etc. The exact detail relevant to the product delivered to the customer will reflect in the label attached to the product so deliveredArt. No.0964500001",
    "img1-src": "//lp2.hm.com/hmgoepprod?set=quality%5B79%5D%2Csource%5B%2F67%2Fda%2F67da03c3e9015d556e0ad41d1c6f4ffe5521fcf0.jpg%5D%2Corigin%5Bdam%5D%2Ccategory%5B%5D%2Ctype%5BLOOKBOOK%5D%2Cres%5Bm%5D%2Chmver%5B1%5D&call=url[file:/product/main]",
    "img2-src": "//lp2.hm.com/hmgoepprod?set=quality%5B79%5D%2Csource%5B%2F55%2F70%2F5570b300ec348837b4c2ae52bfa5320f266e4dea.jpg%5D%2Corigin%5Bdam%5D%2Ccategory%5B%5D%2Ctype%5BLOOKBOOK%5D%2Cres%5Bm%5D%2Chmver%5B1%5D&call=url[file:/product/main]",
    "style": "Joggers",
    "generic name": "Trousers",
    "colors": "Khaki green",
    "descript": null,
    "item__price": "Rs. 1,499",
    "Fit": "Regular fit",
    "Composition": "Pocket: Cotton 100%Linen 55%, Cotton 45%"
  },
  {
    "web-scraper-order": "1629124541-112",
    "web-scraper-start-url": "https://www2.hm.com/en_in/men/shop-by-product/trousers.html",
    "link": "Hybrid Regular Tapered Joggers",
    "link-href": "https://www2.hm.com/en_in/productpage.1013317002.html",
    "name": "Hybrid Regular Tapered Joggers",
    "description": "5-pocket joggers in stretch denim. Regular waist with covered elastication and a drawstring, and a zip fly with a button. Gently tapered legs with good room for movement over the thighs and knees, and covered elastication at the hems. Made using Lycra® Hybrid Technology for exceptional softness and comfort without compromising the authentic denim look.",
    "review_count": null,
    "details": "Details\n\t\n\t\tLengthLongWaist RiseRegular waistFitRegular fitStyleTaperedJoggersCompositionCotton 78%, Polyester 21%, Elastane 1%Care instructionsMachine wash at 40°MaterialDenimDescriptionDenim blueSolid colourConceptDENIMNice to knowConsciousPrice (MRP)Rs. 2,699 incl. of all taxesCountry of productionIndiaCommon generic nameTrousersNet quantity1 NDate of manufacture08-2021Manufactured byARVIND LIMITED\nNO. 26/2 AND 27/2,, KENCHENAHALLI VILLAGE,KENGERI HOBLI, MYSORE ROAD,, 560059, BANGALORECustomer serviceIn case of consumer complaint, write to H&M Hennes & Mauritz Retail PVT. Ltd, A Wing, D3, 2nd Floor, District Center, Saket, New Delhi 110017, India or call Telephone: 0008000501633. For online and store complaints email customerservice.in@hm.com.DisclaimerThis information is based on sample of the product displayed on website. There may be change in the information on label attached to the product delivered to the customer due to size chosen, date of import, name of manufacturer (in case of manufacturing in India), country of manufacture, etc. The exact detail relevant to the product delivered to the customer will reflect in the label attached to the product so deliveredArt. No.1013317002",
    "img1-src": "//lp2.hm.com/hmgoepprod?set=quality%5B79%5D%2Csource%5B%2Fc0%2Fae%2Fc0aeaa120dc257f474d3fb13ee9450770912cb34.jpg%5D%2Corigin%5Bdam%5D%2Ccategory%5B%5D%2Ctype%5BLOOKBOOK%5D%2Cres%5Bm%5D%2Chmver%5B1%5D&call=url[file:/product/main]",
    "img2-src": "//lp2.hm.com/hmgoepprod?set=quality%5B79%5D%2Csource%5B%2F0c%2Ffc%2F0cfccd16076badfa5c3fd46e46c73bcc99173e45.jpg%5D%2Corigin%5Bdam%5D%2Ccategory%5B%5D%2Ctype%5BLOOKBOOK%5D%2Cres%5Bm%5D%2Chmver%5B1%5D&call=url[file:/product/main]",
    "style": "Tapered",
    "generic name": "Trousers",
    "colors": "Denim blue",
    "descript": null,
    "item__price": "Rs. 2,699",
    "Fit": "Regular fit",
    "Composition": "Cotton 78%, Polyester 21%, Elastane 1%"
  },
  {
    "web-scraper-order": "1629124300-38",
    "web-scraper-start-url": "https://www2.hm.com/en_in/men/shop-by-product/trousers.html",
    "link": "Cropped cigarette trousers",
    "link-href": "https://www2.hm.com/en_in/productpage.0933775001.html",
    "name": "Cropped cigarette trousers",
    "description": "Cropped cigarette trousers in a linen, lyocell and cotton weave with creases. Covered elastication at the waist and a concealed hook-and-eye fastener in the waistband. Zip fly and button, side pockets and welt back pockets. Regular Fit – a classic fit with good room for movement over the thighs and knees to create a comfortable, straight silhouette.",
    "review_count": null,
    "details": "Details\n\t\n\t\tSizeOutside leg: Length: 97.7 cm (Size 52L)Inside leg: Length: 72.5 cm (Size 52L)LengthAnkle lengthFitRegular fitStyleCigarette trousersCompositionLining: Polyester 89%, Cotton 11%Shell: Lyocell 58%, Linen 23%, Cotton 19%Care instructionsMachine wash at 30°DescriptionBeigeSolid colourConceptH&M MANNice to knowConsciousPrice (MRP)Rs. 2,699 incl. of all taxesCountry of productionChinaCommon generic nameTrousersNet quantity1 NMarketed or imported byH&M Hennes & Mauritz Retail Pvt. Ltd. A-wing, D-3, 2nd Floor District Centre Saket New Delhi -110017 IndiaDate of import02-2021Date of manufactureN/AManufactured byN/ACustomer serviceIn case of consumer complaint, write to H&M Hennes & Mauritz Retail PVT. Ltd, A Wing, D3, 2nd Floor, District Center, Saket, New Delhi 110017, India or call Telephone: 0008000501633. For online and store complaints email customerservice.in@hm.com.DisclaimerThis information is based on sample of the product displayed on website. There may be change in the information on label attached to the product delivered to the customer due to size chosen, date of import, name of manufacturer (in case of manufacturing in India), country of manufacture, etc. The exact detail relevant to the product delivered to the customer will reflect in the label attached to the product so deliveredArt. No.0933775001",
    "img1-src": "//lp2.hm.com/hmgoepprod?set=quality%5B79%5D%2Csource%5B%2Ff8%2F4a%2Ff84a79d821f958779320515feeeecf8ac5dd7b09.jpg%5D%2Corigin%5Bdam%5D%2Ccategory%5B%5D%2Ctype%5BLOOKBOOK%5D%2Cres%5Bm%5D%2Chmver%5B1%5D&call=url[file:/product/main]",
    "img2-src": "//lp2.hm.com/hmgoepprod?set=quality%5B79%5D%2Csource%5B%2Fbb%2F87%2Fbb875476e2fb41c55cafb6ff91814fa94dc8cefa.jpg%5D%2Corigin%5Bdam%5D%2Ccategory%5B%5D%2Ctype%5BLOOKBOOK%5D%2Cres%5Bm%5D%2Chmver%5B1%5D&call=url[file:/product/main]",
    "style": "Cigarette trousers",
    "generic name": "Trousers",
    "colors": "Beige",
    "descript": null,
    "item__price": "Rs. 2,699",
    "Fit": "Regular fit",
    "Composition": "Lining: Polyester 89%, Cotton 11%Shell: Lyocell 58%, Linen 23%, Cotton 19%"
  },
  {
    "web-scraper-order": "1629124401-70",
    "web-scraper-start-url": "https://www2.hm.com/en_in/men/shop-by-product/trousers.html",
    "link": "Twill trousers Slim Fit",
    "link-href": "https://www2.hm.com/en_in/productpage.0721390003.html",
    "name": "Twill trousers Slim Fit",
    "description": "5-pocket trousers in washed stretch twill with a regular waist and zip fly. Slim fit which is relaxed over the thighs and tapers from the knees down for a relaxed, well-tailored look.",
    "review_count": "(678)",
    "details": "Details\n\t\n\t\tLengthLongWaist RiseRegular waistFitSlim fitCompositionPocket: Cotton 100%Cotton 98%, Elastane 2%Care instructionsMachine wash at 40°MaterialCottonDescriptionDark greySolid colourConceptH&M MANPrice (MRP)Rs. 1,499 incl. of all taxesCountry of productionBangladeshCommon generic nameTrousersSize: 27/30Width: 75 cmLength: 72 cmSize: 30/32Width: 84 cmLength: 1.01 mSize: 31/32Width: 87 cmLength: 1.02 mSize: 32/32Width: 89 cmLength: 1.03 mSize: 33/32Width: 92 cmLength: 1.04 mSize: 34/32Width: 94 cmLength: 1.05 mSize: 36/32Width: 99 cmLength: 1.07 mNet quantity1 NMarketed or imported byH&M Hennes & Mauritz Retail Pvt. Ltd. A-wing, D-3, 2nd Floor District Centre Saket New Delhi -110017 IndiaDate of import10-2020Date of manufactureN/AManufactured byN/ACustomer serviceIn case of consumer complaint, write to H&M Hennes & Mauritz Retail PVT. Ltd, A Wing, D3, 2nd Floor, District Center, Saket, New Delhi 110017, India or call Telephone: 0008000501633. For online and store complaints email customerservice.in@hm.com.DisclaimerThis information is based on sample of the product displayed on website. There may be change in the information on label attached to the product delivered to the customer due to size chosen, date of import, name of manufacturer (in case of manufacturing in India), country of manufacture, etc. The exact detail relevant to the product delivered to the customer will reflect in the label attached to the product so deliveredArt. No.0721390003",
    "img1-src": "//lp2.hm.com/hmgoepprod?set=quality%5B79%5D%2Csource%5B%2Fe4%2F82%2Fe482d071b529a1a9750df25da2fb4dbfa3410c29.jpg%5D%2Corigin%5Bdam%5D%2Ccategory%5Bmen_trousers_trousers_slim_all%5D%2Ctype%5BLOOKBOOK%5D%2Cres%5Bm%5D%2Chmver%5B1%5D&call=url[file:/product/main]",
    "img2-src": "//lp2.hm.com/hmgoepprod?set=quality%5B79%5D%2Csource%5B%2F32%2F79%2F3279f40480cdd4b59131a2575af84db039a1de07.jpg%5D%2Corigin%5Bdam%5D%2Ccategory%5Bmen_trousers_trousers_slim_all%5D%2Ctype%5BLOOKBOOK%5D%2Cres%5Bm%5D%2Chmver%5B1%5D&call=url[file:/product/main]",
    "style": null,
    "generic name": "Trousers",
    "colors": "Dark grey",
    "descript": null,
    "item__price": "Rs. 1,499",
    "Fit": "Slim fit",
    "Composition": "Pocket: Cotton 100%Cotton 98%, Elastane 2%"
  },
  {
    "web-scraper-order": "1629124615-136",
    "web-scraper-start-url": "https://www2.hm.com/en_in/men/shop-by-product/trousers.html",
    "link": "Twill trousers Slim Fit",
    "link-href": "https://www2.hm.com/en_in/productpage.0721390001.html",
    "name": "Twill trousers Slim Fit",
    "description": "5-pocket trousers in washed stretch twill with a regular waist and zip fly. Slim fit which is relaxed over the thighs and tapers from the knees down for a relaxed, well-tailored look.",
    "review_count": null,
    "details": "Details\n\t\n\t\tLengthLongWaist RiseRegular waistFitSlim fitCompositionPocket: Cotton 100%Cotton 98%, Elastane 2%Care instructionsMachine wash at 40°MaterialCottonDescriptionBlackSolid colourConceptH&M MANPrice (MRP)Rs. 1,499 incl. of all taxesCountry of productionBangladeshCommon generic nameTrousersSize: 27/30Width: 74 cmLength: 72 cmSize: 30/32Width: 84 cmLength: 1.01 mSize: 31/32Width: 87 cmLength: 1.02 mSize: 32/32Width: 92 cmLength: 1.03 mSize: 33/32Width: 92 cmLength: 1.04 mSize: 34/32Width: 94 cmLength: 1.05 mSize: 36/32Width: 99 cmLength: 1.07 mNet quantity1 NMarketed or imported byH&M Hennes & Mauritz Retail Pvt. Ltd. A-wing, D-3, 2nd Floor District Centre Saket New Delhi -110017 IndiaDate of import02-2021Date of manufactureN/AManufactured byN/ACustomer serviceIn case of consumer complaint, write to H&M Hennes & Mauritz Retail PVT. Ltd, A Wing, D3, 2nd Floor, District Center, Saket, New Delhi 110017, India or call Telephone: 0008000501633. For online and store complaints email customerservice.in@hm.com.DisclaimerThis information is based on sample of the product displayed on website. There may be change in the information on label attached to the product delivered to the customer due to size chosen, date of import, name of manufacturer (in case of manufacturing in India), country of manufacture, etc. The exact detail relevant to the product delivered to the customer will reflect in the label attached to the product so deliveredArt. No.0721390001",
    "img1-src": "//lp2.hm.com/hmgoepprod?set=quality%5B79%5D%2Csource%5B%2F61%2Fe0%2F61e0ebeaffa2cfe6e494f727d589642c4787dcc7.jpg%5D%2Corigin%5Bdam%5D%2Ccategory%5Bmen_trousers_trousers_slim_all%5D%2Ctype%5BLOOKBOOK%5D%2Cres%5Bm%5D%2Chmver%5B1%5D&call=url[file:/product/main]",
    "img2-src": "//lp2.hm.com/hmgoepprod?set=quality%5B79%5D%2Csource%5B%2F98%2Fdf%2F98df05abac4166ed45139ffdcc731e914546f8f3.jpg%5D%2Corigin%5Bdam%5D%2Ccategory%5Bmen_trousers_trousers_slim_all%5D%2Ctype%5BLOOKBOOK%5D%2Cres%5Bm%5D%2Chmver%5B1%5D&call=url[file:/product/main]",
    "style": null,
    "generic name": "Trousers",
    "colors": "Black",
    "descript": null,
    "item__price": "Rs. 1,499",
    "Fit": "Slim fit",
    "Composition": "Pocket: Cotton 100%Cotton 98%, Elastane 2%"
  },
  {
    "web-scraper-order": "1629124522-106",
    "web-scraper-start-url": "https://www2.hm.com/en_in/men/shop-by-product/trousers.html",
    "link": "Slim Fit Cropped trousers",
    "link-href": "https://www2.hm.com/en_in/productpage.0991309001.html",
    "name": "Slim Fit Cropped trousers",
    "description": "Cropped trousers in woven fabric with a concealed hook-and-eye fastening and button in the waistband and a zip fly. Side pockets, welt back pockets with a button, and legs with creases. Slim Fit – a fit that is close-fitting at the thighs and knees to create a fitted silhouette.",
    "review_count": "(9)",
    "details": "Details\n\t\n\t\tLengthAnkle lengthWaist RiseRegular waistFitSlim fitStyleCigarette trousersCompositionPolyester 77%, Viscose 21%, Elastane 2%Care instructionsMachine wash at 30°DescriptionBlackSolid colourConceptH&M MANNice to knowConsciousPrice (MRP)Rs. 1,499 incl. of all taxesCountry of productionBangladeshCommon generic nameTrousersNet quantity1 NMarketed or imported byH&M Hennes & Mauritz Retail Pvt. Ltd. A-wing, D-3, 2nd Floor District Centre Saket New Delhi -110017 IndiaDate of import06-2021Date of manufactureN/AManufactured byN/ACustomer serviceIn case of consumer complaint, write to H&M Hennes & Mauritz Retail PVT. Ltd, A Wing, D3, 2nd Floor, District Center, Saket, New Delhi 110017, India or call Telephone: 0008000501633. For online and store complaints email customerservice.in@hm.com.DisclaimerThis information is based on sample of the product displayed on website. There may be change in the information on label attached to the product delivered to the customer due to size chosen, date of import, name of manufacturer (in case of manufacturing in India), country of manufacture, etc. The exact detail relevant to the product delivered to the customer will reflect in the label attached to the product so deliveredArt. No.0991309001",
    "img1-src": "//lp2.hm.com/hmgoepprod?set=quality%5B79%5D%2Csource%5B%2F62%2F0e%2F620e635f41c6879e29d13c8461a3024bf1056fc8.jpg%5D%2Corigin%5Bdam%5D%2Ccategory%5B%5D%2Ctype%5BLOOKBOOK%5D%2Cres%5Bm%5D%2Chmver%5B1%5D&call=url[file:/product/main]",
    "img2-src": "//lp2.hm.com/hmgoepprod?set=quality%5B79%5D%2Csource%5B%2F4f%2F6e%2F4f6e33481e4eea31421276d7f76fa656e60cec99.jpg%5D%2Corigin%5Bdam%5D%2Ccategory%5B%5D%2Ctype%5BLOOKBOOK%5D%2Cres%5Bm%5D%2Chmver%5B1%5D&call=url[file:/product/main]",
    "style": "Cigarette trousers",
    "generic name": "Trousers",
    "colors": "Black",
    "descript": null,
    "item__price": "Rs. 1,499",
    "Fit": "Slim fit",
    "Composition": "Polyester 77%, Viscose 21%, Elastane 2%"
  },
  {
    "web-scraper-order": "1629124345-53",
    "web-scraper-start-url": "https://www2.hm.com/en_in/men/shop-by-product/trousers.html",
    "link": "Sports joggers",
    "link-href": "https://www2.hm.com/en_in/productpage.0862104020.html",
    "name": "Sports joggers",
    "description": "Sports joggers in jersey made from a cotton blend with taped details. Elasticated waist, a slightly lower crotch with a ventilating mesh section, and zipped side pockets for safe storage of small items.",
    "review_count": null,
    "details": "Details\n\t\n\t\tLengthLongStyleJoggersCompositionShell: Polyester 58%, Cotton 42%Pocket lining: Polyester 100%More sustainable materialsRecycled polyester 58%Care instructionsMachine wash at 40°Sports activityTrainingDescriptionGrey marlSolid colourNice to knowConsciousPrice (MRP)Rs. 2,299 incl. of all taxesCountry of productionChinaCommon generic nameTrousersNet quantity1 NMarketed or imported byH&M Hennes & Mauritz Retail Pvt. Ltd. A-wing, D-3, 2nd Floor District Centre Saket New Delhi -110017 IndiaDate of import01-2021Date of manufactureN/AManufactured byN/ACustomer serviceIn case of consumer complaint, write to H&M Hennes & Mauritz Retail PVT. Ltd, A Wing, D3, 2nd Floor, District Center, Saket, New Delhi 110017, India or call Telephone: 0008000501633. For online and store complaints email customerservice.in@hm.com.DisclaimerThis information is based on sample of the product displayed on website. There may be change in the information on label attached to the product delivered to the customer due to size chosen, date of import, name of manufacturer (in case of manufacturing in India), country of manufacture, etc. The exact detail relevant to the product delivered to the customer will reflect in the label attached to the product so deliveredArt. No.0862104020",
    "img1-src": "//lp2.hm.com/hmgoepprod?set=quality%5B79%5D%2Csource%5B%2Ffb%2Fd9%2Ffbd9200c7dcc8ca9214037ecd3d3e3a0c77dabe6.jpg%5D%2Corigin%5Bdam%5D%2Ccategory%5Bmen_sport_bottoms%5D%2Ctype%5BDESCRIPTIVESTILLLIFE%5D%2Cres%5Bm%5D%2Chmver%5B1%5D&call=url[file:/product/main]",
    "img2-src": "//lp2.hm.com/hmgoepprod?set=quality%5B79%5D%2Csource%5B%2F66%2F11%2F6611e9fc5464fffa723abf975ff96e86f0560602.jpg%5D%2Corigin%5Bdam%5D%2Ccategory%5Bmen_sport_bottoms%5D%2Ctype%5BDESCRIPTIVEDETAIL%5D%2Cres%5Bm%5D%2Chmver%5B1%5D&call=url[file:/product/main]",
    "style": "Joggers",
    "generic name": "Trousers",
    "colors": "Grey marl",
    "descript": null,
    "item__price": "Rs. 2,299",
    "Fit": null,
    "Composition": "Shell: Polyester 58%, Cotton 42%Pocket lining: Polyester 100%"
  },
  {
    "web-scraper-order": "1629124306-40",
    "web-scraper-start-url": "https://www2.hm.com/en_in/men/shop-by-product/trousers.html",
    "link": "Sweatpants Tapered Fit",
    "link-href": "https://www2.hm.com/en_in/productpage.0904801001.html",
    "name": "Sweatpants Tapered Fit",
    "description": "Trousers in lightweight sweatshirt fabric made from a cotton blend with covered elastication and a drawstring at the waist. Tapered legs, pockets in the side seams and ribbed hems.",
    "review_count": null,
    "details": "Details\n\t\n\t\tSizeInside leg: Length: 74.7 cm (Size L/L)LengthLongStyleSweatpantsTaperedCompositionCotton 100%Care instructionsMachine wash at 40°DescriptionBlackSolid colourConceptBASICSPrice (MRP)Rs. 1,499 incl. of all taxesCountry of productionMyanmarCommon generic nameTrousersNet quantity1 NMarketed or imported byH&M Hennes & Mauritz Retail Pvt. Ltd. A-wing, D-3, 2nd Floor District Centre Saket New Delhi -110017 IndiaDate of import12-2020Date of manufactureN/AManufactured byN/ACustomer serviceIn case of consumer complaint, write to H&M Hennes & Mauritz Retail PVT. Ltd, A Wing, D3, 2nd Floor, District Center, Saket, New Delhi 110017, India or call Telephone: 0008000501633. For online and store complaints email customerservice.in@hm.com.DisclaimerThis information is based on sample of the product displayed on website. There may be change in the information on label attached to the product delivered to the customer due to size chosen, date of import, name of manufacturer (in case of manufacturing in India), country of manufacture, etc. The exact detail relevant to the product delivered to the customer will reflect in the label attached to the product so deliveredArt. No.0904801001",
    "img1-src": "//lp2.hm.com/hmgoepprod?set=quality%5B79%5D%2Csource%5B%2F76%2F63%2F766374e65518d9437769a26fd388a0e8da0a334b.jpg%5D%2Corigin%5Bdam%5D%2Ccategory%5Bmen_trousers_casual%5D%2Ctype%5BDESCRIPTIVESTILLLIFE%5D%2Cres%5Bm%5D%2Chmver%5B1%5D&call=url[file:/product/main]",
    "img2-src": "//lp2.hm.com/hmgoepprod?set=quality%5B79%5D%2Csource%5B%2F8a%2F31%2F8a3145b92402288ba2d8afeb4757afdf60096992.jpg%5D%2Corigin%5Bdam%5D%2Ccategory%5Bmen_trousers_casual%5D%2Ctype%5BDESCRIPTIVEDETAIL%5D%2Cres%5Bm%5D%2Chmver%5B1%5D&call=url[file:/product/main]",
    "style": "Sweatpants",
    "generic name": "Trousers",
    "colors": "Black",
    "descript": "Solid colour",
    "item__price": "Rs. 1,499",
    "Fit": null,
    "Composition": "Cotton 100%"
  },
  {
    "web-scraper-order": "1629124479-93",
    "web-scraper-start-url": "https://www2.hm.com/en_in/men/shop-by-product/trousers.html",
    "link": "Cotton chinos Regular Fit",
    "link-href": "https://www2.hm.com/en_in/productpage.0905932001.html",
    "name": "Cotton chinos Regular Fit",
    "description": "Chinos in stretch cotton twill with a zip fly and button, diagonal side pockets, a coin pocket and welt back pockets with a button. Regular Fit – a classic fit with good room for movement over the thighs and knees to create a comfortable, straight silhouette.",
    "review_count": null,
    "details": "Details\n\t\n\t\tLengthLongFitRegular fitStyleChinosCompositionCotton 98%, Elastane 2%Pocket lining: Cotton 100%Care instructionsMachine wash at 40°MaterialCottonDescriptionBlackSolid colourPrice (MRP)Rs. 1,999 incl. of all taxesCountry of productionBangladeshCommon generic nameTrousersSize: 28/30Width: 79 cmLength: 73 cmSize: 28/32Width: 79 cmLength: 77 cmSize: 29/32Width: 81 cmLength: 78 cmSize: 30/32Width: 84 cmLength: 78 cmSize: 31/32Width: 86 cmLength: 78 cmSize: 32/32Width: 89 cmLength: 79 cmSize: 33/32Width: 91 cmLength: 79 cmSize: 34/32Width: 94 cmLength: 80 cmSize: 36/32Width: 99 cmLength: 80 cmSize: 38/32Width: 1.04 mLength: 81 cmNet quantity1 NMarketed or imported byH&M Hennes & Mauritz Retail Pvt. Ltd. A-wing, D-3, 2nd Floor District Centre Saket New Delhi -110017 IndiaDate of import01-2021Date of manufactureN/AManufactured byN/ACustomer serviceIn case of consumer complaint, write to H&M Hennes & Mauritz Retail PVT. Ltd, A Wing, D3, 2nd Floor, District Center, Saket, New Delhi 110017, India or call Telephone: 0008000501633. For online and store complaints email customerservice.in@hm.com.DisclaimerThis information is based on sample of the product displayed on website. There may be change in the information on label attached to the product delivered to the customer due to size chosen, date of import, name of manufacturer (in case of manufacturing in India), country of manufacture, etc. The exact detail relevant to the product delivered to the customer will reflect in the label attached to the product so deliveredArt. No.0905932001",
    "img1-src": "//lp2.hm.com/hmgoepprod?set=quality%5B79%5D%2Csource%5B%2F25%2F7c%2F257c9f98cf0b1ffd4f6c53b907f700446cd6f741.jpg%5D%2Corigin%5Bdam%5D%2Ccategory%5Bmen_trousers_chinos_regular_all%5D%2Ctype%5BLOOKBOOK%5D%2Cres%5Bm%5D%2Chmver%5B1%5D&call=url[file:/product/main]",
    "img2-src": "//lp2.hm.com/hmgoepprod?set=quality%5B79%5D%2Csource%5B%2F20%2Fb4%2F20b4135be933fd9024843a5778709db56d28644f.jpg%5D%2Corigin%5Bdam%5D%2Ccategory%5Bmen_trousers_chinos_regular_all%5D%2Ctype%5BLOOKBOOK%5D%2Cres%5Bm%5D%2Chmver%5B1%5D&call=url[file:/product/main]",
    "style": "Chinos",
    "generic name": "Trousers",
    "colors": "Black",
    "descript": null,
    "item__price": "Rs. 1,999",
    "Fit": "Regular fit",
    "Composition": "Cotton 98%, Elastane 2%Pocket lining: Cotton 100%"
  },
  {
    "web-scraper-order": "1629124519-105",
    "web-scraper-start-url": "https://www2.hm.com/en_in/men/shop-by-product/trousers.html",
    "link": "Cargo trousers Regular Fit",
    "link-href": "https://www2.hm.com/en_in/productpage.0903210004.html",
    "name": "Cargo trousers Regular Fit",
    "description": "Trousers in a cotton weave with a zip fly and button, diagonal side pockets and flap leg and back pockets with concealed press-studs. Concealed drawstring at the hems. Regular Fit – a classic fit with good room for movement over the thighs and knees to create a comfortable, straight silhouette.",
    "review_count": null,
    "details": "Details\n\t\n\t\tLengthLongFitRegular fitStyleCargoCompositionPocket lining: Cotton 80%, Polyester 20%Shell: Cotton 100%Care instructionsMachine wash at 40°DescriptionBeigeSolid colourPrice (MRP)Rs. 2,299 incl. of all taxesCountry of productionBangladeshCommon generic nameTrousersSize: 28/30Width: 77 cmLength: 71 cmNet quantity1 NMarketed or imported byH&M Hennes & Mauritz Retail Pvt. Ltd. A-wing, D-3, 2nd Floor District Centre Saket New Delhi -110017 IndiaDate of import06-2021Date of manufactureN/AManufactured byN/ACustomer serviceIn case of consumer complaint, write to H&M Hennes & Mauritz Retail PVT. Ltd, A Wing, D3, 2nd Floor, District Center, Saket, New Delhi 110017, India or call Telephone: 0008000501633. For online and store complaints email customerservice.in@hm.com.DisclaimerThis information is based on sample of the product displayed on website. There may be change in the information on label attached to the product delivered to the customer due to size chosen, date of import, name of manufacturer (in case of manufacturing in India), country of manufacture, etc. The exact detail relevant to the product delivered to the customer will reflect in the label attached to the product so deliveredArt. No.0903210004",
    "img1-src": "//lp2.hm.com/hmgoepprod?set=quality%5B79%5D%2Csource%5B%2Fbd%2Fd2%2Fbdd2be51f75d82a3067431cd04a078a9a12b319a.jpg%5D%2Corigin%5Bdam%5D%2Ccategory%5Bmen_trousers_trousers_regular_all%5D%2Ctype%5BLOOKBOOK%5D%2Cres%5Bm%5D%2Chmver%5B1%5D&call=url[file:/product/main]",
    "img2-src": "//lp2.hm.com/hmgoepprod?set=quality%5B79%5D%2Csource%5B%2F71%2Ff2%2F71f2cf3fcf468723aca187ccdcd9fd74f8c0a0f9.jpg%5D%2Corigin%5Bdam%5D%2Ccategory%5Bmen_trousers_trousers_regular_all%5D%2Ctype%5BLOOKBOOK%5D%2Cres%5Bm%5D%2Chmver%5B1%5D&call=url[file:/product/main]",
    "style": "Cargo",
    "generic name": "Trousers",
    "colors": "Beige",
    "descript": "Solid colour",
    "item__price": "Rs. 2,299",
    "Fit": "Regular fit",
    "Composition": "Pocket lining: Cotton 80%, Polyester 20%Shell: Cotton 100%"
  },
  {
    "web-scraper-order": "1629124515-104",
    "web-scraper-start-url": "https://www2.hm.com/en_in/men/shop-by-product/trousers.html",
    "link": "Hybrid Regular Tapered Joggers",
    "link-href": "https://www2.hm.com/en_in/productpage.1013317004.html",
    "name": "Hybrid Regular Tapered Joggers",
    "description": "5-pocket joggers in stretch denim. Regular waist with covered elastication and a drawstring, and a zip fly with a button. Gently tapered legs with good room for movement over the thighs and knees, and covered elastication at the hems. Made using Lycra® Hybrid Technology for exceptional softness and comfort without compromising the authentic denim look.",
    "review_count": null,
    "details": "Details\n\t\n\t\tLengthLongWaist RiseRegular waistFitRegular fitStyleTaperedJoggersCompositionCotton 78%, Polyester 21%, Elastane 1%Care instructionsMachine wash at 40°MaterialDenimDescriptionSolid colourConceptDENIMNice to knowConsciousPrice (MRP)Rs. 2,699 incl. of all taxesCountry of productionIndiaCommon generic nameTrousersNet quantity1 NDate of manufacture08-2021Manufactured byARVIND LIMITED\nNO. 26/2 AND 27/2,, KENCHENAHALLI VILLAGE,KENGERI HOBLI, MYSORE ROAD,, 560059, BANGALORECustomer serviceIn case of consumer complaint, write to H&M Hennes & Mauritz Retail PVT. Ltd, A Wing, D3, 2nd Floor, District Center, Saket, New Delhi 110017, India or call Telephone: 0008000501633. For online and store complaints email customerservice.in@hm.com.DisclaimerThis information is based on sample of the product displayed on website. There may be change in the information on label attached to the product delivered to the customer due to size chosen, date of import, name of manufacturer (in case of manufacturing in India), country of manufacture, etc. The exact detail relevant to the product delivered to the customer will reflect in the label attached to the product so deliveredArt. No.1013317004",
    "img1-src": "//lp2.hm.com/hmgoepprod?set=quality%5B79%5D%2Csource%5B%2F64%2F72%2F6472f9b9b37ad5b8bda0b6cc7a603efc5c16ff4e.jpg%5D%2Corigin%5Bdam%5D%2Ccategory%5B%5D%2Ctype%5BLOOKBOOK%5D%2Cres%5Bm%5D%2Chmver%5B1%5D&call=url[file:/product/main]",
    "img2-src": "//lp2.hm.com/hmgoepprod?set=quality%5B79%5D%2Csource%5B%2Fd9%2F0e%2Fd90e8b0ad5f0662095c762f790806a44f76e59d1.jpg%5D%2Corigin%5Bdam%5D%2Ccategory%5B%5D%2Ctype%5BLOOKBOOK%5D%2Cres%5Bm%5D%2Chmver%5B1%5D&call=url[file:/product/main]",
    "style": "Tapered",
    "generic name": "Trousers",
    "colors": "Solid colour",
    "descript": null,
    "item__price": "Rs. 2,699",
    "Fit": "Regular fit",
    "Composition": "Cotton 78%, Polyester 21%, Elastane 1%"
  },
  {
    "web-scraper-order": "1629124378-63",
    "web-scraper-start-url": "https://www2.hm.com/en_in/men/shop-by-product/trousers.html",
    "link": "Regular Fit Linen-mix trousers",
    "link-href": "https://www2.hm.com/en_in/productpage.0941384003.html",
    "name": "Regular Fit Linen-mix trousers",
    "description": "Trousers in a linen and cotton weave with covered elastication and a drawstring at the waist. Zip fly and button, diagonal side pockets, welt back pockets with a button, and cropped, tapered legs. Regular Fit – a classic fit with good room for movement over the thighs and knees to create a comfortable, straight silhouette.",
    "review_count": null,
    "details": "Details\n\t\n\t\tLengthAnkle lengthWaist RiseRegular waistFitRegular fitStyleTaperedCompositionShell: Linen 55%, Cotton 45%Pocket lining: Cotton 100%Care instructionsMachine wash at 30°MaterialLinenDescriptionDark khaki greenSolid colourPrice (MRP)Rs. 1,999 incl. of all taxesCountry of productionMyanmarCommon generic nameTrousersNet quantity1 NMarketed or imported byH&M Hennes & Mauritz Retail Pvt. Ltd. A-wing, D-3, 2nd Floor District Centre Saket New Delhi -110017 IndiaDate of import04-2021Date of manufactureN/AManufactured byN/ACustomer serviceIn case of consumer complaint, write to H&M Hennes & Mauritz Retail PVT. Ltd, A Wing, D3, 2nd Floor, District Center, Saket, New Delhi 110017, India or call Telephone: 0008000501633. For online and store complaints email customerservice.in@hm.com.DisclaimerThis information is based on sample of the product displayed on website. There may be change in the information on label attached to the product delivered to the customer due to size chosen, date of import, name of manufacturer (in case of manufacturing in India), country of manufacture, etc. The exact detail relevant to the product delivered to the customer will reflect in the label attached to the product so deliveredArt. No.0941384003",
    "img1-src": "//lp2.hm.com/hmgoepprod?set=quality%5B79%5D%2Csource%5B%2Fe4%2Fc0%2Fe4c0cd29c85d019795cc8eab786e805602466a0a.jpg%5D%2Corigin%5Bdam%5D%2Ccategory%5B%5D%2Ctype%5BLOOKBOOK%5D%2Cres%5Bm%5D%2Chmver%5B1%5D&call=url[file:/product/main]",
    "img2-src": "//lp2.hm.com/hmgoepprod?set=quality%5B79%5D%2Csource%5B%2Fc7%2Fe0%2Fc7e0ce7c194826c8e401ee2e146b8cd9d8038a15.jpg%5D%2Corigin%5Bdam%5D%2Ccategory%5B%5D%2Ctype%5BLOOKBOOK%5D%2Cres%5Bm%5D%2Chmver%5B1%5D&call=url[file:/product/main]",
    "style": "Tapered",
    "generic name": "Trousers",
    "colors": "Dark khaki green",
    "descript": null,
    "item__price": "Rs. 1,999",
    "Fit": "Regular fit",
    "Composition": "Shell: Linen 55%, Cotton 45%Pocket lining: Cotton 100%"
  },
  {
    "web-scraper-order": "1629124462-88",
    "web-scraper-start-url": "https://www2.hm.com/en_in/men/shop-by-product/trousers.html",
    "link": "Cotton chinos Regular Fit",
    "link-href": "https://www2.hm.com/en_in/productpage.0905932005.html",
    "name": "Cotton chinos Regular Fit",
    "description": "Chinos in stretch cotton twill with a zip fly and button, diagonal side pockets, a coin pocket and welt back pockets with a button. Regular Fit – a classic fit with good room for movement over the thighs and knees to create a comfortable, straight silhouette.",
    "review_count": null,
    "details": "Details\n\t\n\t\tLengthLongFitRegular fitStyleChinosCompositionPocket lining: Cotton 100%Cotton 98%, Elastane 2%Care instructionsMachine wash at 40°MaterialCottonDescriptionDark blueSolid colourPrice (MRP)Rs. 1,999 incl. of all taxesCountry of productionBangladeshCommon generic nameTrousersNet quantity1 NMarketed or imported byH&M Hennes & Mauritz Retail Pvt. Ltd. A-wing, D-3, 2nd Floor District Centre Saket New Delhi -110017 IndiaDate of import06-2021Date of manufactureN/AManufactured byN/ACustomer serviceIn case of consumer complaint, write to H&M Hennes & Mauritz Retail PVT. Ltd, A Wing, D3, 2nd Floor, District Center, Saket, New Delhi 110017, India or call Telephone: 0008000501633. For online and store complaints email customerservice.in@hm.com.DisclaimerThis information is based on sample of the product displayed on website. There may be change in the information on label attached to the product delivered to the customer due to size chosen, date of import, name of manufacturer (in case of manufacturing in India), country of manufacture, etc. The exact detail relevant to the product delivered to the customer will reflect in the label attached to the product so deliveredArt. No.0905932005",
    "img1-src": "//lp2.hm.com/hmgoepprod?set=quality%5B79%5D%2Csource%5B%2F3f%2F83%2F3f83341bee873d4956afffb27e37474a86f7431a.jpg%5D%2Corigin%5Bdam%5D%2Ccategory%5Bmen_trousers_chinos_regular_all%5D%2Ctype%5BLOOKBOOK%5D%2Cres%5Bm%5D%2Chmver%5B1%5D&call=url[file:/product/main]",
    "img2-src": "//lp2.hm.com/hmgoepprod?set=quality%5B79%5D%2Csource%5B%2F9d%2F5a%2F9d5ad8b69aa196d8df57aba0ccfbb7c34cd59e4a.jpg%5D%2Corigin%5Bdam%5D%2Ccategory%5Bmen_trousers_chinos_regular_all%5D%2Ctype%5BLOOKBOOK%5D%2Cres%5Bm%5D%2Chmver%5B1%5D&call=url[file:/product/main]",
    "style": "Chinos",
    "generic name": "Trousers",
    "colors": "Dark blue",
    "descript": null,
    "item__price": "Rs. 1,999",
    "Fit": "Regular fit",
    "Composition": "Pocket lining: Cotton 100%Cotton 98%, Elastane 2%"
  },
  {
    "web-scraper-order": "1629124598-130",
    "web-scraper-start-url": "https://www2.hm.com/en_in/men/shop-by-product/trousers.html",
    "link": "Cotton chinos Regular Fit",
    "link-href": "https://www2.hm.com/en_in/productpage.0905932009.html",
    "name": "Cotton chinos Regular Fit",
    "description": "Chinos in stretch cotton twill with a zip fly and button, diagonal side pockets, a coin pocket and welt back pockets with a button. Regular Fit – a classic fit with good room for movement over the thighs and knees to create a comfortable, straight silhouette.",
    "review_count": null,
    "details": "Details\n\t\n\t\tLengthLongFitRegular fitStyleChinosCompositionCotton 98%, Elastane 2%Pocket lining: Cotton 100%Care instructionsMachine wash at 40°MaterialCottonDescriptionDark greySolid colourPrice (MRP)Rs. 1,999 incl. of all taxesCountry of productionMyanmarCommon generic nameTrousersNet quantity1 NMarketed or imported byH&M Hennes & Mauritz Retail Pvt. Ltd. A-wing, D-3, 2nd Floor District Centre Saket New Delhi -110017 IndiaDate of import01-2021Date of manufactureN/AManufactured byN/ACustomer serviceIn case of consumer complaint, write to H&M Hennes & Mauritz Retail PVT. Ltd, A Wing, D3, 2nd Floor, District Center, Saket, New Delhi 110017, India or call Telephone: 0008000501633. For online and store complaints email customerservice.in@hm.com.DisclaimerThis information is based on sample of the product displayed on website. There may be change in the information on label attached to the product delivered to the customer due to size chosen, date of import, name of manufacturer (in case of manufacturing in India), country of manufacture, etc. The exact detail relevant to the product delivered to the customer will reflect in the label attached to the product so deliveredArt. No.0905932009",
    "img1-src": "//lp2.hm.com/hmgoepprod?set=quality%5B79%5D%2Csource%5B%2F59%2Fff%2F59ff7506a8196db5e41189ac2a122dd16f9ee87a.jpg%5D%2Corigin%5Bdam%5D%2Ccategory%5Bmen_trousers_chinos_regular_all%5D%2Ctype%5BLOOKBOOK%5D%2Cres%5Bm%5D%2Chmver%5B1%5D&call=url[file:/product/main]",
    "img2-src": "//lp2.hm.com/hmgoepprod?set=quality%5B79%5D%2Csource%5B%2F59%2Fb2%2F59b2eda4d32068b580f11404b6f8bb01be0d8de4.jpg%5D%2Corigin%5Bdam%5D%2Ccategory%5Bmen_trousers_chinos_regular_all%5D%2Ctype%5BLOOKBOOK%5D%2Cres%5Bm%5D%2Chmver%5B1%5D&call=url[file:/product/main]",
    "style": "Chinos",
    "generic name": "Trousers",
    "colors": "Dark grey",
    "descript": null,
    "item__price": "Rs. 1,999",
    "Fit": "Regular fit",
    "Composition": "Cotton 98%, Elastane 2%Pocket lining: Cotton 100%"
  },
  {
    "web-scraper-order": "1629124567-121",
    "web-scraper-start-url": "https://www2.hm.com/en_in/men/shop-by-product/trousers.html",
    "link": "Skinny Fit Cargo joggers",
    "link-href": "https://www2.hm.com/en_in/productpage.0997065002.html",
    "name": "Skinny Fit Cargo joggers",
    "description": "Joggers in cotton twill with an elasticated, drawstring waist, side pockets, and leg and back pockets with a flap and concealed press-studs. Tapered legs with seams at the knees and cuffed hems. Skinny Fit – a fit with slightly shorter legs that is close-fitting at the thighs, knees and ankles to create a completely fitted silhouette.",
    "review_count": null,
    "details": "Details\n\t\n\t\tSizeInside leg: Length: 76.5 cm (Size M/L)LengthLongWaist RiseRegular waistFitSkinny fitStyleCargoJoggersCompositionShell: Cotton 98%, Elastane 2%Pocket lining: Cotton 100%Care instructionsMachine wash at 40°MaterialCottonDescriptionDark khaki greenSolid colourPrice (MRP)Rs. 2,299 incl. of all taxesCountry of productionBangladeshCommon generic nameTrousersNet quantity1 NMarketed or imported byH&M Hennes & Mauritz Retail Pvt. Ltd. A-wing, D-3, 2nd Floor District Centre Saket New Delhi -110017 IndiaDate of import06-2021Date of manufactureN/AManufactured byN/ACustomer serviceIn case of consumer complaint, write to H&M Hennes & Mauritz Retail PVT. Ltd, A Wing, D3, 2nd Floor, District Center, Saket, New Delhi 110017, India or call Telephone: 0008000501633. For online and store complaints email customerservice.in@hm.com.DisclaimerThis information is based on sample of the product displayed on website. There may be change in the information on label attached to the product delivered to the customer due to size chosen, date of import, name of manufacturer (in case of manufacturing in India), country of manufacture, etc. The exact detail relevant to the product delivered to the customer will reflect in the label attached to the product so deliveredArt. No.0997065002",
    "img1-src": "//lp2.hm.com/hmgoepprod?set=quality%5B79%5D%2Csource%5B%2F56%2F92%2F5692a8dbe099854300e806797b6b34944ce11ef1.jpg%5D%2Corigin%5Bdam%5D%2Ccategory%5B%5D%2Ctype%5BLOOKBOOK%5D%2Cres%5Bm%5D%2Chmver%5B1%5D&call=url[file:/product/main]",
    "img2-src": "//lp2.hm.com/hmgoepprod?set=quality%5B79%5D%2Csource%5B%2F69%2F93%2F6993c09621853b503bc4b214376b921fdf1be522.jpg%5D%2Corigin%5Bdam%5D%2Ccategory%5B%5D%2Ctype%5BLOOKBOOK%5D%2Cres%5Bm%5D%2Chmver%5B1%5D&call=url[file:/product/main]",
    "style": "Cargo",
    "generic name": "Trousers",
    "colors": "Dark khaki green",
    "descript": "Pocket lining: Cotton 100%",
    "item__price": "Rs. 2,299",
    "Fit": "Skinny fit",
    "Composition": "Shell: Cotton 98%, Elastane 2%Pocket lining: Cotton 100%"
  },
  {
    "web-scraper-order": "1629124442-82",
    "web-scraper-start-url": "https://www2.hm.com/en_in/men/shop-by-product/trousers.html",
    "link": "Slim Fit Chinos",
    "link-href": "https://www2.hm.com/en_in/productpage.0815456046.html",
    "name": "Slim Fit Chinos",
    "description": "Chinos in extra-stretchy cotton twill with a zip fly, side pockets, a coin pocket and welt back pockets with a button. Slim Fit – a fit that is close-fitting at the thighs, knees and ankles to create a fitted silhouette.",
    "review_count": null,
    "details": "Details\n\t\n\t\tLengthLongFitSlim fitStyleChinosCompositionCotton 98%, Elastane 2%Pocket lining: Cotton 100%Care instructionsMachine wash at 40°MaterialCottonDescriptionDark blueSolid colourPrice (MRP)Rs. 1,999 incl. of all taxesCountry of productionBangladeshCommon generic nameTrousersNet quantity1 NMarketed or imported byH&M Hennes & Mauritz Retail Pvt. Ltd. A-wing, D-3, 2nd Floor District Centre Saket New Delhi -110017 IndiaDate of import06-2021Date of manufactureN/AManufactured byN/ACustomer serviceIn case of consumer complaint, write to H&M Hennes & Mauritz Retail PVT. Ltd, A Wing, D3, 2nd Floor, District Center, Saket, New Delhi 110017, India or call Telephone: 0008000501633. For online and store complaints email customerservice.in@hm.com.DisclaimerThis information is based on sample of the product displayed on website. There may be change in the information on label attached to the product delivered to the customer due to size chosen, date of import, name of manufacturer (in case of manufacturing in India), country of manufacture, etc. The exact detail relevant to the product delivered to the customer will reflect in the label attached to the product so deliveredArt. No.0815456046",
    "img1-src": "//lp2.hm.com/hmgoepprod?set=quality%5B79%5D%2Csource%5B%2F70%2F6d%2F706d6e7399a38333cc0fd9afb97cf5bbaab1693a.jpg%5D%2Corigin%5Bdam%5D%2Ccategory%5B%5D%2Ctype%5BLOOKBOOK%5D%2Cres%5Bm%5D%2Chmver%5B1%5D&call=url[file:/product/main]",
    "img2-src": "//lp2.hm.com/hmgoepprod?set=quality%5B79%5D%2Csource%5B%2F2c%2F9d%2F2c9d19af36b1335866bf52e0b80e2dd7fdb0806f.jpg%5D%2Corigin%5Bdam%5D%2Ccategory%5B%5D%2Ctype%5BLOOKBOOK%5D%2Cres%5Bm%5D%2Chmver%5B1%5D&call=url[file:/product/main]",
    "style": "Chinos",
    "generic name": "Trousers",
    "colors": "Dark blue",
    "descript": null,
    "item__price": "Rs. 1,999",
    "Fit": "Slim fit",
    "Composition": "Cotton 98%, Elastane 2%Pocket lining: Cotton 100%"
  },
  {
    "web-scraper-order": "1629124309-41",
    "web-scraper-start-url": "https://www2.hm.com/en_in/men/shop-by-product/trousers.html",
    "link": "Regular Fit Cropped trousers",
    "link-href": "https://www2.hm.com/en_in/productpage.0977908001.html",
    "name": "Regular Fit Cropped trousers",
    "description": "Cropped trousers in a cotton weave. Extended waistband with a hook-and-eye fastener, a zip fly and button, side pockets, welt back pockets with a button, and legs with creases. Regular Fit – a classic fit with good room for movement over the thighs and knees to create a comfortable, straight silhouette.",
    "review_count": null,
    "details": "Details\n\t\n\t\tLengthAnkle lengthFitRegular fitStyleCigarette trousersCompositionShell: Cotton 100%Pocket lining: Polyester 83%, Cotton 17%Care instructionsLine dryOnly non-chlorine bleach when neededMedium ironMachine wash at 30°Can be dry cleanedDescriptionNavy blueSolid colourPrice (MRP)Rs. 2,299 incl. of all taxesCountry of productionChinaCommon generic nameTrousersNet quantity1 NMarketed or imported byH&M Hennes & Mauritz Retail Pvt. Ltd. A-wing, D-3, 2nd Floor District Centre Saket New Delhi -110017 IndiaDate of import03-2021Date of manufactureN/AManufactured byN/ACustomer serviceIn case of consumer complaint, write to H&M Hennes & Mauritz Retail PVT. Ltd, A Wing, D3, 2nd Floor, District Center, Saket, New Delhi 110017, India or call Telephone: 0008000501633. For online and store complaints email customerservice.in@hm.com.DisclaimerThis information is based on sample of the product displayed on website. There may be change in the information on label attached to the product delivered to the customer due to size chosen, date of import, name of manufacturer (in case of manufacturing in India), country of manufacture, etc. The exact detail relevant to the product delivered to the customer will reflect in the label attached to the product so deliveredArt. No.0977908001",
    "img1-src": "//lp2.hm.com/hmgoepprod?set=quality%5B79%5D%2Csource%5B%2F6c%2F1e%2F6c1e9d466934424581f9f0c886690de8b1d617e0.jpg%5D%2Corigin%5Bdam%5D%2Ccategory%5B%5D%2Ctype%5BLOOKBOOK%5D%2Cres%5Bm%5D%2Chmver%5B1%5D&call=url[file:/product/main]",
    "img2-src": "//lp2.hm.com/hmgoepprod?set=quality%5B79%5D%2Csource%5B%2F5b%2Fb9%2F5bb9b95b8af21a58d29de00e93290d32c4d438e1.jpg%5D%2Corigin%5Bdam%5D%2Ccategory%5B%5D%2Ctype%5BLOOKBOOK%5D%2Cres%5Bm%5D%2Chmver%5B1%5D&call=url[file:/product/main]",
    "style": "Cigarette trousers",
    "generic name": "Trousers",
    "colors": "Navy blue",
    "descript": "Solid colour",
    "item__price": "Rs. 2,299",
    "Fit": "Regular fit",
    "Composition": "Shell: Cotton 100%Pocket lining: Polyester 83%, Cotton 17%"
  },
  {
    "web-scraper-order": "1629124367-60",
    "web-scraper-start-url": "https://www2.hm.com/en_in/men/shop-by-product/trousers.html",
    "link": "Regular Fit Cropped trousers",
    "link-href": "https://www2.hm.com/en_in/productpage.0977908002.html",
    "name": "Regular Fit Cropped trousers",
    "description": "Cropped trousers in a cotton weave. Extended waistband with a hook-and-eye fastener, a zip fly and button, side pockets, welt back pockets with a button, and legs with creases. Regular Fit – a classic fit with good room for movement over the thighs and knees to create a comfortable, straight silhouette.",
    "review_count": null,
    "details": "Details\n\t\n\t\tLengthAnkle lengthFitRegular fitStyleCigarette trousersCompositionPocket lining: Polyester 83%, Cotton 17%Shell: Cotton 100%Care instructionsLine dryOnly non-chlorine bleach when neededMedium ironMachine wash at 30°Can be dry cleanedDescriptionBeigeSolid colourPrice (MRP)Rs. 2,299 incl. of all taxesCountry of productionChinaCommon generic nameTrousersNet quantity1 NMarketed or imported byH&M Hennes & Mauritz Retail Pvt. Ltd. A-wing, D-3, 2nd Floor District Centre Saket New Delhi -110017 IndiaDate of import03-2021Date of manufactureN/AManufactured byN/ACustomer serviceIn case of consumer complaint, write to H&M Hennes & Mauritz Retail PVT. Ltd, A Wing, D3, 2nd Floor, District Center, Saket, New Delhi 110017, India or call Telephone: 0008000501633. For online and store complaints email customerservice.in@hm.com.DisclaimerThis information is based on sample of the product displayed on website. There may be change in the information on label attached to the product delivered to the customer due to size chosen, date of import, name of manufacturer (in case of manufacturing in India), country of manufacture, etc. The exact detail relevant to the product delivered to the customer will reflect in the label attached to the product so deliveredArt. No.0977908002",
    "img1-src": "//lp2.hm.com/hmgoepprod?set=quality%5B79%5D%2Csource%5B%2F8c%2Fae%2F8caee50baf6d55c88c1c05078c900e56a935478e.jpg%5D%2Corigin%5Bdam%5D%2Ccategory%5B%5D%2Ctype%5BLOOKBOOK%5D%2Cres%5Bm%5D%2Chmver%5B1%5D&call=url[file:/product/main]",
    "img2-src": "//lp2.hm.com/hmgoepprod?set=quality%5B79%5D%2Csource%5B%2F55%2Fc9%2F55c9e13b63f66f0e0eeb441609a440bdd2501ef6.jpg%5D%2Corigin%5Bdam%5D%2Ccategory%5B%5D%2Ctype%5BLOOKBOOK%5D%2Cres%5Bm%5D%2Chmver%5B1%5D&call=url[file:/product/main]",
    "style": "Cigarette trousers",
    "generic name": "Trousers",
    "colors": "Beige",
    "descript": "Solid colour",
    "item__price": "Rs. 2,299",
    "Fit": "Regular fit",
    "Composition": "Pocket lining: Polyester 83%, Cotton 17%Shell: Cotton 100%"
  },
  {
    "web-scraper-order": "1629124577-124",
    "web-scraper-start-url": "https://www2.hm.com/en_in/men/shop-by-product/trousers.html",
    "link": "Slim Fit Sports joggers",
    "link-href": "https://www2.hm.com/en_in/productpage.0995680002.html",
    "name": "Slim Fit Sports joggers",
    "description": "Jersey joggers for indoor and outdoor workouts. Covered elastication and a drawstring at the waist, zipped side pockets for safe storage of valuables and a mesh panel at the crotch for increased air permeability. Cuffed hems.",
    "review_count": null,
    "details": "Details\n\t\n\t\tSizeInside leg: Length: 73.5 cm (Size L/L)LengthLongWaist RiseRegular waistFitSlim fitStyleJoggersCompositionShell: Cotton 58%, Polyester 38%, Elastane 4%Mesh: Polyester 100%Care instructionsMachine wash at 40°Sports activityTrainingDescriptionBlackSolid colourNice to knowConsciousPrice (MRP)Rs. 1,999 incl. of all taxesCountry of productionCambodiaCommon generic nameTrousersNet quantity1 NMarketed or imported byH&M Hennes & Mauritz Retail Pvt. Ltd. A-wing, D-3, 2nd Floor District Centre Saket New Delhi -110017 IndiaDate of import08-2021Date of manufactureN/AManufactured byN/ACustomer serviceIn case of consumer complaint, write to H&M Hennes & Mauritz Retail PVT. Ltd, A Wing, D3, 2nd Floor, District Center, Saket, New Delhi 110017, India or call Telephone: 0008000501633. For online and store complaints email customerservice.in@hm.com.DisclaimerThis information is based on sample of the product displayed on website. There may be change in the information on label attached to the product delivered to the customer due to size chosen, date of import, name of manufacturer (in case of manufacturing in India), country of manufacture, etc. The exact detail relevant to the product delivered to the customer will reflect in the label attached to the product so deliveredArt. No.0995680002",
    "img1-src": "//lp2.hm.com/hmgoepprod?set=quality%5B79%5D%2Csource%5B%2F8e%2F96%2F8e96545b60407d8f52bc07954c1b049a5a5c91ba.jpg%5D%2Corigin%5Bdam%5D%2Ccategory%5B%5D%2Ctype%5BLOOKBOOK%5D%2Cres%5Bm%5D%2Chmver%5B1%5D&call=url[file:/product/main]",
    "img2-src": "//lp2.hm.com/hmgoepprod?set=quality%5B79%5D%2Csource%5B%2F42%2Fbb%2F42bb3aa71866c846c9256929387777b352526d1a.jpg%5D%2Corigin%5Bdam%5D%2Ccategory%5B%5D%2Ctype%5BLOOKBOOK%5D%2Cres%5Bm%5D%2Chmver%5B1%5D&call=url[file:/product/main]",
    "style": "Joggers",
    "generic name": "Trousers",
    "colors": "Black",
    "descript": "Mesh: Polyester 100%",
    "item__price": "Rs. 1,999",
    "Fit": "Slim fit",
    "Composition": "Shell: Cotton 58%, Polyester 38%, Elastane 4%Mesh: Polyester 100%"
  },
  {
    "web-scraper-order": "1629124570-122",
    "web-scraper-start-url": "https://www2.hm.com/en_in/men/shop-by-product/trousers.html",
    "link": "Wide cotton trousers",
    "link-href": "https://www2.hm.com/en_in/productpage.0881721001.html",
    "name": "Wide cotton trousers",
    "description": "SABYASACHI x H&M. Wide chinos in lightweight cotton twill with a high waist, concealed button in the waistband and zip fly. Side pockets, jetted back pockets and pleats at the top to create extra-wide legs.",
    "review_count": null,
    "details": "Details\n\t\n\t\tLengthLongWaist RiseHigh waistStyleChinosCompositionCotton 97%, Elastane 3%Care instructionsMachine wash at 40°MaterialCottonDescriptionDark khaki beigeSolid colourCollectionSabyasachi x H&MPrice (MRP)Rs. 3,499 incl. of all taxesCountry of productionIndiaCommon generic nameTrousersSize: 46Width: 84 cmLength: 1.04 mSize: 48Width: 88 cmLength: 1.05 mSize: 50Width: 91 cmLength: 1.06 mSize: 52Width: 95 cmLength: 1.07 mNet quantity1 NDate of manufacture05-2020Manufactured byGLOBAL MODE AND ACCESSORIES PVT. LTD.\nD 34, Sector 63,, 201301, NoidaCustomer serviceIn case of consumer complaint, write to H&M Hennes & Mauritz Retail PVT. Ltd, A Wing, D3, 2nd Floor, District Center, Saket, New Delhi 110017, India or call Telephone: 0008000501633. For online and store complaints email customerservice.in@hm.com.DisclaimerThis information is based on sample of the product displayed on website. There may be change in the information on label attached to the product delivered to the customer due to size chosen, date of import, name of manufacturer (in case of manufacturing in India), country of manufacture, etc. The exact detail relevant to the product delivered to the customer will reflect in the label attached to the product so deliveredArt. No.0881721001",
    "img1-src": "//lp2.hm.com/hmgoepprod?set=quality%5B79%5D%2Csource%5B%2F82%2F1c%2F821c08d79c762e9022d0719f0770a77b42a7d760.jpg%5D%2Corigin%5Bdam%5D%2Ccategory%5Bladies_trousers_chinosslacks%5D%2Ctype%5BLOOKBOOK%5D%2Cres%5Bm%5D%2Chmver%5B1%5D&call=url[file:/product/main]",
    "img2-src": "//lp2.hm.com/hmgoepprod?set=quality%5B79%5D%2Csource%5B%2F7c%2Ff6%2F7cf620c5ddd871a526e1944e9c38bc24928cbe43.jpg%5D%2Corigin%5Bdam%5D%2Ccategory%5Bladies_trousers_chinosslacks%5D%2Ctype%5BLOOKBOOK%5D%2Cres%5Bm%5D%2Chmver%5B1%5D&call=url[file:/product/main]",
    "style": "Chinos",
    "generic name": "Trousers",
    "colors": "Dark khaki beige",
    "descript": null,
    "item__price": "Rs. 3,499",
    "Fit": null,
    "Composition": "Cotton 97%, Elastane 3%"
  },
  {
    "web-scraper-order": "1629124469-90",
    "web-scraper-start-url": "https://www2.hm.com/en_in/men/shop-by-product/trousers.html",
    "link": "Slim Fit Chinos",
    "link-href": "https://www2.hm.com/en_in/productpage.0815456044.html",
    "name": "Slim Fit Chinos",
    "description": "Chinos in extra-stretchy cotton twill with a zip fly, side pockets, a coin pocket and welt back pockets with a button. Slim Fit – a fit that is close-fitting at the thighs, knees and ankles to create a fitted silhouette.",
    "review_count": null,
    "details": "Details\n\t\n\t\tLengthLongFitSlim fitStyleChinosCompositionCotton 98%, Elastane 2%Pocket lining: Cotton 100%Care instructionsMachine wash at 40°MaterialCottonDescriptionBeigeSolid colourPrice (MRP)Rs. 1,999 incl. of all taxesCountry of productionBangladeshCommon generic nameTrousersNet quantity1 NMarketed or imported byH&M Hennes & Mauritz Retail Pvt. Ltd. A-wing, D-3, 2nd Floor District Centre Saket New Delhi -110017 IndiaDate of import06-2021Date of manufactureN/AManufactured byN/ACustomer serviceIn case of consumer complaint, write to H&M Hennes & Mauritz Retail PVT. Ltd, A Wing, D3, 2nd Floor, District Center, Saket, New Delhi 110017, India or call Telephone: 0008000501633. For online and store complaints email customerservice.in@hm.com.DisclaimerThis information is based on sample of the product displayed on website. There may be change in the information on label attached to the product delivered to the customer due to size chosen, date of import, name of manufacturer (in case of manufacturing in India), country of manufacture, etc. The exact detail relevant to the product delivered to the customer will reflect in the label attached to the product so deliveredArt. No.0815456044",
    "img1-src": "//lp2.hm.com/hmgoepprod?set=quality%5B79%5D%2Csource%5B%2F9e%2Fd2%2F9ed2868d56bf1249f52d2ad1be82926ba70fe8c9.jpg%5D%2Corigin%5Bdam%5D%2Ccategory%5B%5D%2Ctype%5BLOOKBOOK%5D%2Cres%5Bm%5D%2Chmver%5B1%5D&call=url[file:/product/main]",
    "img2-src": "//lp2.hm.com/hmgoepprod?set=quality%5B79%5D%2Csource%5B%2F33%2F19%2F3319f5e0465ba86a677ee245bd3c4f8ff17c5b89.jpg%5D%2Corigin%5Bdam%5D%2Ccategory%5B%5D%2Ctype%5BLOOKBOOK%5D%2Cres%5Bm%5D%2Chmver%5B1%5D&call=url[file:/product/main]",
    "style": "Chinos",
    "generic name": "Trousers",
    "colors": "Beige",
    "descript": null,
    "item__price": "Rs. 1,999",
    "Fit": "Slim fit",
    "Composition": "Cotton 98%, Elastane 2%Pocket lining: Cotton 100%"
  },
  {
    "web-scraper-order": "1629124495-98",
    "web-scraper-start-url": "https://www2.hm.com/en_in/men/shop-by-product/trousers.html",
    "link": "Printed joggers",
    "link-href": "https://www2.hm.com/en_in/productpage.0787035018.html",
    "name": "Printed joggers",
    "description": "Joggers in printed sweatshirt fabric made from a cotton blend with covered elastication and a drawstring at the waist, side pockets, a back pocket and tapered legs with ribbed hems. Soft brushed inside.",
    "review_count": null,
    "details": "Details\n\t\n\t\tLengthLongStyleSweatpantsJoggersCompositionCotton 60%, Polyester 40%Care instructionsMachine wash at 40°DescriptionBlack/White/RedKeith HaringConceptDIVIDEDPrice (MRP)Rs. 2,299 incl. of all taxesCountry of productionIndonesiaCommon generic nameTrousersNet quantity1 NMarketed or imported byH&M Hennes & Mauritz Retail Pvt. Ltd. A-wing, D-3, 2nd Floor District Centre Saket New Delhi -110017 IndiaDate of import05-2021Date of manufactureN/AManufactured byN/ACustomer serviceIn case of consumer complaint, write to H&M Hennes & Mauritz Retail PVT. Ltd, A Wing, D3, 2nd Floor, District Center, Saket, New Delhi 110017, India or call Telephone: 0008000501633. For online and store complaints email customerservice.in@hm.com.DisclaimerThis information is based on sample of the product displayed on website. There may be change in the information on label attached to the product delivered to the customer due to size chosen, date of import, name of manufacturer (in case of manufacturing in India), country of manufacture, etc. The exact detail relevant to the product delivered to the customer will reflect in the label attached to the product so deliveredArt. No.0787035018",
    "img1-src": "//lp2.hm.com/hmgoepprod?set=quality%5B79%5D%2Csource%5B%2F08%2F74%2F0874e34df0b47c8074b836a8ad6e312d5c1aedc2.jpg%5D%2Corigin%5Bdam%5D%2Ccategory%5B%5D%2Ctype%5BLOOKBOOK%5D%2Cres%5Bm%5D%2Chmver%5B1%5D&call=url[file:/product/main]",
    "img2-src": "//lp2.hm.com/hmgoepprod?set=quality%5B79%5D%2Csource%5B%2Fb9%2F7b%2Fb97bf7efd717ebb22d18a378c4db540d6510e9d8.jpg%5D%2Corigin%5Bdam%5D%2Ccategory%5B%5D%2Ctype%5BLOOKBOOK%5D%2Cres%5Bm%5D%2Chmver%5B1%5D&call=url[file:/product/main]",
    "style": "Sweatpants",
    "generic name": "Trousers",
    "colors": "Black/White/Red",
    "descript": null,
    "item__price": "Rs. 2,299",
    "Fit": null,
    "Composition": "Cotton 60%, Polyester 40%"
  },
  {
    "web-scraper-order": "1629124429-78",
    "web-scraper-start-url": "https://www2.hm.com/en_in/men/shop-by-product/trousers.html",
    "link": "Joggers",
    "link-href": "https://www2.hm.com/en_in/productpage.0441386001.html",
    "name": "Joggers",
    "description": "Joggers in sweatshirt fabric with an elasticated drawstring waist, zipped side pockets, a low crotch and tapered legs with seams at the knees and ribbed hems.",
    "review_count": "(117)",
    "details": "Details\n\t\n\t\tLengthLongStyleJoggersCompositionCotton 60%, Polyester 40%Care instructionsMachine wash at 40°DescriptionSolid colourConceptDIVIDEDNice to knowConsciousPrice (MRP)Rs. 1,999 incl. of all taxesCountry of productionIndonesiaCommon generic nameTrousersSize: XS/LWidth: 70 cmLength: 71 cmSize: S/LWidth: 77 cmLength: 71 cmSize: M/LWidth: 84 cmLength: 73 cmSize: L/LWidth: 91 cmLength: 73 cmSize: XL/LWidth: 98 cmLength: 75 cmSize: XXL/LWidth: 1.05 mLength: 75 cmSize: XXLWidth: 1.05 mLength: 68 cmNet quantity1 NMarketed or imported byH&M Hennes & Mauritz Retail Pvt. Ltd. A-wing, D-3, 2nd Floor District Centre Saket New Delhi -110017 IndiaDate of import01-2021Date of manufactureN/AManufactured byN/ACustomer serviceIn case of consumer complaint, write to H&M Hennes & Mauritz Retail PVT. Ltd, A Wing, D3, 2nd Floor, District Center, Saket, New Delhi 110017, India or call Telephone: 0008000501633. For online and store complaints email customerservice.in@hm.com.DisclaimerThis information is based on sample of the product displayed on website. There may be change in the information on label attached to the product delivered to the customer due to size chosen, date of import, name of manufacturer (in case of manufacturing in India), country of manufacture, etc. The exact detail relevant to the product delivered to the customer will reflect in the label attached to the product so deliveredArt. No.0441386001",
    "img1-src": "//lp2.hm.com/hmgoepprod?set=quality%5B79%5D%2Csource%5B%2Fe7%2F10%2Fe710eff54960d82dff0e0f70293ed4ec2f847d5b.jpg%5D%2Corigin%5Bdam%5D%2Ccategory%5Bmen_trousers_joggers%5D%2Ctype%5BDESCRIPTIVESTILLLIFE%5D%2Cres%5Bm%5D%2Chmver%5B1%5D&call=url[file:/product/main]",
    "img2-src": "//lp2.hm.com/hmgoepprod?set=quality%5B79%5D%2Csource%5B%2F71%2F76%2F7176cc90ed67370974c181ebc9fede2f66f00085.jpg%5D%2Corigin%5Bdam%5D%2Ccategory%5Bmen_trousers_joggers%5D%2Ctype%5BDESCRIPTIVEDETAIL%5D%2Cres%5Bm%5D%2Chmver%5B1%5D&call=url[file:/product/main]",
    "style": "Joggers",
    "generic name": "Trousers",
    "colors": "Solid colour",
    "descript": null,
    "item__price": "Rs. 1,999",
    "Fit": null,
    "Composition": "Cotton 60%, Polyester 40%"
  },
  {
    "web-scraper-order": "1629124364-59",
    "web-scraper-start-url": "https://www2.hm.com/en_in/men/shop-by-product/trousers.html",
    "link": "Slim Fit Cropped trousers",
    "link-href": "https://www2.hm.com/en_in/productpage.0991309005.html",
    "name": "Slim Fit Cropped trousers",
    "description": "Cropped trousers in woven fabric with a concealed hook-and-eye fastening and button in the waistband and a zip fly. Side pockets, welt back pockets with a button, and legs with creases. Slim Fit – a fit that is close-fitting at the thighs and knees to create a fitted silhouette.",
    "review_count": null,
    "details": "Details\n\t\n\t\tLengthAnkle lengthWaist RiseRegular waistFitSlim fitStyleCigarette trousersCompositionPolyester 82%, Viscose 16%, Elastane 2%Care instructionsMachine wash at 30°DescriptionBlack/Beige/Grey/WhiteCheckedConceptH&M MANNice to knowConsciousPrice (MRP)Rs. 1,499 incl. of all taxesCountry of productionChinaCommon generic nameTrousersNet quantity1 NMarketed or imported byH&M Hennes & Mauritz Retail Pvt. Ltd. A-wing, D-3, 2nd Floor District Centre Saket New Delhi -110017 IndiaDate of import06-2021Date of manufactureN/AManufactured byN/ACustomer serviceIn case of consumer complaint, write to H&M Hennes & Mauritz Retail PVT. Ltd, A Wing, D3, 2nd Floor, District Center, Saket, New Delhi 110017, India or call Telephone: 0008000501633. For online and store complaints email customerservice.in@hm.com.DisclaimerThis information is based on sample of the product displayed on website. There may be change in the information on label attached to the product delivered to the customer due to size chosen, date of import, name of manufacturer (in case of manufacturing in India), country of manufacture, etc. The exact detail relevant to the product delivered to the customer will reflect in the label attached to the product so deliveredArt. No.0991309005",
    "img1-src": "//lp2.hm.com/hmgoepprod?set=quality%5B79%5D%2Csource%5B%2Fcf%2F6d%2Fcf6d29a947ea38ce20542da3b1cef8ab3b4ce984.jpg%5D%2Corigin%5Bdam%5D%2Ccategory%5B%5D%2Ctype%5BLOOKBOOK%5D%2Cres%5Bm%5D%2Chmver%5B1%5D&call=url[file:/product/main]",
    "img2-src": "//lp2.hm.com/hmgoepprod?set=quality%5B79%5D%2Csource%5B%2F73%2Fc2%2F73c20f5af6bd24b083f9ef51a6e86b837224c94e.jpg%5D%2Corigin%5Bdam%5D%2Ccategory%5B%5D%2Ctype%5BLOOKBOOK%5D%2Cres%5Bm%5D%2Chmver%5B1%5D&call=url[file:/product/main]",
    "style": "Cigarette trousers",
    "generic name": "Trousers",
    "colors": "Black/Beige/Grey/White",
    "descript": null,
    "item__price": "Rs. 1,499",
    "Fit": "Slim fit",
    "Composition": "Polyester 82%, Viscose 16%, Elastane 2%"
  },
  {
    "web-scraper-order": "1629124371-61",
    "web-scraper-start-url": "https://www2.hm.com/en_in/men/shop-by-product/trousers.html",
    "link": "Suit trousers Skinny Fit",
    "link-href": "https://www2.hm.com/en_in/productpage.0714032002.html",
    "name": "Suit trousers Skinny Fit",
    "description": "Suit trousers in a stretch weave with a concealed hook-and-eye fastener and zip fly. Side pockets, welt back pockets and legs with creases. Skinny fit – a fit with slightly shorter legs that is close-fitting at the thighs, knees and ankles to create a completely fitted silhouette.",
    "review_count": null,
    "details": "Details\n\t\n\t\tLengthLongFitSkinny fitStyleSuit trousersCompositionPolyester 68%, Viscose 31%, Elastane 1%More sustainable materialsRecycled polyester 68%Care instructionsMachine wash at 30°DescriptionBlackSolid colourConceptH&M MANNice to knowConsciousPrice (MRP)Rs. 2,299 incl. of all taxesCountry of productionMyanmarCommon generic nameTrousersSize: 54Width: 97 cmLength: 74 cmSize: 44LWidth: 80 cmLength: 76 cmSize: 46LWidth: 83 cmLength: 76 cmSize: 48LWidth: 87 cmLength: 77 cmSize: 50LWidth: 90 cmLength: 77 cmSize: 52LWidth: 93 cmLength: 78 cmSize: 54LWidth: 97 cmLength: 78 cmNet quantity1 NMarketed or imported byH&M Hennes & Mauritz Retail Pvt. Ltd. A-wing, D-3, 2nd Floor District Centre Saket New Delhi -110017 IndiaDate of import04-2021Date of manufactureN/AManufactured byN/ACustomer serviceIn case of consumer complaint, write to H&M Hennes & Mauritz Retail PVT. Ltd, A Wing, D3, 2nd Floor, District Center, Saket, New Delhi 110017, India or call Telephone: 0008000501633. For online and store complaints email customerservice.in@hm.com.DisclaimerThis information is based on sample of the product displayed on website. There may be change in the information on label attached to the product delivered to the customer due to size chosen, date of import, name of manufacturer (in case of manufacturing in India), country of manufacture, etc. The exact detail relevant to the product delivered to the customer will reflect in the label attached to the product so deliveredArt. No.0714032002",
    "img1-src": "//lp2.hm.com/hmgoepprod?set=quality%5B79%5D%2Csource%5B%2Ff5%2F68%2Ff568fc4e7f174a8cb581a55cdb9a2056ca5f1459.jpg%5D%2Corigin%5Bdam%5D%2Ccategory%5Bmen_trousers_dressed%5D%2Ctype%5BLOOKBOOK%5D%2Cres%5Bm%5D%2Chmver%5B1%5D&call=url[file:/product/main]",
    "img2-src": "//lp2.hm.com/hmgoepprod?set=quality%5B79%5D%2Csource%5B%2Fa1%2F38%2Fa1381ecd4ab36c5a1e7f968b4f09da5f1579d5b7.jpg%5D%2Corigin%5Bdam%5D%2Ccategory%5Bmen_trousers_dressed%5D%2Ctype%5BLOOKBOOK%5D%2Cres%5Bm%5D%2Chmver%5B1%5D&call=url[file:/product/main]",
    "style": "Suit trousers",
    "generic name": "Trousers",
    "colors": "Black",
    "descript": null,
    "item__price": "Rs. 2,299",
    "Fit": "Skinny fit",
    "Composition": "Polyester 68%, Viscose 31%, Elastane 1%"
  },
  {
    "web-scraper-order": "1629124329-48",
    "web-scraper-start-url": "https://www2.hm.com/en_in/men/shop-by-product/trousers.html",
    "link": "Regular Fit Suit trousers",
    "link-href": "https://www2.hm.com/en_in/productpage.0929428001.html",
    "name": "Regular Fit Suit trousers",
    "description": "Suit trousers in woven fabric with a zip fly and waistband with a button and hook-and-eye fastener. Diagonal side pockets, welt back pockets and legs with creases. Regular Fit – a classic fit with good room for movement over the thighs and knees to create a comfortable, straight silhouette.",
    "review_count": null,
    "details": "Details\n\t\n\t\tSizeWaist: Circumference: 95.0 cm (Size 52L)Outside leg: Length: 102.2 cm (Size 52L)Inside leg: Length: 77.0 cm (Size 52L)LengthLongFitRegular fitStyleSuit trousersCompositionShell: Polyester 75%, Viscose 23%, Elastane 2%Pocket lining: Polyester 80%, Cotton 20%DescriptionDark blueSolid colourConceptH&M MANNice to knowConsciousPrice (MRP)Rs. 2,299 incl. of all taxesCountry of productionIndonesiaCommon generic nameTrousersNet quantity1 NMarketed or imported byH&M Hennes & Mauritz Retail Pvt. Ltd. A-wing, D-3, 2nd Floor District Centre Saket New Delhi -110017 IndiaDate of import02-2021Date of manufactureN/AManufactured byN/ACustomer serviceIn case of consumer complaint, write to H&M Hennes & Mauritz Retail PVT. Ltd, A Wing, D3, 2nd Floor, District Center, Saket, New Delhi 110017, India or call Telephone: 0008000501633. For online and store complaints email customerservice.in@hm.com.DisclaimerThis information is based on sample of the product displayed on website. There may be change in the information on label attached to the product delivered to the customer due to size chosen, date of import, name of manufacturer (in case of manufacturing in India), country of manufacture, etc. The exact detail relevant to the product delivered to the customer will reflect in the label attached to the product so deliveredArt. No.0929428001",
    "img1-src": "//lp2.hm.com/hmgoepprod?set=quality%5B79%5D%2Csource%5B%2F20%2Faf%2F20afbbe7f997e25847e676a7ffda5c953a065337.jpg%5D%2Corigin%5Bdam%5D%2Ccategory%5B%5D%2Ctype%5BLOOKBOOK%5D%2Cres%5Bm%5D%2Chmver%5B1%5D&call=url[file:/product/main]",
    "img2-src": "//lp2.hm.com/hmgoepprod?set=quality%5B79%5D%2Csource%5B%2Fb4%2F85%2Fb485881f5c9c546448d12f7bdb2627c124201e3f.jpg%5D%2Corigin%5Bdam%5D%2Ccategory%5B%5D%2Ctype%5BLOOKBOOK%5D%2Cres%5Bm%5D%2Chmver%5B1%5D&call=url[file:/product/main]",
    "style": "Suit trousers",
    "generic name": "Trousers",
    "colors": "Dark blue",
    "descript": "Solid colour",
    "item__price": "Rs. 2,299",
    "Fit": "Regular fit",
    "Composition": "Shell: Polyester 75%, Viscose 23%, Elastane 2%Pocket lining: Polyester 80%, Cotton 20%"
  },
  {
    "web-scraper-order": "1629124358-57",
    "web-scraper-start-url": "https://www2.hm.com/en_in/men/shop-by-product/trousers.html",
    "link": "Skinny Fit Cotton chinos",
    "link-href": "https://www2.hm.com/en_in/productpage.1007196001.html",
    "name": "Skinny Fit Cotton chinos",
    "description": "Chinos in stretch cotton twill with a zip fly and button, diagonal side pockets and welt back pockets with a button. Skinny Fit – a fit with slightly shorter legs that is close-fitting at the thighs, knees and ankles to create a completely fitted silhouette.",
    "review_count": null,
    "details": "Details\n\t\n\t\tLengthLongWaist RiseRegular waistFitSkinny fitStyleChinosCompositionShell: Cotton 98%, Elastane 2%Pocket: Cotton 100%Care instructionsMachine wash at 40°DescriptionNavy blueSolid colourNice to knowConsciousPrice (MRP)Rs. 1,999 incl. of all taxesCountry of productionBangladeshCommon generic nameTrousersNet quantity1 NMarketed or imported byH&M Hennes & Mauritz Retail Pvt. Ltd. A-wing, D-3, 2nd Floor District Centre Saket New Delhi -110017 IndiaDate of import06-2021Date of manufactureN/AManufactured byN/ACustomer serviceIn case of consumer complaint, write to H&M Hennes & Mauritz Retail PVT. Ltd, A Wing, D3, 2nd Floor, District Center, Saket, New Delhi 110017, India or call Telephone: 0008000501633. For online and store complaints email customerservice.in@hm.com.DisclaimerThis information is based on sample of the product displayed on website. There may be change in the information on label attached to the product delivered to the customer due to size chosen, date of import, name of manufacturer (in case of manufacturing in India), country of manufacture, etc. The exact detail relevant to the product delivered to the customer will reflect in the label attached to the product so deliveredArt. No.1007196001",
    "img1-src": "//lp2.hm.com/hmgoepprod?set=quality%5B79%5D%2Csource%5B%2F42%2F13%2F4213d0cde5f98026c922096c354031240bc59dcb.jpg%5D%2Corigin%5Bdam%5D%2Ccategory%5B%5D%2Ctype%5BLOOKBOOK%5D%2Cres%5Bm%5D%2Chmver%5B1%5D&call=url[file:/product/main]",
    "img2-src": "//lp2.hm.com/hmgoepprod?set=quality%5B79%5D%2Csource%5B%2Fb9%2F0a%2Fb90ac3a0c1fcdd50ea7bdf5956b78fdf2e69ac28.jpg%5D%2Corigin%5Bdam%5D%2Ccategory%5B%5D%2Ctype%5BLOOKBOOK%5D%2Cres%5Bm%5D%2Chmver%5B1%5D&call=url[file:/product/main]",
    "style": "Chinos",
    "generic name": "Trousers",
    "colors": "Navy blue",
    "descript": null,
    "item__price": "Rs. 1,999",
    "Fit": "Skinny fit",
    "Composition": "Shell: Cotton 98%, Elastane 2%Pocket: Cotton 100%"
  },
  {
    "web-scraper-order": "1629124482-94",
    "web-scraper-start-url": "https://www2.hm.com/en_in/men/shop-by-product/trousers.html",
    "link": "Regular Fit Twill joggers",
    "link-href": "https://www2.hm.com/en_in/productpage.0975244003.html",
    "name": "Regular Fit Twill joggers",
    "description": "Joggers in stretch cotton twill with covered elastication and a drawstring at the waist and a fake fly. Side pockets, back pockets with a button and covered elastication at the hems. Regular Fit – a classic fit with good room for movement over the thighs and knees to create a comfortable, straight silhouette.",
    "review_count": null,
    "details": "Details\n\t\n\t\tSizeInside leg: Length: 76.0 cm (Size L/L)LengthLongWaist RiseRegular waistFitRegular fitStyleJoggersCompositionPocket lining: Cotton 100%Shell: Cotton 98%, Elastane 2%Care instructionsMachine wash at 40°MaterialCottonDescriptionDark khaki greenSolid colourNice to knowConsciousPrice (MRP)Rs. 1,499 incl. of all taxesCountry of productionBangladeshCommon generic nameTrousersNet quantity1 NMarketed or imported byH&M Hennes & Mauritz Retail Pvt. Ltd. A-wing, D-3, 2nd Floor District Centre Saket New Delhi -110017 IndiaDate of import05-2021Date of manufactureN/AManufactured byN/ACustomer serviceIn case of consumer complaint, write to H&M Hennes & Mauritz Retail PVT. Ltd, A Wing, D3, 2nd Floor, District Center, Saket, New Delhi 110017, India or call Telephone: 0008000501633. For online and store complaints email customerservice.in@hm.com.DisclaimerThis information is based on sample of the product displayed on website. There may be change in the information on label attached to the product delivered to the customer due to size chosen, date of import, name of manufacturer (in case of manufacturing in India), country of manufacture, etc. The exact detail relevant to the product delivered to the customer will reflect in the label attached to the product so deliveredArt. No.0975244003",
    "img1-src": "//lp2.hm.com/hmgoepprod?set=quality%5B79%5D%2Csource%5B%2F68%2F6c%2F686c3d66aa72c775f871667e458923124291db18.jpg%5D%2Corigin%5Bdam%5D%2Ccategory%5B%5D%2Ctype%5BLOOKBOOK%5D%2Cres%5Bm%5D%2Chmver%5B1%5D&call=url[file:/product/main]",
    "img2-src": "//lp2.hm.com/hmgoepprod?set=quality%5B79%5D%2Csource%5B%2F25%2F9d%2F259d25808150320915a3880c3b037b0739f0d870.jpg%5D%2Corigin%5Bdam%5D%2Ccategory%5B%5D%2Ctype%5BLOOKBOOK%5D%2Cres%5Bm%5D%2Chmver%5B1%5D&call=url[file:/product/main]",
    "style": "Joggers",
    "generic name": "Trousers",
    "colors": "Dark khaki green",
    "descript": "Shell: Cotton 98%, Elastane 2%",
    "item__price": "Rs. 1,499",
    "Fit": "Regular fit",
    "Composition": "Pocket lining: Cotton 100%Shell: Cotton 98%, Elastane 2%"
  },
  {
    "web-scraper-order": "1629124326-47",
    "web-scraper-start-url": "https://www2.hm.com/en_in/men/shop-by-product/trousers.html",
    "link": "Sports trousers",
    "link-href": "https://www2.hm.com/en_in/productpage.0890677004.html",
    "name": "Sports trousers",
    "description": "Sports trousers in fast-drying functional fabric with an elasticated, drawstring waist, diagonal side pockets with a zip, and slim, tapered legs with cuffed hems.",
    "review_count": null,
    "details": "Details\n\t\n\t\tLengthLongWaist RiseRegular waistStyleTaperedFunctionsQuick dryCompositionPolyester 92%, Elastane 8%Care instructionsMachine wash at 40°Sports activityTrainingDescriptionDark grey marlPrice (MRP)Rs. 1,999 incl. of all taxesCountry of productionChinaCommon generic nameTrousersNet quantity1 NMarketed or imported byH&M Hennes & Mauritz Retail Pvt. Ltd. A-wing, D-3, 2nd Floor District Centre Saket New Delhi -110017 IndiaDate of import02-2021Date of manufactureN/AManufactured byN/ACustomer serviceIn case of consumer complaint, write to H&M Hennes & Mauritz Retail PVT. Ltd, A Wing, D3, 2nd Floor, District Center, Saket, New Delhi 110017, India or call Telephone: 0008000501633. For online and store complaints email customerservice.in@hm.com.DisclaimerThis information is based on sample of the product displayed on website. There may be change in the information on label attached to the product delivered to the customer due to size chosen, date of import, name of manufacturer (in case of manufacturing in India), country of manufacture, etc. The exact detail relevant to the product delivered to the customer will reflect in the label attached to the product so deliveredArt. No.0890677004",
    "img1-src": "//lp2.hm.com/hmgoepprod?set=quality%5B79%5D%2Csource%5B%2Fab%2Fa8%2Faba81d83ae220fb7eb801256fff9cc8caa6b2052.jpg%5D%2Corigin%5Bdam%5D%2Ccategory%5Bmen_sport_bottoms%5D%2Ctype%5BDESCRIPTIVESTILLLIFE%5D%2Cres%5Bm%5D%2Chmver%5B1%5D&call=url[file:/product/main]",
    "img2-src": "//lp2.hm.com/hmgoepprod?set=quality%5B79%5D%2Csource%5B%2Fb6%2F70%2Fb6701d45eaf8cd9725201b5cd9058be98a769a5c.jpg%5D%2Corigin%5Bdam%5D%2Ccategory%5Bmen_sport_bottoms%5D%2Ctype%5BDESCRIPTIVEDETAIL%5D%2Cres%5Bm%5D%2Chmver%5B1%5D&call=url[file:/product/main]",
    "style": "Tapered",
    "generic name": "Trousers",
    "colors": "Dark grey marl",
    "descript": null,
    "item__price": "Rs. 1,999",
    "Fit": null,
    "Composition": "Polyester 92%, Elastane 8%"
  },
  {
    "web-scraper-order": "1629124425-77",
    "web-scraper-start-url": "https://www2.hm.com/en_in/men/shop-by-product/trousers.html",
    "link": "Slim Fit Trousers",
    "link-href": "https://www2.hm.com/en_in/productpage.0991256001.html",
    "name": "Slim Fit Trousers",
    "description": "Crease-leg trousers in woven fabric with a concealed hook-and-eye fastening and button on the waistband and a zip fly. Diagonal side pockets and jetted back pockets with a button. Slim Fit – a fit that is close-fitting at the thighs and knees to create a fitted silhouette.",
    "review_count": "(1)",
    "details": "Details\n\t\n\t\tLengthLongWaist RiseRegular waistFitSlim fitStyleCigarette trousersCompositionPolyester 68%, Viscose 28%, Elastane 4%Care instructionsMachine wash at 30°DescriptionBlackSolid colourConceptH&M MANNice to knowConsciousPrice (MRP)Rs. 2,299 incl. of all taxesCountry of productionIndonesiaCommon generic nameTrousersNet quantity1 NMarketed or imported byH&M Hennes & Mauritz Retail Pvt. Ltd. A-wing, D-3, 2nd Floor District Centre Saket New Delhi -110017 IndiaDate of import06-2021Date of manufactureN/AManufactured byN/ACustomer serviceIn case of consumer complaint, write to H&M Hennes & Mauritz Retail PVT. Ltd, A Wing, D3, 2nd Floor, District Center, Saket, New Delhi 110017, India or call Telephone: 0008000501633. For online and store complaints email customerservice.in@hm.com.DisclaimerThis information is based on sample of the product displayed on website. There may be change in the information on label attached to the product delivered to the customer due to size chosen, date of import, name of manufacturer (in case of manufacturing in India), country of manufacture, etc. The exact detail relevant to the product delivered to the customer will reflect in the label attached to the product so deliveredArt. No.0991256001",
    "img1-src": "//lp2.hm.com/hmgoepprod?set=quality%5B79%5D%2Csource%5B%2Fd2%2F7e%2Fd27e8c5fa415207f921168e77e10f12877c9f2b9.jpg%5D%2Corigin%5Bdam%5D%2Ccategory%5B%5D%2Ctype%5BLOOKBOOK%5D%2Cres%5Bm%5D%2Chmver%5B1%5D&call=url[file:/product/main]",
    "img2-src": "//lp2.hm.com/hmgoepprod?set=quality%5B79%5D%2Csource%5B%2F88%2F9b%2F889bf875fc2135018bc2d667312621b818110b41.jpg%5D%2Corigin%5Bdam%5D%2Ccategory%5B%5D%2Ctype%5BLOOKBOOK%5D%2Cres%5Bm%5D%2Chmver%5B1%5D&call=url[file:/product/main]",
    "style": "Cigarette trousers",
    "generic name": "Trousers",
    "colors": "Black",
    "descript": null,
    "item__price": "Rs. 2,299",
    "Fit": "Slim fit",
    "Composition": "Polyester 68%, Viscose 28%, Elastane 4%"
  },
  {
    "web-scraper-order": "1629124489-96",
    "web-scraper-start-url": "https://www2.hm.com/en_in/men/shop-by-product/trousers.html",
    "link": "Cargo joggers",
    "link-href": "https://www2.hm.com/en_in/productpage.1002227004.html",
    "name": "Cargo joggers",
    "description": "Joggers in a cotton weave with covered elastication and a drawstring at the waist, diagonal side pockets and flap back and leg pockets with concealed press-studs. Tapered legs with seams and darts at the knees and covered elastication at the hems.",
    "review_count": null,
    "details": "Details\n\t\n\t\tSizeInside leg: Length: 75.0 cm (Size L/L)LengthLongWaist RiseRegular waistStyleCargoTaperedJoggersCompositionShell: Cotton 98%, Elastane 2%Pocket lining: Cotton 100%Care instructionsMachine wash at 40°MaterialCottonDescriptionBeigeSolid colourNice to knowConsciousPrice (MRP)Rs. 2,699 incl. of all taxesCountry of productionBangladeshCommon generic nameTrousersNet quantity1 NMarketed or imported byH&M Hennes & Mauritz Retail Pvt. Ltd. A-wing, D-3, 2nd Floor District Centre Saket New Delhi -110017 IndiaDate of import06-2021Date of manufactureN/AManufactured byN/ACustomer serviceIn case of consumer complaint, write to H&M Hennes & Mauritz Retail PVT. Ltd, A Wing, D3, 2nd Floor, District Center, Saket, New Delhi 110017, India or call Telephone: 0008000501633. For online and store complaints email customerservice.in@hm.com.DisclaimerThis information is based on sample of the product displayed on website. There may be change in the information on label attached to the product delivered to the customer due to size chosen, date of import, name of manufacturer (in case of manufacturing in India), country of manufacture, etc. The exact detail relevant to the product delivered to the customer will reflect in the label attached to the product so deliveredArt. No.1002227004",
    "img1-src": "//lp2.hm.com/hmgoepprod?set=quality%5B79%5D%2Csource%5B%2Ffd%2F79%2Ffd79f088787400efb6957ddddfc837578537d4ab.jpg%5D%2Corigin%5Bdam%5D%2Ccategory%5B%5D%2Ctype%5BLOOKBOOK%5D%2Cres%5Bm%5D%2Chmver%5B1%5D&call=url[file:/product/main]",
    "img2-src": "//lp2.hm.com/hmgoepprod?set=quality%5B79%5D%2Csource%5B%2F8c%2F14%2F8c141ced0886f1fb59f92d373e7e846b101d539a.jpg%5D%2Corigin%5Bdam%5D%2Ccategory%5B%5D%2Ctype%5BLOOKBOOK%5D%2Cres%5Bm%5D%2Chmver%5B1%5D&call=url[file:/product/main]",
    "style": "Cargo",
    "generic name": "Trousers",
    "colors": "Beige",
    "descript": null,
    "item__price": "Rs. 2,699",
    "Fit": null,
    "Composition": "Shell: Cotton 98%, Elastane 2%Pocket lining: Cotton 100%"
  },
  {
    "web-scraper-order": "1629124294-36",
    "web-scraper-start-url": "https://www2.hm.com/en_in/men/shop-by-product/trousers.html",
    "link": "Suit trousers Straight Fit",
    "link-href": "https://www2.hm.com/en_in/productpage.0867466001.html",
    "name": "Suit trousers Straight Fit",
    "description": "Suit trousers in woven fabric. Extended waistband with a concealed button and hook-and-eye fastener, and a zip fly. Diagonal side pockets, welt back pockets with a button, and straight legs with pleats and creases. The polyester content of the trousers is recycled.",
    "review_count": null,
    "details": "Details\n\t\n\t\tSizeInside leg: Length: 78.0 cm (Size 52L)LengthLongWaist RiseRegular waistStyleSuit trousersStraight legCompositionShell: Polyester 62%, Viscose 36%, Elastane 2%Pocket lining: Polyester 90%, Cotton 10%More sustainable materialsRecycled polyester 63%Care instructionsMachine wash at 30°DescriptionBlackSolid colourConceptH&M MANNice to knowConsciousPrice (MRP)Rs. 2,299 incl. of all taxesCountry of productionChinaCommon generic nameTrousersNet quantity1 NMarketed or imported byH&M Hennes & Mauritz Retail Pvt. Ltd. A-wing, D-3, 2nd Floor District Centre Saket New Delhi -110017 IndiaDate of import01-2021Date of manufactureN/AManufactured byN/ACustomer serviceIn case of consumer complaint, write to H&M Hennes & Mauritz Retail PVT. Ltd, A Wing, D3, 2nd Floor, District Center, Saket, New Delhi 110017, India or call Telephone: 0008000501633. For online and store complaints email customerservice.in@hm.com.DisclaimerThis information is based on sample of the product displayed on website. There may be change in the information on label attached to the product delivered to the customer due to size chosen, date of import, name of manufacturer (in case of manufacturing in India), country of manufacture, etc. The exact detail relevant to the product delivered to the customer will reflect in the label attached to the product so deliveredArt. No.0867466001",
    "img1-src": "//lp2.hm.com/hmgoepprod?set=quality%5B79%5D%2Csource%5B%2Fb8%2F51%2Fb8512e5013ae03f07f2dc0a61bdcbc152b596114.jpg%5D%2Corigin%5Bdam%5D%2Ccategory%5B%5D%2Ctype%5BDESCRIPTIVESTILLLIFE%5D%2Cres%5Bm%5D%2Chmver%5B2%5D&call=url[file:/product/main]",
    "img2-src": "//lp2.hm.com/hmgoepprod?set=quality%5B79%5D%2Csource%5B%2F35%2F74%2F3574cc9222f12614c86418d61e6046c2c102f1eb.jpg%5D%2Corigin%5Bdam%5D%2Ccategory%5B%5D%2Ctype%5BDESCRIPTIVEDETAIL%5D%2Cres%5Bm%5D%2Chmver%5B2%5D&call=url[file:/product/main]",
    "style": "Suit trousers",
    "generic name": "Trousers",
    "colors": "Black",
    "descript": null,
    "item__price": "Rs. 2,299",
    "Fit": null,
    "Composition": "Shell: Polyester 62%, Viscose 36%, Elastane 2%Pocket lining: Polyester 90%, Cotton 10%"
  },
  {
    "web-scraper-order": "1629124476-92",
    "web-scraper-start-url": "https://www2.hm.com/en_in/men/shop-by-product/trousers.html",
    "link": "Slim Fit Joggers",
    "link-href": "https://www2.hm.com/en_in/productpage.0988366002.html",
    "name": "Slim Fit Joggers",
    "description": "Dressy joggers in woven fabric with covered elastication and a drawstring at the waist, side pockets, a welt back pocket and legs with creases. Slim Fit – a fit that is close-fitting at the thighs, knees and ankles to create a fitted silhouette.",
    "review_count": null,
    "details": "Details\n\t\n\t\tSizeInside leg: Length: 76.5 cm (Size L/L)LengthLongWaist RiseRegular waistFitSlim fitStyleJoggersCompositionShell: Polyester 81%, Viscose 17%, Elastane 2%Pocket lining: Polyester 80%, Cotton 20%Care instructionsMachine wash at 30°DescriptionGrey/Dark beige/WhiteCheckedNice to knowConsciousPrice (MRP)Rs. 1,499 incl. of all taxesCountry of productionChinaCommon generic nameTrousersNet quantity1 NMarketed or imported byH&M Hennes & Mauritz Retail Pvt. Ltd. A-wing, D-3, 2nd Floor District Centre Saket New Delhi -110017 IndiaDate of import07-2021Date of manufactureN/AManufactured byN/ACustomer serviceIn case of consumer complaint, write to H&M Hennes & Mauritz Retail PVT. Ltd, A Wing, D3, 2nd Floor, District Center, Saket, New Delhi 110017, India or call Telephone: 0008000501633. For online and store complaints email customerservice.in@hm.com.DisclaimerThis information is based on sample of the product displayed on website. There may be change in the information on label attached to the product delivered to the customer due to size chosen, date of import, name of manufacturer (in case of manufacturing in India), country of manufacture, etc. The exact detail relevant to the product delivered to the customer will reflect in the label attached to the product so deliveredArt. No.0988366002",
    "img1-src": "//lp2.hm.com/hmgoepprod?set=quality%5B79%5D%2Csource%5B%2F49%2Fd2%2F49d2ff3ecfbd13061737f33bca7498812db17122.jpg%5D%2Corigin%5Bdam%5D%2Ccategory%5B%5D%2Ctype%5BLOOKBOOK%5D%2Cres%5Bm%5D%2Chmver%5B1%5D&call=url[file:/product/main]",
    "img2-src": "//lp2.hm.com/hmgoepprod?set=quality%5B79%5D%2Csource%5B%2Fc8%2F9c%2Fc89cb3dfe1c69fbf278a405356bfb8bc1400675a.jpg%5D%2Corigin%5Bdam%5D%2Ccategory%5B%5D%2Ctype%5BLOOKBOOK%5D%2Cres%5Bm%5D%2Chmver%5B1%5D&call=url[file:/product/main]",
    "style": "Joggers",
    "generic name": "Trousers",
    "colors": "Grey/Dark beige/White",
    "descript": "Pocket lining: Polyester 80%, Cotton 20%",
    "item__price": "Rs. 1,499",
    "Fit": "Slim fit",
    "Composition": "Shell: Polyester 81%, Viscose 17%, Elastane 2%Pocket lining: Polyester 80%, Cotton 20%"
  },
  {
    "web-scraper-order": "1629124375-62",
    "web-scraper-start-url": "https://www2.hm.com/en_in/men/shop-by-product/trousers.html",
    "link": "Slim Fit Chinos",
    "link-href": "https://www2.hm.com/en_in/productpage.0815456042.html",
    "name": "Slim Fit Chinos",
    "description": "Chinos in extra-stretchy cotton twill with a zip fly, side pockets, a coin pocket and welt back pockets with a button. Slim Fit – a fit that is close-fitting at the thighs, knees and ankles to create a fitted silhouette.",
    "review_count": null,
    "details": "Details\n\t\n\t\tLengthLongFitSlim fitStyleChinosCompositionCotton 98%, Elastane 2%Pocket lining: Cotton 100%Care instructionsMachine wash at 40°MaterialCottonDescriptionKhaki greenSolid colourPrice (MRP)Rs. 1,999 incl. of all taxesCountry of productionBangladeshCommon generic nameTrousersNet quantity1 NMarketed or imported byH&M Hennes & Mauritz Retail Pvt. Ltd. A-wing, D-3, 2nd Floor District Centre Saket New Delhi -110017 IndiaDate of import06-2021Date of manufactureN/AManufactured byN/ACustomer serviceIn case of consumer complaint, write to H&M Hennes & Mauritz Retail PVT. Ltd, A Wing, D3, 2nd Floor, District Center, Saket, New Delhi 110017, India or call Telephone: 0008000501633. For online and store complaints email customerservice.in@hm.com.DisclaimerThis information is based on sample of the product displayed on website. There may be change in the information on label attached to the product delivered to the customer due to size chosen, date of import, name of manufacturer (in case of manufacturing in India), country of manufacture, etc. The exact detail relevant to the product delivered to the customer will reflect in the label attached to the product so deliveredArt. No.0815456042",
    "img1-src": "//lp2.hm.com/hmgoepprod?set=quality%5B79%5D%2Csource%5B%2Fee%2F8f%2Fee8f33b8ae9ed04762e853d669d34c77090adc3b.jpg%5D%2Corigin%5Bdam%5D%2Ccategory%5B%5D%2Ctype%5BLOOKBOOK%5D%2Cres%5Bm%5D%2Chmver%5B1%5D&call=url[file:/product/main]",
    "img2-src": "//lp2.hm.com/hmgoepprod?set=quality%5B79%5D%2Csource%5B%2Fdd%2F39%2Fdd39873fac44ae69c3be99f169fbc22c7f46397a.jpg%5D%2Corigin%5Bdam%5D%2Ccategory%5B%5D%2Ctype%5BLOOKBOOK%5D%2Cres%5Bm%5D%2Chmver%5B1%5D&call=url[file:/product/main]",
    "style": "Chinos",
    "generic name": "Trousers",
    "colors": "Khaki green",
    "descript": null,
    "item__price": "Rs. 1,999",
    "Fit": "Slim fit",
    "Composition": "Cotton 98%, Elastane 2%Pocket lining: Cotton 100%"
  },
  {
    "web-scraper-order": "1629124544-113",
    "web-scraper-start-url": "https://www2.hm.com/en_in/men/shop-by-product/trousers.html",
    "link": "Cargo joggers",
    "link-href": "https://www2.hm.com/en_in/productpage.1002227003.html",
    "name": "Cargo joggers",
    "description": "Joggers in a cotton weave with covered elastication and a drawstring at the waist, diagonal side pockets and flap back and leg pockets with concealed press-studs. Tapered legs with seams and darts at the knees and covered elastication at the hems.",
    "review_count": null,
    "details": "Details\n\t\n\t\tSizeInside leg: Length: 75.0 cm (Size L/L)LengthLongWaist RiseRegular waistStyleCargoTaperedJoggersCompositionShell: Cotton 98%, Elastane 2%Pocket lining: Cotton 100%Care instructionsMachine wash at 40°MaterialCottonDescriptionDark greySolid colourNice to knowConsciousPrice (MRP)Rs. 2,699 incl. of all taxesCountry of productionBangladeshCommon generic nameTrousersNet quantity1 NMarketed or imported byH&M Hennes & Mauritz Retail Pvt. Ltd. A-wing, D-3, 2nd Floor District Centre Saket New Delhi -110017 IndiaDate of import06-2021Date of manufactureN/AManufactured byN/ACustomer serviceIn case of consumer complaint, write to H&M Hennes & Mauritz Retail PVT. Ltd, A Wing, D3, 2nd Floor, District Center, Saket, New Delhi 110017, India or call Telephone: 0008000501633. For online and store complaints email customerservice.in@hm.com.DisclaimerThis information is based on sample of the product displayed on website. There may be change in the information on label attached to the product delivered to the customer due to size chosen, date of import, name of manufacturer (in case of manufacturing in India), country of manufacture, etc. The exact detail relevant to the product delivered to the customer will reflect in the label attached to the product so deliveredArt. No.1002227003",
    "img1-src": "//lp2.hm.com/hmgoepprod?set=quality%5B79%5D%2Csource%5B%2F35%2F8d%2F358d398bb65376f08fab43e262cebdfe9736ac86.jpg%5D%2Corigin%5Bdam%5D%2Ccategory%5B%5D%2Ctype%5BLOOKBOOK%5D%2Cres%5Bm%5D%2Chmver%5B1%5D&call=url[file:/product/main]",
    "img2-src": "//lp2.hm.com/hmgoepprod?set=quality%5B79%5D%2Csource%5B%2F1a%2F6d%2F1a6d816bd2c2e351a863498a7c55108c128d91c4.jpg%5D%2Corigin%5Bdam%5D%2Ccategory%5B%5D%2Ctype%5BLOOKBOOK%5D%2Cres%5Bm%5D%2Chmver%5B1%5D&call=url[file:/product/main]",
    "style": "Cargo",
    "generic name": "Trousers",
    "colors": "Dark grey",
    "descript": null,
    "item__price": "Rs. 2,699",
    "Fit": null,
    "Composition": "Shell: Cotton 98%, Elastane 2%Pocket lining: Cotton 100%"
  },
  {
    "web-scraper-order": "1629124342-52",
    "web-scraper-start-url": "https://www2.hm.com/en_in/men/shop-by-product/trousers.html",
    "link": "Running trousers",
    "link-href": "https://www2.hm.com/en_in/productpage.0865474001.html",
    "name": "Running trousers",
    "description": "Running trousers in fast-drying functional fabric designed to help keep you dry and cool while exercising. Elastication and a concealed drawstring at the waist, zipped, mesh-lined side pockets, tapered legs with a zip at the hems, and reflective details.",
    "review_count": null,
    "details": "Details\n\t\n\t\tLengthLongStyleTaperedFunctionsQuick dryReflective detailsCompositionPolyester 86%, Elastane 14%More sustainable materialsRecycled polyester 86%Care instructionsMachine wash at 40°Sports activityTrainingDescriptionBlackSolid colourNice to knowConsciousPrice (MRP)Rs. 2,299 incl. of all taxesCountry of productionIndonesiaCommon generic nameOutdoor trousersNet quantity1 NMarketed or imported byH&M Hennes & Mauritz Retail Pvt. Ltd. A-wing, D-3, 2nd Floor District Centre Saket New Delhi -110017 IndiaDate of import07-2021Date of manufactureN/AManufactured byN/ACustomer serviceIn case of consumer complaint, write to H&M Hennes & Mauritz Retail PVT. Ltd, A Wing, D3, 2nd Floor, District Center, Saket, New Delhi 110017, India or call Telephone: 0008000501633. For online and store complaints email customerservice.in@hm.com.DisclaimerThis information is based on sample of the product displayed on website. There may be change in the information on label attached to the product delivered to the customer due to size chosen, date of import, name of manufacturer (in case of manufacturing in India), country of manufacture, etc. The exact detail relevant to the product delivered to the customer will reflect in the label attached to the product so deliveredArt. No.0865474001",
    "img1-src": "//lp2.hm.com/hmgoepprod?set=quality%5B79%5D%2Csource%5B%2Fe4%2F58%2Fe458ddc1101626290a0cf56e326908bab556edcc.jpg%5D%2Corigin%5Bdam%5D%2Ccategory%5Bmen_sport_bottoms%5D%2Ctype%5BLOOKBOOK%5D%2Cres%5Bm%5D%2Chmver%5B1%5D&call=url[file:/product/main]",
    "img2-src": "//lp2.hm.com/hmgoepprod?set=quality%5B79%5D%2Csource%5B%2Fde%2Fa6%2Fdea694a28263ece5c74336a325f5c38a04f9e322.jpg%5D%2Corigin%5Bdam%5D%2Ccategory%5Bmen_sport_bottoms%5D%2Ctype%5BLOOKBOOK%5D%2Cres%5Bm%5D%2Chmver%5B1%5D&call=url[file:/product/main]",
    "style": "Tapered",
    "generic name": "Outdoor trousers",
    "colors": "Black",
    "descript": null,
    "item__price": "Rs. 2,299",
    "Fit": null,
    "Composition": "Polyester 86%, Elastane 14%"
  },
  {
    "web-scraper-order": "1629124581-125",
    "web-scraper-start-url": "https://www2.hm.com/en_in/men/shop-by-product/trousers.html",
    "link": "Regular Fit Linen-mix joggers",
    "link-href": "https://www2.hm.com/en_in/productpage.0964500004.html",
    "name": "Regular Fit Linen-mix joggers",
    "description": "Joggers in a linen and cotton weave with covered elastication and a drawstring at the waist. Diagonal side pockets, welt back pockets and covered elastication at the hems. Regular Fit – a classic fit with good room for movement over the thighs and knees to create a comfortable, straight silhouette.",
    "review_count": null,
    "details": "Details\n\t\n\t\tLengthLongWaist RiseRegular waistFitRegular fitStyleJoggersCompositionPocket: Cotton 100%Linen 55%, Cotton 45%Care instructionsMachine wash at 40°MaterialLinenDescriptionDark blueSolid colourPrice (MRP)Rs. 1,499 incl. of all taxesCountry of productionMyanmarCommon generic nameTrousersNet quantity1 NMarketed or imported byH&M Hennes & Mauritz Retail Pvt. Ltd. A-wing, D-3, 2nd Floor District Centre Saket New Delhi -110017 IndiaDate of import03-2021Date of manufactureN/AManufactured byN/ACustomer serviceIn case of consumer complaint, write to H&M Hennes & Mauritz Retail PVT. Ltd, A Wing, D3, 2nd Floor, District Center, Saket, New Delhi 110017, India or call Telephone: 0008000501633. For online and store complaints email customerservice.in@hm.com.DisclaimerThis information is based on sample of the product displayed on website. There may be change in the information on label attached to the product delivered to the customer due to size chosen, date of import, name of manufacturer (in case of manufacturing in India), country of manufacture, etc. The exact detail relevant to the product delivered to the customer will reflect in the label attached to the product so deliveredArt. No.0964500004",
    "img1-src": "//lp2.hm.com/hmgoepprod?set=quality%5B79%5D%2Csource%5B%2F13%2Fbf%2F13bf87edd689e0d1c43f01aebf724621432de561.jpg%5D%2Corigin%5Bdam%5D%2Ccategory%5B%5D%2Ctype%5BDESCRIPTIVESTILLLIFE%5D%2Cres%5Bm%5D%2Chmver%5B2%5D&call=url[file:/product/main]",
    "img2-src": "//lp2.hm.com/hmgoepprod?set=quality%5B79%5D%2Csource%5B%2F70%2F85%2F7085b29142e45ddc8b6682ab3e52d3a37e021fe8.jpg%5D%2Corigin%5Bdam%5D%2Ccategory%5B%5D%2Ctype%5BDESCRIPTIVEDETAIL%5D%2Cres%5Bm%5D%2Chmver%5B2%5D&call=url[file:/product/main]",
    "style": "Joggers",
    "generic name": "Trousers",
    "colors": "Dark blue",
    "descript": null,
    "item__price": "Rs. 1,499",
    "Fit": "Regular fit",
    "Composition": "Pocket: Cotton 100%Linen 55%, Cotton 45%"
  },
  {
    "web-scraper-order": "1629124459-87",
    "web-scraper-start-url": "https://www2.hm.com/en_in/men/shop-by-product/trousers.html",
    "link": "Twill trousers Slim Fit",
    "link-href": "https://www2.hm.com/en_in/productpage.0721390009.html",
    "name": "Twill trousers Slim Fit",
    "description": "5-pocket trousers in washed stretch twill with a regular waist and zip fly. Slim fit which is relaxed over the thighs and tapers from the knees down for a relaxed, well-tailored look.",
    "review_count": "(678)",
    "details": "Details\n\t\n\t\tLengthLongWaist RiseRegular waistFitSlim fitCompositionPocket: Cotton 100%Cotton 98%, Elastane 2%Care instructionsMachine wash at 40°MaterialCottonDescriptionWhiteSolid colourConceptH&M MANPrice (MRP)Rs. 1,499 incl. of all taxesCountry of productionBangladeshCommon generic nameTrousersSize: 27/30Width: 75 cmLength: 72 cmSize: 30/32Width: 82 cmLength: 80 cmSize: 31/32Width: 85 cmLength: 81 cmSize: 32/32Width: 87 cmLength: 81 cmSize: 33/32Width: 92 cmLength: 78 cmSize: 34/32Width: 92 cmLength: 82 cmSize: 36/32Width: 97 cmLength: 83 cmNet quantity1 NMarketed or imported byH&M Hennes & Mauritz Retail Pvt. Ltd. A-wing, D-3, 2nd Floor District Centre Saket New Delhi -110017 IndiaDate of import05-2021Date of manufactureN/AManufactured byN/ACustomer serviceIn case of consumer complaint, write to H&M Hennes & Mauritz Retail PVT. Ltd, A Wing, D3, 2nd Floor, District Center, Saket, New Delhi 110017, India or call Telephone: 0008000501633. For online and store complaints email customerservice.in@hm.com.DisclaimerThis information is based on sample of the product displayed on website. There may be change in the information on label attached to the product delivered to the customer due to size chosen, date of import, name of manufacturer (in case of manufacturing in India), country of manufacture, etc. The exact detail relevant to the product delivered to the customer will reflect in the label attached to the product so deliveredArt. No.0721390009",
    "img1-src": "//lp2.hm.com/hmgoepprod?set=quality%5B79%5D%2Csource%5B%2F2c%2F61%2F2c61cb8353b6bfcc66a31d6012dc9cedee966b6e.jpg%5D%2Corigin%5Bdam%5D%2Ccategory%5Bmen_trousers_trousers_slim_all%5D%2Ctype%5BLOOKBOOK%5D%2Cres%5Bm%5D%2Chmver%5B1%5D&call=url[file:/product/main]",
    "img2-src": "//lp2.hm.com/hmgoepprod?set=quality%5B79%5D%2Csource%5B%2Ff0%2Fde%2Ff0deb3e7f5c1b4adb88e61acc523d1960eb123a0.jpg%5D%2Corigin%5Bdam%5D%2Ccategory%5Bmen_trousers_trousers_slim_all%5D%2Ctype%5BLOOKBOOK%5D%2Cres%5Bm%5D%2Chmver%5B1%5D&call=url[file:/product/main]",
    "style": null,
    "generic name": "Trousers",
    "colors": "White",
    "descript": null,
    "item__price": "Rs. 1,499",
    "Fit": "Slim fit",
    "Composition": "Pocket: Cotton 100%Cotton 98%, Elastane 2%"
  },
  {
    "web-scraper-order": "1629124485-95",
    "web-scraper-start-url": "https://www2.hm.com/en_in/men/shop-by-product/trousers.html",
    "link": "Cotton joggers",
    "link-href": "https://www2.hm.com/en_in/productpage.0967542001.html",
    "name": "Cotton joggers",
    "description": "Blank Staples is a streetwear collection of minimalistic pieces that are the perfect canvas for your personal style and creativity. These pared-back joggers are made from heavy, 460 g organic cotton sweatshirt fabric for a premium handfeel. They have covered elastication at the waist and hems, jersey-lined pockets in the side seams and an open back pocket.",
    "review_count": null,
    "details": "Details\n\t\n\t\tLengthLongWaist RiseRegular waistStyleJoggersCompositionCotton 100%Care instructionsMachine wash at 40°MaterialCottonDescriptionCreamSolid colourConceptBASICSCollectionBlank StaplesPrice (MRP)Rs. 2,299 incl. of all taxesCountry of productionBangladeshCommon generic nameTrousersNet quantity1 NMarketed or imported byH&M Hennes & Mauritz Retail Pvt. Ltd. A-wing, D-3, 2nd Floor District Centre Saket New Delhi -110017 IndiaDate of import08-2021Date of manufactureN/AManufactured byN/ACustomer serviceIn case of consumer complaint, write to H&M Hennes & Mauritz Retail PVT. Ltd, A Wing, D3, 2nd Floor, District Center, Saket, New Delhi 110017, India or call Telephone: 0008000501633. For online and store complaints email customerservice.in@hm.com.DisclaimerThis information is based on sample of the product displayed on website. There may be change in the information on label attached to the product delivered to the customer due to size chosen, date of import, name of manufacturer (in case of manufacturing in India), country of manufacture, etc. The exact detail relevant to the product delivered to the customer will reflect in the label attached to the product so deliveredArt. No.0967542001",
    "img1-src": "//lp2.hm.com/hmgoepprod?set=quality%5B79%5D%2Csource%5B%2F36%2Fa7%2F36a783c93b8bbd5e12fd0dc921027a2b7b624957.jpg%5D%2Corigin%5Bdam%5D%2Ccategory%5B%5D%2Ctype%5BDESCRIPTIVESTILLLIFE%5D%2Cres%5Bm%5D%2Chmver%5B2%5D&call=url[file:/product/main]",
    "img2-src": "//lp2.hm.com/hmgoepprod?set=quality%5B79%5D%2Csource%5B%2F5f%2F91%2F5f91cd8c63e9fe62ef4ae98e871fc57c3ec14226.jpg%5D%2Corigin%5Bdam%5D%2Ccategory%5B%5D%2Ctype%5BDESCRIPTIVEDETAIL%5D%2Cres%5Bm%5D%2Chmver%5B2%5D&call=url[file:/product/main]",
    "style": "Joggers",
    "generic name": "Trousers",
    "colors": "Cream",
    "descript": null,
    "item__price": "Rs. 2,299",
    "Fit": null,
    "Composition": "Cotton 100%"
  },
  {
    "web-scraper-order": "1629124449-84",
    "web-scraper-start-url": "https://www2.hm.com/en_in/men/shop-by-product/trousers.html",
    "link": "Cotton chinos Skinny Fit",
    "link-href": "https://www2.hm.com/en_in/productpage.0710876001.html",
    "name": "Cotton chinos Skinny Fit",
    "description": "Chinos in stretch cotton twill with a zip fly and button, diagonal side pockets and welt back pockets with a button. Skinny Fit – a fit with slightly shorter legs that is close-fitting at the thighs, knees and ankles to create a completely fitted silhouette.",
    "review_count": null,
    "details": "Details\n\t\n\t\tLengthAnkle lengthWaist RiseRegular waistFitSkinny fitStyleChinosCompositionPocket: Cotton 100%Cotton 98%, Elastane 2%Care instructionsMachine wash at 40°MaterialCottonDescriptionBlackSolid colourNice to knowConsciousPrice (MRP)Rs. 1,999 incl. of all taxesCountry of productionMyanmarCommon generic nameTrousersSize: 28/30Width: 75 cmLength: 77 cmSize: 28/32Width: 77 cmLength: 79 cmSize: 29/32Width: 80 cmLength: 80 cmSize: 30/32Width: 82 cmLength: 80 cmSize: 31/32Width: 80 cmLength: 85 cmSize: 32/32Width: 87 cmLength: 81 cmSize: 32/34Width: 87 cmLength: 85 cmSize: 33/32Width: 81 cmLength: 90 cmSize: 33/34Width: 90 cmLength: 85 cmSize: 34/32Width: 82 cmLength: 92 cmSize: 34/34Width: 92 cmLength: 86 cmSize: 36/32Width: 97 cmLength: 82 cmSize: 36/34Width: 97 cmLength: 86 cmSize: 38/30Width: 1.02 mLength: 79 cmSize: 38/32Width: 83 cmLength: 1.02 mSize: 38/34Width: 1.02 mLength: 87 cmNet quantity1 NMarketed or imported byH&M Hennes & Mauritz Retail Pvt. Ltd. A-wing, D-3, 2nd Floor District Centre Saket New Delhi -110017 IndiaDate of import02-2021Date of manufactureN/AManufactured byN/ACustomer serviceIn case of consumer complaint, write to H&M Hennes & Mauritz Retail PVT. Ltd, A Wing, D3, 2nd Floor, District Center, Saket, New Delhi 110017, India or call Telephone: 0008000501633. For online and store complaints email customerservice.in@hm.com.DisclaimerThis information is based on sample of the product displayed on website. There may be change in the information on label attached to the product delivered to the customer due to size chosen, date of import, name of manufacturer (in case of manufacturing in India), country of manufacture, etc. The exact detail relevant to the product delivered to the customer will reflect in the label attached to the product so deliveredArt. No.0710876001",
    "img1-src": "//lp2.hm.com/hmgoepprod?set=quality%5B79%5D%2Csource%5B%2F3a%2F2f%2F3a2ffd0fd8b7da2a500ab7bc25208ff728e46e09.jpg%5D%2Corigin%5Bdam%5D%2Ccategory%5Bmen_trousers_chinos_skinny_all%5D%2Ctype%5BDESCRIPTIVESTILLLIFE%5D%2Cres%5Bm%5D%2Chmver%5B1%5D&call=url[file:/product/main]",
    "img2-src": "//lp2.hm.com/hmgoepprod?set=quality%5B79%5D%2Csource%5B%2F7c%2Fd6%2F7cd6553089940b305597735733a37ad18343857c.jpg%5D%2Corigin%5Bdam%5D%2Ccategory%5Bmen_trousers_chinos_skinny_all%5D%2Ctype%5BDESCRIPTIVEDETAIL%5D%2Cres%5Bm%5D%2Chmver%5B1%5D&call=url[file:/product/main]",
    "style": "Chinos",
    "generic name": "Trousers",
    "colors": "Black",
    "descript": null,
    "item__price": "Rs. 1,999",
    "Fit": "Skinny fit",
    "Composition": "Pocket: Cotton 100%Cotton 98%, Elastane 2%"
  },
  {
    "web-scraper-order": "1629124415-74",
    "web-scraper-start-url": "https://www2.hm.com/en_in/men/shop-by-product/trousers.html",
    "link": "Regular Fit Twill joggers",
    "link-href": "https://www2.hm.com/en_in/productpage.0975244004.html",
    "name": "Regular Fit Twill joggers",
    "description": "Joggers in stretch cotton twill with covered elastication and a drawstring at the waist and a fake fly. Side pockets, back pockets with a button and covered elastication at the hems. Regular Fit – a classic fit with good room for movement over the thighs and knees to create a comfortable, straight silhouette.",
    "review_count": null,
    "details": "Details\n\t\n\t\tSizeInside leg: Length: 76.0 cm (Size L/L)LengthLongWaist RiseRegular waistFitRegular fitStyleJoggersCompositionShell: Cotton 98%, Elastane 2%Pocket lining: Cotton 100%Care instructionsMachine wash at 40°MaterialCottonDescriptionDark greySolid colourNice to knowConsciousPrice (MRP)Rs. 1,499 incl. of all taxesCountry of productionBangladeshCommon generic nameTrousersNet quantity1 NMarketed or imported byH&M Hennes & Mauritz Retail Pvt. Ltd. A-wing, D-3, 2nd Floor District Centre Saket New Delhi -110017 IndiaDate of import05-2021Date of manufactureN/AManufactured byN/ACustomer serviceIn case of consumer complaint, write to H&M Hennes & Mauritz Retail PVT. Ltd, A Wing, D3, 2nd Floor, District Center, Saket, New Delhi 110017, India or call Telephone: 0008000501633. For online and store complaints email customerservice.in@hm.com.DisclaimerThis information is based on sample of the product displayed on website. There may be change in the information on label attached to the product delivered to the customer due to size chosen, date of import, name of manufacturer (in case of manufacturing in India), country of manufacture, etc. The exact detail relevant to the product delivered to the customer will reflect in the label attached to the product so deliveredArt. No.0975244004",
    "img1-src": "//lp2.hm.com/hmgoepprod?set=quality%5B79%5D%2Csource%5B%2Fb5%2Fe0%2Fb5e0a108509399ba9b5f308783eb76d92e7ccdc0.jpg%5D%2Corigin%5Bdam%5D%2Ccategory%5B%5D%2Ctype%5BLOOKBOOK%5D%2Cres%5Bm%5D%2Chmver%5B1%5D&call=url[file:/product/main]",
    "img2-src": "//lp2.hm.com/hmgoepprod?set=quality%5B79%5D%2Csource%5B%2Fbc%2Fca%2Fbcca95325aa25fb51fc6ab7b21a95f4b3ffb3b87.jpg%5D%2Corigin%5Bdam%5D%2Ccategory%5B%5D%2Ctype%5BLOOKBOOK%5D%2Cres%5Bm%5D%2Chmver%5B1%5D&call=url[file:/product/main]",
    "style": "Joggers",
    "generic name": "Trousers",
    "colors": "Dark grey",
    "descript": "Pocket lining: Cotton 100%",
    "item__price": "Rs. 1,499",
    "Fit": "Regular fit",
    "Composition": "Shell: Cotton 98%, Elastane 2%Pocket lining: Cotton 100%"
  },
  {
    "web-scraper-order": "1629124318-44",
    "web-scraper-start-url": "https://www2.hm.com/en_in/men/shop-by-product/trousers.html",
    "link": "Sports joggers",
    "link-href": "https://www2.hm.com/en_in/productpage.0862106003.html",
    "name": "Sports joggers",
    "description": "Sports joggers in heavy jersey with taped details. Elasticated, drawstring waist and zipped side pockets. Tapered legs with shaping seams at the knees for added mobility and wide ribbing at the hems. The polyester content of the joggers is recycled.",
    "review_count": null,
    "details": "Details\n\t\n\t\tLengthLongStyleTaperedJoggersCompositionShell: Polyester 58%, Cotton 42%Pocket lining: Polyester 100%More sustainable materialsRecycled polyester 58%Care instructionsMachine wash at 40°Sports activityTrainingDescriptionNavy blueSolid colourNice to knowConsciousPrice (MRP)Rs. 2,299 incl. of all taxesCountry of productionChinaCommon generic nameTrousersNet quantity1 NMarketed or imported byH&M Hennes & Mauritz Retail Pvt. Ltd. A-wing, D-3, 2nd Floor District Centre Saket New Delhi -110017 IndiaDate of import01-2021Date of manufactureN/AManufactured byN/ACustomer serviceIn case of consumer complaint, write to H&M Hennes & Mauritz Retail PVT. Ltd, A Wing, D3, 2nd Floor, District Center, Saket, New Delhi 110017, India or call Telephone: 0008000501633. For online and store complaints email customerservice.in@hm.com.DisclaimerThis information is based on sample of the product displayed on website. There may be change in the information on label attached to the product delivered to the customer due to size chosen, date of import, name of manufacturer (in case of manufacturing in India), country of manufacture, etc. The exact detail relevant to the product delivered to the customer will reflect in the label attached to the product so deliveredArt. No.0862106003",
    "img1-src": "//lp2.hm.com/hmgoepprod?set=quality%5B79%5D%2Csource%5B%2Fcb%2F34%2Fcb34d99821eff07c9892eba2406a13b27b83833a.jpg%5D%2Corigin%5Bdam%5D%2Ccategory%5Bmen_sport_bottoms%5D%2Ctype%5BLOOKBOOK%5D%2Cres%5Bm%5D%2Chmver%5B1%5D&call=url[file:/product/main]",
    "img2-src": "//lp2.hm.com/hmgoepprod?set=quality%5B79%5D%2Csource%5B%2F26%2F4b%2F264b560d7c2a09c239b20b0e1cbf7fc26f7e814e.jpg%5D%2Corigin%5Bdam%5D%2Ccategory%5Bmen_sport_bottoms%5D%2Ctype%5BLOOKBOOK%5D%2Cres%5Bm%5D%2Chmver%5B1%5D&call=url[file:/product/main]",
    "style": "Tapered",
    "generic name": "Trousers",
    "colors": "Navy blue",
    "descript": null,
    "item__price": "Rs. 2,299",
    "Fit": null,
    "Composition": "Shell: Polyester 58%, Cotton 42%Pocket lining: Polyester 100%"
  },
  {
    "web-scraper-order": "1629124618-137",
    "web-scraper-start-url": "https://www2.hm.com/en_in/men/shop-by-product/trousers.html",
    "link": "Twill trousers Slim Fit",
    "link-href": "https://www2.hm.com/en_in/productpage.0721390002.html",
    "name": "Twill trousers Slim Fit",
    "description": "5-pocket trousers in washed stretch twill with a regular waist and zip fly. Slim fit which is relaxed over the thighs and tapers from the knees down for a relaxed, well-tailored look.",
    "review_count": null,
    "details": "Details\n\t\n\t\tLengthLongWaist RiseRegular waistFitSlim fitCompositionPocket: Cotton 100%Cotton 98%, Elastane 2%Care instructionsMachine wash at 40°MaterialCottonDescriptionDark blueSolid colourDark blueConceptH&M MANPrice (MRP)Rs. 1,499 incl. of all taxesCountry of productionIndiaCommon generic nameTrousersSize: 27/30Width: 75 cmLength: 72 cmSize: 29/32Width: 82 cmLength: 83 cmSize: 30/32Width: 84 cmLength: 80 cmSize: 31/32Width: 87 cmLength: 80 cmSize: 32/32Width: 89 cmLength: 81 cmSize: 33/32Width: 92 cmLength: 81 cmSize: 34/32Width: 94 cmLength: 82 cmSize: 36/32Width: 99 cmLength: 83 cmNet quantity1 NDate of manufacture01-2021Manufactured bySHAHI EXPORTS PRIVATE LIMITED\nINDUSTRIAL PLOT NO. 1, SECTOR 28, 121008, FARIDABADCustomer serviceIn case of consumer complaint, write to H&M Hennes & Mauritz Retail PVT. Ltd, A Wing, D3, 2nd Floor, District Center, Saket, New Delhi 110017, India or call Telephone: 0008000501633. For online and store complaints email customerservice.in@hm.com.DisclaimerThis information is based on sample of the product displayed on website. There may be change in the information on label attached to the product delivered to the customer due to size chosen, date of import, name of manufacturer (in case of manufacturing in India), country of manufacture, etc. The exact detail relevant to the product delivered to the customer will reflect in the label attached to the product so deliveredArt. No.0721390002",
    "img1-src": "//lp2.hm.com/hmgoepprod?set=quality%5B79%5D%2Csource%5B%2Fe7%2Fd1%2Fe7d16e58410b3ec94796f2ef15ee77333be6e9d1.jpg%5D%2Corigin%5Bdam%5D%2Ccategory%5Bmen_trousers_trousers_slim_all%5D%2Ctype%5BLOOKBOOK%5D%2Cres%5Bm%5D%2Chmver%5B1%5D&call=url[file:/product/main]",
    "img2-src": "//lp2.hm.com/hmgoepprod?set=quality%5B79%5D%2Csource%5B%2F3e%2F56%2F3e565b42f4c45e2af9439f20664dc6286ec7a7b1.jpg%5D%2Corigin%5Bdam%5D%2Ccategory%5Bmen_trousers_trousers_slim_all%5D%2Ctype%5BLOOKBOOK%5D%2Cres%5Bm%5D%2Chmver%5B1%5D&call=url[file:/product/main]",
    "style": null,
    "generic name": "Trousers",
    "colors": "Dark blue",
    "descript": null,
    "item__price": "Rs. 1,499",
    "Fit": "Slim fit",
    "Composition": "Pocket: Cotton 100%Cotton 98%, Elastane 2%"
  },
  {
    "web-scraper-order": "1629124526-107",
    "web-scraper-start-url": "https://www2.hm.com/en_in/men/shop-by-product/trousers.html",
    "link": "Slim Fit Joggers",
    "link-href": "https://www2.hm.com/en_in/productpage.0988366004.html",
    "name": "Slim Fit Joggers",
    "description": "Dressy joggers in woven fabric with covered elastication and a drawstring at the waist, side pockets, a welt back pocket and legs with creases. Slim Fit – a fit that is close-fitting at the thighs, knees and ankles to create a fitted silhouette.",
    "review_count": null,
    "details": "Details\n\t\n\t\tSizeInside leg: Length: 76.5 cm (Size L/L)LengthLongWaist RiseRegular waistFitSlim fitStyleJoggersCompositionPocket lining: Polyester 65%, Cotton 35%Shell: Polyester 77%, Viscose 21%, Elastane 2%Care instructionsMachine wash at 30°DescriptionBrownSolid colourNice to knowConsciousPrice (MRP)Rs. 1,499 incl. of all taxesCountry of productionBangladeshCommon generic nameTrousersNet quantity1 NMarketed or imported byH&M Hennes & Mauritz Retail Pvt. Ltd. A-wing, D-3, 2nd Floor District Centre Saket New Delhi -110017 IndiaDate of import06-2021Date of manufactureN/AManufactured byN/ACustomer serviceIn case of consumer complaint, write to H&M Hennes & Mauritz Retail PVT. Ltd, A Wing, D3, 2nd Floor, District Center, Saket, New Delhi 110017, India or call Telephone: 0008000501633. For online and store complaints email customerservice.in@hm.com.DisclaimerThis information is based on sample of the product displayed on website. There may be change in the information on label attached to the product delivered to the customer due to size chosen, date of import, name of manufacturer (in case of manufacturing in India), country of manufacture, etc. The exact detail relevant to the product delivered to the customer will reflect in the label attached to the product so deliveredArt. No.0988366004",
    "img1-src": "//lp2.hm.com/hmgoepprod?set=quality%5B79%5D%2Csource%5B%2F5b%2F28%2F5b28d977aebd5d36907820adc7b0096fb6169fd0.jpg%5D%2Corigin%5Bdam%5D%2Ccategory%5B%5D%2Ctype%5BLOOKBOOK%5D%2Cres%5Bm%5D%2Chmver%5B1%5D&call=url[file:/product/main]",
    "img2-src": "//lp2.hm.com/hmgoepprod?set=quality%5B79%5D%2Csource%5B%2F45%2F02%2F4502c344553ceb78ecf19b96cd57e55224f625bb.jpg%5D%2Corigin%5Bdam%5D%2Ccategory%5B%5D%2Ctype%5BLOOKBOOK%5D%2Cres%5Bm%5D%2Chmver%5B1%5D&call=url[file:/product/main]",
    "style": "Joggers",
    "generic name": "Trousers",
    "colors": "Brown",
    "descript": "Shell: Polyester 77%, Viscose 21%, Elastane 2%",
    "item__price": "Rs. 1,499",
    "Fit": "Slim fit",
    "Composition": "Pocket lining: Polyester 65%, Cotton 35%Shell: Polyester 77%, Viscose 21%, Elastane 2%"
  },
  {
    "web-scraper-order": "1629124574-123",
    "web-scraper-start-url": "https://www2.hm.com/en_in/men/shop-by-product/trousers.html",
    "link": "Regular Fit Cargo trousers",
    "link-href": "https://www2.hm.com/en_in/productpage.0983711001.html",
    "name": "Regular Fit Cargo trousers",
    "description": "Trousers in cotton twill with an elasticated, drawstring waist, zip fly and button, flap side and back pockets with a concealed press-stud, and bellows leg pockets with a flap and concealed press-studs. Legs with shaping seams at the knees for added mobility and covered elastication at the hems. Regular Fit – a classic fit with good room for movement over the thighs and knees to create a comfortable, straight silhouette.",
    "review_count": null,
    "details": "Details\n\t\n\t\tLengthLongWaist RiseRegular waistFitRegular fitStyleCargoCompositionPocket: Cotton 100%Shell: Cotton 98%, Elastane 2%Care instructionsMachine wash at 40°DescriptionBeigeSolid colourNice to knowConsciousPrice (MRP)Rs. 1,299 incl. of all taxesCountry of productionBangladeshCommon generic nameTrousersNet quantity1 NMarketed or imported byH&M Hennes & Mauritz Retail Pvt. Ltd. A-wing, D-3, 2nd Floor District Centre Saket New Delhi -110017 IndiaDate of import06-2021Date of manufactureN/AManufactured byN/ACustomer serviceIn case of consumer complaint, write to H&M Hennes & Mauritz Retail PVT. Ltd, A Wing, D3, 2nd Floor, District Center, Saket, New Delhi 110017, India or call Telephone: 0008000501633. For online and store complaints email customerservice.in@hm.com.DisclaimerThis information is based on sample of the product displayed on website. There may be change in the information on label attached to the product delivered to the customer due to size chosen, date of import, name of manufacturer (in case of manufacturing in India), country of manufacture, etc. The exact detail relevant to the product delivered to the customer will reflect in the label attached to the product so deliveredArt. No.0983711001",
    "img1-src": "//lp2.hm.com/hmgoepprod?set=quality%5B79%5D%2Csource%5B%2F71%2Fc1%2F71c1b0fd0d92a212307aca4d9c0bbd823651d987.jpg%5D%2Corigin%5Bdam%5D%2Ccategory%5B%5D%2Ctype%5BLOOKBOOK%5D%2Cres%5Bm%5D%2Chmver%5B1%5D&call=url[file:/product/main]",
    "img2-src": "//lp2.hm.com/hmgoepprod?set=quality%5B79%5D%2Csource%5B%2F28%2F33%2F2833ce4fc770074b37668cfd17e7121d984ab17a.jpg%5D%2Corigin%5Bdam%5D%2Ccategory%5B%5D%2Ctype%5BLOOKBOOK%5D%2Cres%5Bm%5D%2Chmver%5B3%5D&call=url[file:/product/main]",
    "style": "Cargo",
    "generic name": "Trousers",
    "colors": "Beige",
    "descript": null,
    "item__price": "Rs. 1,299",
    "Fit": "Regular fit",
    "Composition": "Pocket: Cotton 100%Shell: Cotton 98%, Elastane 2%"
  },
  {
    "web-scraper-order": "1629124505-101",
    "web-scraper-start-url": "https://www2.hm.com/en_in/men/shop-by-product/trousers.html",
    "link": "Slim Fit Cropped trousers",
    "link-href": "https://www2.hm.com/en_in/productpage.0991309002.html",
    "name": "Slim Fit Cropped trousers",
    "description": "Cropped trousers in woven fabric with a concealed hook-and-eye fastening and button in the waistband and a zip fly. Side pockets, welt back pockets with a button, and legs with creases. Slim Fit – a fit that is close-fitting at the thighs and knees to create a fitted silhouette.",
    "review_count": "(9)",
    "details": "Details\n\t\n\t\tLengthAnkle lengthWaist RiseRegular waistFitSlim fitStyleCigarette trousersCompositionPolyester 82%, Viscose 16%, Elastane 2%Care instructionsMachine wash at 30°DescriptionGrey/BlackCheckedConceptH&M MANNice to knowConsciousPrice (MRP)Rs. 1,499 incl. of all taxesCountry of productionChinaCommon generic nameTrousersNet quantity1 NMarketed or imported byH&M Hennes & Mauritz Retail Pvt. Ltd. A-wing, D-3, 2nd Floor District Centre Saket New Delhi -110017 IndiaDate of import06-2021Date of manufactureN/AManufactured byN/ACustomer serviceIn case of consumer complaint, write to H&M Hennes & Mauritz Retail PVT. Ltd, A Wing, D3, 2nd Floor, District Center, Saket, New Delhi 110017, India or call Telephone: 0008000501633. For online and store complaints email customerservice.in@hm.com.DisclaimerThis information is based on sample of the product displayed on website. There may be change in the information on label attached to the product delivered to the customer due to size chosen, date of import, name of manufacturer (in case of manufacturing in India), country of manufacture, etc. The exact detail relevant to the product delivered to the customer will reflect in the label attached to the product so deliveredArt. No.0991309002",
    "img1-src": "//lp2.hm.com/hmgoepprod?set=quality%5B79%5D%2Csource%5B%2F64%2F1b%2F641b717334e92a4fa0474777b8e40613bfef35f4.jpg%5D%2Corigin%5Bdam%5D%2Ccategory%5B%5D%2Ctype%5BLOOKBOOK%5D%2Cres%5Bm%5D%2Chmver%5B1%5D&call=url[file:/product/main]",
    "img2-src": "//lp2.hm.com/hmgoepprod?set=quality%5B79%5D%2Csource%5B%2Fb3%2Fb5%2Fb3b559f6b3bf34e25ef9c15f6f2ae993ec527994.jpg%5D%2Corigin%5Bdam%5D%2Ccategory%5B%5D%2Ctype%5BLOOKBOOK%5D%2Cres%5Bm%5D%2Chmver%5B1%5D&call=url[file:/product/main]",
    "style": "Cigarette trousers",
    "generic name": "Trousers",
    "colors": "Grey/Black",
    "descript": null,
    "item__price": "Rs. 1,499",
    "Fit": "Slim fit",
    "Composition": "Polyester 82%, Viscose 16%, Elastane 2%"
  },
  {
    "web-scraper-order": "1629124609-134",
    "web-scraper-start-url": "https://www2.hm.com/en_in/men/shop-by-product/trousers.html",
    "link": "Relaxed Fit Trousers",
    "link-href": "https://www2.hm.com/en_in/productpage.0843634011.html",
    "name": "Relaxed Fit Trousers",
    "description": "Trousers in woven fabric with covered elastication and a drawstring at the waist, a zip fly and a hook-and-eye fastening, side pockets and a welt back pocket. Relaxed Fit – a fit with good room for movement creating a comfortable, relaxed silhouette.",
    "review_count": null,
    "details": "Details\n\t\n\t\tLengthLongWaist RiseRegular waistFitRelaxed fitStyleTaperedCompositionShell: Linen 55%, Cotton 45%Pocket lining: Polyester 65%, Cotton 35%DescriptionDark beigeSolid colourConceptH&M MANNice to knowPremium SelectionPrice (MRP)Rs. 2,299 incl. of all taxesCountry of productionBangladeshCommon generic nameTrousersNet quantity1 NMarketed or imported byH&M Hennes & Mauritz Retail Pvt. Ltd. A-wing, D-3, 2nd Floor District Centre Saket New Delhi -110017 IndiaDate of import02-2021Date of manufactureN/AManufactured byN/ACustomer serviceIn case of consumer complaint, write to H&M Hennes & Mauritz Retail PVT. Ltd, A Wing, D3, 2nd Floor, District Center, Saket, New Delhi 110017, India or call Telephone: 0008000501633. For online and store complaints email customerservice.in@hm.com.DisclaimerThis information is based on sample of the product displayed on website. There may be change in the information on label attached to the product delivered to the customer due to size chosen, date of import, name of manufacturer (in case of manufacturing in India), country of manufacture, etc. The exact detail relevant to the product delivered to the customer will reflect in the label attached to the product so deliveredArt. No.0843634011",
    "img1-src": "//lp2.hm.com/hmgoepprod?set=quality%5B79%5D%2Csource%5B%2F69%2Fcc%2F69cc7039bd9d7933c3a002b70afe70f269ea93b2.jpg%5D%2Corigin%5Bdam%5D%2Ccategory%5B%5D%2Ctype%5BLOOKBOOK%5D%2Cres%5Bm%5D%2Chmver%5B1%5D&call=url[file:/product/main]",
    "img2-src": "//lp2.hm.com/hmgoepprod?set=quality%5B79%5D%2Csource%5B%2F56%2F6b%2F566b87f8aa3346a7ada1374300ceb78a8fa12973.jpg%5D%2Corigin%5Bdam%5D%2Ccategory%5B%5D%2Ctype%5BLOOKBOOK%5D%2Cres%5Bm%5D%2Chmver%5B1%5D&call=url[file:/product/main]",
    "style": "Tapered",
    "generic name": "Trousers",
    "colors": "Dark beige",
    "descript": "Solid colour",
    "item__price": "Rs. 2,299",
    "Fit": "Relaxed fit",
    "Composition": "Shell: Linen 55%, Cotton 45%Pocket lining: Polyester 65%, Cotton 35%"
  },
  {
    "web-scraper-order": "1629124455-86",
    "web-scraper-start-url": "https://www2.hm.com/en_in/men/shop-by-product/trousers.html",
    "link": "Cotton joggers",
    "link-href": "https://www2.hm.com/en_in/productpage.0967542004.html",
    "name": "Cotton joggers",
    "description": "Blank Staples is a streetwear collection of minimalistic pieces that are the perfect canvas for your personal style and creativity. These pared-back joggers are made from heavy, 460 g organic cotton sweatshirt fabric for a premium handfeel. They have covered elastication at the waist and hems, jersey-lined pockets in the side seams and an open back pocket.",
    "review_count": null,
    "details": "Details\n\t\n\t\tLengthLongWaist RiseRegular waistStyleJoggersCompositionCotton 100%Care instructionsMachine wash at 40°MaterialCottonDescriptionSteel greySolid colourConceptBASICSCollectionBlank StaplesPrice (MRP)Rs. 2,299 incl. of all taxesCountry of productionBangladeshCommon generic nameTrousersNet quantity1 NMarketed or imported byH&M Hennes & Mauritz Retail Pvt. Ltd. A-wing, D-3, 2nd Floor District Centre Saket New Delhi -110017 IndiaDate of import08-2021Date of manufactureN/AManufactured byN/ACustomer serviceIn case of consumer complaint, write to H&M Hennes & Mauritz Retail PVT. Ltd, A Wing, D3, 2nd Floor, District Center, Saket, New Delhi 110017, India or call Telephone: 0008000501633. For online and store complaints email customerservice.in@hm.com.DisclaimerThis information is based on sample of the product displayed on website. There may be change in the information on label attached to the product delivered to the customer due to size chosen, date of import, name of manufacturer (in case of manufacturing in India), country of manufacture, etc. The exact detail relevant to the product delivered to the customer will reflect in the label attached to the product so deliveredArt. No.0967542004",
    "img1-src": "//lp2.hm.com/hmgoepprod?set=quality%5B79%5D%2Csource%5B%2F49%2F47%2F494743a8e810c821c1e7f0fd2ad09350411aaf34.jpg%5D%2Corigin%5Bdam%5D%2Ccategory%5B%5D%2Ctype%5BDESCRIPTIVESTILLLIFE%5D%2Cres%5Bm%5D%2Chmver%5B2%5D&call=url[file:/product/main]",
    "img2-src": "//lp2.hm.com/hmgoepprod?set=quality%5B79%5D%2Csource%5B%2F73%2Fe9%2F73e96e853da4a178d0e3783d6d7c1e35ea19d41f.jpg%5D%2Corigin%5Bdam%5D%2Ccategory%5B%5D%2Ctype%5BDESCRIPTIVEDETAIL%5D%2Cres%5Bm%5D%2Chmver%5B2%5D&call=url[file:/product/main]",
    "style": "Joggers",
    "generic name": "Trousers",
    "colors": "Steel grey",
    "descript": null,
    "item__price": "Rs. 2,299",
    "Fit": null,
    "Composition": "Cotton 100%"
  },
  {
    "web-scraper-order": "1629124452-85",
    "web-scraper-start-url": "https://www2.hm.com/en_in/men/shop-by-product/trousers.html",
    "link": "Slim Fit Chinos",
    "link-href": "https://www2.hm.com/en_in/productpage.0815456010.html",
    "name": "Slim Fit Chinos",
    "description": "Chinos in extra-stretchy cotton twill with a zip fly, side pockets, a coin pocket and welt back pockets with a button. Slim Fit – a fit that is close-fitting at the thighs, knees and ankles to create a fitted silhouette.",
    "review_count": null,
    "details": "Details\n\t\n\t\tLengthLongFitSlim fitStyleChinosCompositionCotton 98%, Elastane 2%Pocket lining: Cotton 100%Care instructionsMachine wash at 40°MaterialCottonDescriptionDark blueSolid colourPrice (MRP)Rs. 1,999 incl. of all taxesCountry of productionBangladeshCommon generic nameTrousersSize: 28/30Width: 79 cmLength: 73 cmSize: 28/32Width: 79 cmLength: 77 cmSize: 29/32Width: 81 cmLength: 78 cmSize: 30/32Width: 84 cmLength: 78 cmSize: 31/32Width: 86 cmLength: 78 cmSize: 32/32Width: 89 cmLength: 79 cmSize: 33/32Width: 91 cmLength: 79 cmSize: 34/32Width: 94 cmLength: 80 cmSize: 36/32Width: 99 cmLength: 80 cmSize: 38/32Width: 1.04 mLength: 81 cmNet quantity1 NMarketed or imported byH&M Hennes & Mauritz Retail Pvt. Ltd. A-wing, D-3, 2nd Floor District Centre Saket New Delhi -110017 IndiaDate of import06-2021Date of manufactureN/AManufactured byN/ACustomer serviceIn case of consumer complaint, write to H&M Hennes & Mauritz Retail PVT. Ltd, A Wing, D3, 2nd Floor, District Center, Saket, New Delhi 110017, India or call Telephone: 0008000501633. For online and store complaints email customerservice.in@hm.com.DisclaimerThis information is based on sample of the product displayed on website. There may be change in the information on label attached to the product delivered to the customer due to size chosen, date of import, name of manufacturer (in case of manufacturing in India), country of manufacture, etc. The exact detail relevant to the product delivered to the customer will reflect in the label attached to the product so deliveredArt. No.0815456010",
    "img1-src": "//lp2.hm.com/hmgoepprod?set=quality%5B79%5D%2Csource%5B%2F6f%2Fd6%2F6fd6516982eb50892a798049c53a691c0c434965.jpg%5D%2Corigin%5Bdam%5D%2Ccategory%5Bmen_trousers_chinos_slim_all%5D%2Ctype%5BLOOKBOOK%5D%2Cres%5Bm%5D%2Chmver%5B1%5D&call=url[file:/product/main]",
    "img2-src": "//lp2.hm.com/hmgoepprod?set=quality%5B79%5D%2Csource%5B%2Ffb%2F50%2Ffb50ca317813b53cd401e660f6c9a33980b0cc83.jpg%5D%2Corigin%5Bdam%5D%2Ccategory%5Bmen_trousers_chinos_slim_all%5D%2Ctype%5BLOOKBOOK%5D%2Cres%5Bm%5D%2Chmver%5B1%5D&call=url[file:/product/main]",
    "style": "Chinos",
    "generic name": "Trousers",
    "colors": "Dark blue",
    "descript": null,
    "item__price": "Rs. 1,999",
    "Fit": "Slim fit",
    "Composition": "Cotton 98%, Elastane 2%Pocket lining: Cotton 100%"
  },
  {
    "web-scraper-order": "1629124547-114",
    "web-scraper-start-url": "https://www2.hm.com/en_in/men/shop-by-product/trousers.html",
    "link": "Slim Fit Joggers",
    "link-href": "https://www2.hm.com/en_in/productpage.0988366007.html",
    "name": "Slim Fit Joggers",
    "description": "Dressy joggers in woven fabric with covered elastication and a drawstring at the waist, side pockets, a welt back pocket and legs with creases. Slim Fit – a fit that is close-fitting at the thighs, knees and ankles to create a fitted silhouette.",
    "review_count": null,
    "details": "Details\n\t\n\t\tSizeInside leg: Length: 76.5 cm (Size L/L)LengthLongWaist RiseRegular waistFitSlim fitStyleJoggersCompositionShell: Polyester 77%, Viscose 21%, Elastane 2%Pocket lining: Polyester 65%, Cotton 35%Care instructionsMachine wash at 30°DescriptionLight beigeSolid colourNice to knowConsciousPrice (MRP)Rs. 1,499 incl. of all taxesCountry of productionBangladeshCommon generic nameTrousersNet quantity1 NMarketed or imported byH&M Hennes & Mauritz Retail Pvt. Ltd. A-wing, D-3, 2nd Floor District Centre Saket New Delhi -110017 IndiaDate of import05-2021Date of manufactureN/AManufactured byN/ACustomer serviceIn case of consumer complaint, write to H&M Hennes & Mauritz Retail PVT. Ltd, A Wing, D3, 2nd Floor, District Center, Saket, New Delhi 110017, India or call Telephone: 0008000501633. For online and store complaints email customerservice.in@hm.com.DisclaimerThis information is based on sample of the product displayed on website. There may be change in the information on label attached to the product delivered to the customer due to size chosen, date of import, name of manufacturer (in case of manufacturing in India), country of manufacture, etc. The exact detail relevant to the product delivered to the customer will reflect in the label attached to the product so deliveredArt. No.0988366007",
    "img1-src": "//lp2.hm.com/hmgoepprod?set=quality%5B79%5D%2Csource%5B%2F8f%2F5d%2F8f5d2751b96362940979e1fa0b1f3b68f5b45139.jpg%5D%2Corigin%5Bdam%5D%2Ccategory%5B%5D%2Ctype%5BLOOKBOOK%5D%2Cres%5Bm%5D%2Chmver%5B1%5D&call=url[file:/product/main]",
    "img2-src": "//lp2.hm.com/hmgoepprod?set=quality%5B79%5D%2Csource%5B%2Fe2%2F39%2Fe2394d99b6f19d1ab545c0291074710a3562bf1f.jpg%5D%2Corigin%5Bdam%5D%2Ccategory%5B%5D%2Ctype%5BLOOKBOOK%5D%2Cres%5Bm%5D%2Chmver%5B1%5D&call=url[file:/product/main]",
    "style": "Joggers",
    "generic name": "Trousers",
    "colors": "Light beige",
    "descript": "Pocket lining: Polyester 65%, Cotton 35%",
    "item__price": "Rs. 1,499",
    "Fit": "Slim fit",
    "Composition": "Shell: Polyester 77%, Viscose 21%, Elastane 2%Pocket lining: Polyester 65%, Cotton 35%"
  },
  {
    "web-scraper-order": "1629124492-97",
    "web-scraper-start-url": "https://www2.hm.com/en_in/men/shop-by-product/trousers.html",
    "link": "Twill trousers Slim Fit",
    "link-href": "https://www2.hm.com/en_in/productpage.0721390032.html",
    "name": "Twill trousers Slim Fit",
    "description": "5-pocket trousers in washed stretch twill with a regular waist and zip fly. Slim fit which is relaxed over the thighs and tapers from the knees down for a relaxed, well-tailored look.",
    "review_count": "(678)",
    "details": "Details\n\t\n\t\tLengthLongWaist RiseRegular waistFitSlim fitCompositionCotton 98%, Elastane 2%Pocket: Cotton 100%Care instructionsMachine wash at 40°MaterialCottonDescriptionDark khaki greenSolid colourConceptH&M MANPrice (MRP)Rs. 1,499 incl. of all taxesCountry of productionBangladeshCommon generic nameTrousersNet quantity1 NDate of manufacture02-2021Manufactured bySHAHI EXPORTS PRIVATE LIMITED\nINDUSTRIAL PLOT NO. 1, SECTOR 28, 121008, FARIDABADCustomer serviceIn case of consumer complaint, write to H&M Hennes & Mauritz Retail PVT. Ltd, A Wing, D3, 2nd Floor, District Center, Saket, New Delhi 110017, India or call Telephone: 0008000501633. For online and store complaints email customerservice.in@hm.com.DisclaimerThis information is based on sample of the product displayed on website. There may be change in the information on label attached to the product delivered to the customer due to size chosen, date of import, name of manufacturer (in case of manufacturing in India), country of manufacture, etc. The exact detail relevant to the product delivered to the customer will reflect in the label attached to the product so deliveredArt. No.0721390032",
    "img1-src": "//lp2.hm.com/hmgoepprod?set=quality%5B79%5D%2Csource%5B%2F75%2Ff7%2F75f78bc5887149f3f3766963d476bc5dc2393716.jpg%5D%2Corigin%5Bdam%5D%2Ccategory%5Bmen_trousers_trousers_slim_all%5D%2Ctype%5BDESCRIPTIVESTILLLIFE%5D%2Cres%5Bm%5D%2Chmver%5B2%5D&call=url[file:/product/main]",
    "img2-src": "//lp2.hm.com/hmgoepprod?set=quality%5B79%5D%2Csource%5B%2F5a%2F18%2F5a182a6a58a1f3939226b23fab1e6d9191e5cd0d.jpg%5D%2Corigin%5Bdam%5D%2Ccategory%5Bmen_trousers_trousers_slim_all%5D%2Ctype%5BDESCRIPTIVEDETAIL%5D%2Cres%5Bm%5D%2Chmver%5B2%5D&call=url[file:/product/main]",
    "style": null,
    "generic name": "Trousers",
    "colors": "Dark khaki green",
    "descript": null,
    "item__price": "Rs. 1,499",
    "Fit": "Slim fit",
    "Composition": "Cotton 98%, Elastane 2%Pocket: Cotton 100%"
  },
  {
    "web-scraper-order": "1629124595-129",
    "web-scraper-start-url": "https://www2.hm.com/en_in/men/shop-by-product/trousers.html",
    "link": "2-pack Regular Fit Joggers",
    "link-href": "https://www2.hm.com/en_in/productpage.0970816002.html",
    "name": "2-pack Regular Fit Joggers",
    "description": "Joggers in sweatshirt fabric made from a cotton blend. Covered elastication and a drawstring at the waist, pockets in the side seams and ribbed hems. Soft brushed inside.",
    "review_count": null,
    "details": "Details\n\t\n\t\tPieces2LengthLongWaist RiseRegular waistFitRegular fitStyleJoggersCompositionCotton 55%, Polyester 45%Cotton 55%, Polyester 45%Care instructionsMachine wash at 40°DescriptionDark grey/Navy blueSolid colourConceptBASICSPrice (MRP)Rs. 2,299 incl. of all taxesCountry of productionBangladeshCommon generic nameTrousersNet quantity2 NMarketed or imported byH&M Hennes & Mauritz Retail Pvt. Ltd. A-wing, D-3, 2nd Floor District Centre Saket New Delhi -110017 IndiaDate of import06-2021Date of manufactureN/AManufactured byN/ACustomer serviceIn case of consumer complaint, write to H&M Hennes & Mauritz Retail PVT. Ltd, A Wing, D3, 2nd Floor, District Center, Saket, New Delhi 110017, India or call Telephone: 0008000501633. For online and store complaints email customerservice.in@hm.com.DisclaimerThis information is based on sample of the product displayed on website. There may be change in the information on label attached to the product delivered to the customer due to size chosen, date of import, name of manufacturer (in case of manufacturing in India), country of manufacture, etc. The exact detail relevant to the product delivered to the customer will reflect in the label attached to the product so deliveredArt. No.0970816002",
    "img1-src": "//lp2.hm.com/hmgoepprod?set=quality%5B79%5D%2Csource%5B%2Faa%2F92%2Faa92229c5d9abffeb2450392c0e08e126e399ac3.jpg%5D%2Corigin%5Bdam%5D%2Ccategory%5B%5D%2Ctype%5BLOOKBOOK%5D%2Cres%5Bm%5D%2Chmver%5B1%5D&call=url[file:/product/main]",
    "img2-src": "//lp2.hm.com/hmgoepprod?set=quality%5B79%5D%2Csource%5B%2F96%2F9e%2F969e9b281a07846edce1312e69ce0667ad0e74e8.jpg%5D%2Corigin%5Bdam%5D%2Ccategory%5B%5D%2Ctype%5BLOOKBOOK%5D%2Cres%5Bm%5D%2Chmver%5B1%5D&call=url[file:/product/main]",
    "style": "Joggers",
    "generic name": "Trousers",
    "colors": "Dark grey/Navy blue",
    "descript": "Cotton 55%, Polyester 45%",
    "item__price": "Rs. 2,299",
    "Fit": "Regular fit",
    "Composition": "Cotton 55%, Polyester 45%Cotton 55%, Polyester 45%"
  },
  {
    "web-scraper-order": "1629124588-127",
    "web-scraper-start-url": "https://www2.hm.com/en_in/men/shop-by-product/trousers.html",
    "link": "Regular Fit Joggers",
    "link-href": "https://www2.hm.com/en_in/productpage.0970817006.html",
    "name": "Regular Fit Joggers",
    "description": "Joggers in sweatshirt fabric made from a cotton blend. Covered elastication and a drawstring at the waist, pockets in the side seams and ribbed hems. Soft brushed inside.",
    "review_count": null,
    "details": "Details\n\t\n\t\tLengthLongWaist RiseRegular waistFitRegular fitStyleJoggersCompositionCotton 60%, Polyester 40%Care instructionsMachine wash at 40°DescriptionSteel greySolid colourPrice (MRP)Rs. 1,299 incl. of all taxesCountry of productionIndonesiaCommon generic nameTrousersNet quantity1 NMarketed or imported byH&M Hennes & Mauritz Retail Pvt. Ltd. A-wing, D-3, 2nd Floor District Centre Saket New Delhi -110017 IndiaDate of import06-2021Date of manufactureN/AManufactured byN/ACustomer serviceIn case of consumer complaint, write to H&M Hennes & Mauritz Retail PVT. Ltd, A Wing, D3, 2nd Floor, District Center, Saket, New Delhi 110017, India or call Telephone: 0008000501633. For online and store complaints email customerservice.in@hm.com.DisclaimerThis information is based on sample of the product displayed on website. There may be change in the information on label attached to the product delivered to the customer due to size chosen, date of import, name of manufacturer (in case of manufacturing in India), country of manufacture, etc. The exact detail relevant to the product delivered to the customer will reflect in the label attached to the product so deliveredArt. No.0970817006",
    "img1-src": "//lp2.hm.com/hmgoepprod?set=quality%5B79%5D%2Csource%5B%2Ff2%2F47%2Ff24712b7b8ffce51cc4c9efc45afb0610a22d0a0.jpg%5D%2Corigin%5Bdam%5D%2Ccategory%5B%5D%2Ctype%5BLOOKBOOK%5D%2Cres%5Bm%5D%2Chmver%5B1%5D&call=url[file:/product/main]",
    "img2-src": "//lp2.hm.com/hmgoepprod?set=quality%5B79%5D%2Csource%5B%2F10%2F76%2F1076ca1b4753577be22bc0a41754ccd01b0b428d.jpg%5D%2Corigin%5Bdam%5D%2Ccategory%5B%5D%2Ctype%5BLOOKBOOK%5D%2Cres%5Bm%5D%2Chmver%5B1%5D&call=url[file:/product/main]",
    "style": "Joggers",
    "generic name": "Trousers",
    "colors": "Steel grey",
    "descript": null,
    "item__price": "Rs. 1,299",
    "Fit": "Regular fit",
    "Composition": "Cotton 60%, Polyester 40%"
  },
  {
    "web-scraper-order": "1629124606-133",
    "web-scraper-start-url": "https://www2.hm.com/en_in/men/shop-by-product/trousers.html",
    "link": "Slim Fit Chinos",
    "link-href": "https://www2.hm.com/en_in/productpage.0815456001.html",
    "name": "Slim Fit Chinos",
    "description": "Chinos in extra-stretchy cotton twill with a zip fly, side pockets, a coin pocket and welt back pockets with a button. Slim Fit – a fit that is close-fitting at the thighs, knees and ankles to create a fitted silhouette.",
    "review_count": null,
    "details": "Details\n\t\n\t\tLengthLongFitSlim fitStyleChinosCompositionPocket lining: Cotton 100%Cotton 98%, Elastane 2%Care instructionsMachine wash at 40°MaterialCottonDescriptionBlackSolid colourPrice (MRP)Rs. 1,999 incl. of all taxesCountry of productionBangladeshCommon generic nameTrousersSize: 28/30Width: 79 cmLength: 73 cmSize: 28/32Width: 79 cmLength: 77 cmSize: 29/32Width: 81 cmLength: 78 cmSize: 30/32Width: 84 cmLength: 78 cmSize: 31/32Width: 86 cmLength: 78 cmSize: 32/32Width: 89 cmLength: 79 cmSize: 32/34Width: 89 cmLength: 82 cmSize: 33/32Width: 91 cmLength: 79 cmSize: 33/34Width: 91 cmLength: 83 cmSize: 34/32Width: 94 cmLength: 80 cmSize: 34/34Width: 94 cmLength: 83 cmSize: 36/32Width: 99 cmLength: 80 cmSize: 36/34Width: 99 cmLength: 84 cmSize: 38/32Width: 1.04 mLength: 81 cmNet quantity1 NMarketed or imported byH&M Hennes & Mauritz Retail Pvt. Ltd. A-wing, D-3, 2nd Floor District Centre Saket New Delhi -110017 IndiaDate of import06-2021Date of manufactureN/AManufactured byN/ACustomer serviceIn case of consumer complaint, write to H&M Hennes & Mauritz Retail PVT. Ltd, A Wing, D3, 2nd Floor, District Center, Saket, New Delhi 110017, India or call Telephone: 0008000501633. For online and store complaints email customerservice.in@hm.com.DisclaimerThis information is based on sample of the product displayed on website. There may be change in the information on label attached to the product delivered to the customer due to size chosen, date of import, name of manufacturer (in case of manufacturing in India), country of manufacture, etc. The exact detail relevant to the product delivered to the customer will reflect in the label attached to the product so deliveredArt. No.0815456001",
    "img1-src": "//lp2.hm.com/hmgoepprod?set=quality%5B79%5D%2Csource%5B%2F40%2F41%2F404180c2edbb73a0414a4d417cf1f0d0f8507651.jpg%5D%2Corigin%5Bdam%5D%2Ccategory%5Bmen_trousers_chinos_slim_all%5D%2Ctype%5BLOOKBOOK%5D%2Cres%5Bm%5D%2Chmver%5B1%5D&call=url[file:/product/main]",
    "img2-src": "//lp2.hm.com/hmgoepprod?set=quality%5B79%5D%2Csource%5B%2Fb0%2Fad%2Fb0adf9a5dfbf6804f79ec0fdd73978e89d501f42.jpg%5D%2Corigin%5Bdam%5D%2Ccategory%5Bmen_trousers_chinos_slim_all%5D%2Ctype%5BLOOKBOOK%5D%2Cres%5Bm%5D%2Chmver%5B1%5D&call=url[file:/product/main]",
    "style": "Chinos",
    "generic name": "Trousers",
    "colors": "Black",
    "descript": null,
    "item__price": "Rs. 1,999",
    "Fit": "Slim fit",
    "Composition": "Pocket lining: Cotton 100%Cotton 98%, Elastane 2%"
  },
  {
    "web-scraper-order": "1629124536-110",
    "web-scraper-start-url": "https://www2.hm.com/en_in/men/shop-by-product/trousers.html",
    "link": "Slim Fit Joggers",
    "link-href": "https://www2.hm.com/en_in/productpage.0988366006.html",
    "name": "Slim Fit Joggers",
    "description": "Dressy joggers in woven fabric with covered elastication and a drawstring at the waist, side pockets, a welt back pocket and legs with creases. Slim Fit – a fit that is close-fitting at the thighs, knees and ankles to create a fitted silhouette.",
    "review_count": null,
    "details": "Details\n\t\n\t\tSizeInside leg: Length: 76.5 cm (Size L/L)LengthLongWaist RiseRegular waistFitSlim fitStyleJoggersCompositionPocket lining: Polyester 81%, Cotton 19%Shell: Polyester 76%, Viscose 22%, Elastane 2%Care instructionsMachine wash at 30°DescriptionBlack/WhiteCheckedNice to knowConsciousPrice (MRP)Rs. 1,499 incl. of all taxesCountry of productionChinaCommon generic nameTrousersNet quantity1 NMarketed or imported byH&M Hennes & Mauritz Retail Pvt. Ltd. A-wing, D-3, 2nd Floor District Centre Saket New Delhi -110017 IndiaDate of import07-2021Date of manufactureN/AManufactured byN/ACustomer serviceIn case of consumer complaint, write to H&M Hennes & Mauritz Retail PVT. Ltd, A Wing, D3, 2nd Floor, District Center, Saket, New Delhi 110017, India or call Telephone: 0008000501633. For online and store complaints email customerservice.in@hm.com.DisclaimerThis information is based on sample of the product displayed on website. There may be change in the information on label attached to the product delivered to the customer due to size chosen, date of import, name of manufacturer (in case of manufacturing in India), country of manufacture, etc. The exact detail relevant to the product delivered to the customer will reflect in the label attached to the product so deliveredArt. No.0988366006",
    "img1-src": "//lp2.hm.com/hmgoepprod?set=quality%5B79%5D%2Csource%5B%2F61%2F5a%2F615a12b39af4600c8aa203c199f05e3eb8a63cad.jpg%5D%2Corigin%5Bdam%5D%2Ccategory%5B%5D%2Ctype%5BLOOKBOOK%5D%2Cres%5Bm%5D%2Chmver%5B1%5D&call=url[file:/product/main]",
    "img2-src": "//lp2.hm.com/hmgoepprod?set=quality%5B79%5D%2Csource%5B%2F13%2F26%2F1326e1063c95a0ddf993ebc52d9a604bbc8334b0.jpg%5D%2Corigin%5Bdam%5D%2Ccategory%5B%5D%2Ctype%5BLOOKBOOK%5D%2Cres%5Bm%5D%2Chmver%5B1%5D&call=url[file:/product/main]",
    "style": "Joggers",
    "generic name": "Trousers",
    "colors": "Black/White",
    "descript": "Shell: Polyester 76%, Viscose 22%, Elastane 2%",
    "item__price": "Rs. 1,499",
    "Fit": "Slim fit",
    "Composition": "Pocket lining: Polyester 81%, Cotton 19%Shell: Polyester 76%, Viscose 22%, Elastane 2%"
  },
  {
    "web-scraper-order": "1629124432-79",
    "web-scraper-start-url": "https://www2.hm.com/en_in/men/shop-by-product/trousers.html",
    "link": "Suit trousers Skinny Fit",
    "link-href": "https://www2.hm.com/en_in/productpage.0714032026.html",
    "name": "Suit trousers Skinny Fit",
    "description": "Suit trousers in a stretch weave with a concealed hook-and-eye fastener and zip fly. Side pockets, welt back pockets and legs with creases. Skinny fit – a fit with slightly shorter legs that is close-fitting at the thighs, knees and ankles to create a completely fitted silhouette.",
    "review_count": null,
    "details": "Details\n\t\n\t\tLengthLongFitSkinny fitStyleSuit trousersCompositionPolyester 63%, Viscose 35%, Elastane 2%Pocket: Polyester 82%, Cotton 18%Care instructionsMachine wash at 30°DescriptionBeige/WhiteCheckedConceptH&M MANNice to knowConsciousPrice (MRP)Rs. 2,299 incl. of all taxesCountry of productionMyanmarCommon generic nameTrousersNet quantity1 NMarketed or imported byH&M Hennes & Mauritz Retail Pvt. Ltd. A-wing, D-3, 2nd Floor District Centre Saket New Delhi -110017 IndiaDate of import02-2021Date of manufactureN/AManufactured byN/ACustomer serviceIn case of consumer complaint, write to H&M Hennes & Mauritz Retail PVT. Ltd, A Wing, D3, 2nd Floor, District Center, Saket, New Delhi 110017, India or call Telephone: 0008000501633. For online and store complaints email customerservice.in@hm.com.DisclaimerThis information is based on sample of the product displayed on website. There may be change in the information on label attached to the product delivered to the customer due to size chosen, date of import, name of manufacturer (in case of manufacturing in India), country of manufacture, etc. The exact detail relevant to the product delivered to the customer will reflect in the label attached to the product so deliveredArt. No.0714032026",
    "img1-src": "//lp2.hm.com/hmgoepprod?set=quality%5B79%5D%2Csource%5B%2F8a%2F16%2F8a1673da9e9d83c65f3f9694703f0f7c5ef9857d.jpg%5D%2Corigin%5Bdam%5D%2Ccategory%5Bmen_trousers_dressed%5D%2Ctype%5BLOOKBOOK%5D%2Cres%5Bm%5D%2Chmver%5B1%5D&call=url[file:/product/main]",
    "img2-src": "//lp2.hm.com/hmgoepprod?set=quality%5B79%5D%2Csource%5B%2F9b%2F21%2F9b215857d161abd6e148f3bbc4837642f1b5a412.jpg%5D%2Corigin%5Bdam%5D%2Ccategory%5Bmen_trousers_dressed%5D%2Ctype%5BLOOKBOOK%5D%2Cres%5Bm%5D%2Chmver%5B1%5D&call=url[file:/product/main]",
    "style": "Suit trousers",
    "generic name": "Trousers",
    "colors": "Beige/White",
    "descript": "Checked",
    "item__price": "Rs. 2,299",
    "Fit": "Skinny fit",
    "Composition": "Polyester 63%, Viscose 35%, Elastane 2%Pocket: Polyester 82%, Cotton 18%"
  },
  {
    "web-scraper-order": "1629124316-43",
    "web-scraper-start-url": "https://www2.hm.com/en_in/men/shop-by-product/trousers.html",
    "link": "Slim Fit Jersey suit trousers",
    "link-href": "https://www2.hm.com/en_in/productpage.0943982001.html",
    "name": "Slim Fit Jersey suit trousers",
    "description": "Cropped suit trousers in stretch jersey with an extended waistband, concealed hook-and-eye fastener, and a zip fly. Side pockets, welt back pockets and legs with creases. Slim Fit – a fit that is close-fitting at the thighs, knees and ankles to create a fitted silhouette.",
    "review_count": null,
    "details": "Details\n\t\n\t\tSizeWaist: Circumference: 93.5 cm (Size 52L)Inside leg: Length: 73.7 cm (Size 52L)LengthAnkle lengthWaist RiseRegular waistFitSlim fitStyleSuit trousersCompositionShell: Viscose 66%, Polyamide 30%, Elastane 4%Pocket lining: Polyester 92%, Cotton 8%Care instructionsMachine wash at 30°DescriptionGreyConceptH&M MANPrice (MRP)Rs. 2,299 incl. of all taxesCountry of productionChinaCommon generic nameTrousersNet quantity1 NMarketed or imported byH&M Hennes & Mauritz Retail Pvt. Ltd. A-wing, D-3, 2nd Floor District Centre Saket New Delhi -110017 IndiaDate of import12-2020Date of manufactureN/AManufactured byN/ACustomer serviceIn case of consumer complaint, write to H&M Hennes & Mauritz Retail PVT. Ltd, A Wing, D3, 2nd Floor, District Center, Saket, New Delhi 110017, India or call Telephone: 0008000501633. For online and store complaints email customerservice.in@hm.com.DisclaimerThis information is based on sample of the product displayed on website. There may be change in the information on label attached to the product delivered to the customer due to size chosen, date of import, name of manufacturer (in case of manufacturing in India), country of manufacture, etc. The exact detail relevant to the product delivered to the customer will reflect in the label attached to the product so deliveredArt. No.0943982001",
    "img1-src": "//lp2.hm.com/hmgoepprod?set=quality%5B79%5D%2Csource%5B%2F1d%2Faa%2F1daa6479bfe9aa38bb0c1d636342f987ce20e219.jpg%5D%2Corigin%5Bdam%5D%2Ccategory%5B%5D%2Ctype%5BLOOKBOOK%5D%2Cres%5Bm%5D%2Chmver%5B1%5D&call=url[file:/product/main]",
    "img2-src": "//lp2.hm.com/hmgoepprod?set=quality%5B79%5D%2Csource%5B%2F25%2F17%2F2517d69f99ea40e7d5eed9c66596cd8eb5118529.jpg%5D%2Corigin%5Bdam%5D%2Ccategory%5B%5D%2Ctype%5BLOOKBOOK%5D%2Cres%5Bm%5D%2Chmver%5B1%5D&call=url[file:/product/main]",
    "style": "Suit trousers",
    "generic name": "Trousers",
    "colors": "Grey",
    "descript": "Pocket lining: Polyester 92%, Cotton 8%",
    "item__price": "Rs. 2,299",
    "Fit": "Slim fit",
    "Composition": "Shell: Viscose 66%, Polyamide 30%, Elastane 4%Pocket lining: Polyester 92%, Cotton 8%"
  },
  {
    "web-scraper-order": "1629124556-117",
    "web-scraper-start-url": "https://www2.hm.com/en_in/men/shop-by-product/trousers.html",
    "link": "Slim Fit Sports joggers",
    "link-href": "https://www2.hm.com/en_in/productpage.0995680005.html",
    "name": "Slim Fit Sports joggers",
    "description": "Jersey joggers for indoor and outdoor workouts. Covered elastication and a drawstring at the waist, zipped side pockets for safe storage of valuables and a mesh panel at the crotch for increased air permeability. Cuffed hems.",
    "review_count": null,
    "details": "Details\n\t\n\t\tSizeInside leg: Length: 73.5 cm (Size L/L)LengthLongWaist RiseRegular waistFitSlim fitStyleJoggersCompositionShell: Cotton 58%, Polyester 38%, Elastane 4%Mesh: Polyester 100%Care instructionsMachine wash at 40°Sports activityTrainingDescriptionDark blueSolid colourNice to knowConsciousPrice (MRP)Rs. 1,999 incl. of all taxesCountry of productionCambodiaCommon generic nameTrousersNet quantity1 NMarketed or imported byH&M Hennes & Mauritz Retail Pvt. Ltd. A-wing, D-3, 2nd Floor District Centre Saket New Delhi -110017 IndiaDate of import08-2021Date of manufactureN/AManufactured byN/ACustomer serviceIn case of consumer complaint, write to H&M Hennes & Mauritz Retail PVT. Ltd, A Wing, D3, 2nd Floor, District Center, Saket, New Delhi 110017, India or call Telephone: 0008000501633. For online and store complaints email customerservice.in@hm.com.DisclaimerThis information is based on sample of the product displayed on website. There may be change in the information on label attached to the product delivered to the customer due to size chosen, date of import, name of manufacturer (in case of manufacturing in India), country of manufacture, etc. The exact detail relevant to the product delivered to the customer will reflect in the label attached to the product so deliveredArt. No.0995680005",
    "img1-src": "//lp2.hm.com/hmgoepprod?set=quality%5B79%5D%2Csource%5B%2F07%2F5d%2F075db8a220163baf4375068f7c6298690052b476.jpg%5D%2Corigin%5Bdam%5D%2Ccategory%5B%5D%2Ctype%5BLOOKBOOK%5D%2Cres%5Bm%5D%2Chmver%5B1%5D&call=url[file:/product/main]",
    "img2-src": "//lp2.hm.com/hmgoepprod?set=quality%5B79%5D%2Csource%5B%2F27%2Fd1%2F27d12d7fa097a6799d7b2e7ef60c145ac997c006.jpg%5D%2Corigin%5Bdam%5D%2Ccategory%5B%5D%2Ctype%5BLOOKBOOK%5D%2Cres%5Bm%5D%2Chmver%5B1%5D&call=url[file:/product/main]",
    "style": "Joggers",
    "generic name": "Trousers",
    "colors": "Dark blue",
    "descript": "Mesh: Polyester 100%",
    "item__price": "Rs. 1,999",
    "Fit": "Slim fit",
    "Composition": "Shell: Cotton 58%, Polyester 38%, Elastane 4%Mesh: Polyester 100%"
  },
  {
    "web-scraper-order": "1629124603-132",
    "web-scraper-start-url": "https://www2.hm.com/en_in/men/shop-by-product/trousers.html",
    "link": "Cargo joggers",
    "link-href": "https://www2.hm.com/en_in/productpage.0606395006.html",
    "name": "Cargo joggers",
    "description": "Cargo joggers in stretch cotton twill with an elasticated drawstring waist, side pockets and flap back and leg pockets with press-studs. Fake fly, shaping seams at the knees and ribbed hems.",
    "review_count": "(297)",
    "details": "Details\n\t\n\t\tLengthLongStyleCargoTaperedJoggersCompositionCotton 98%, Elastane 2%Pocket lining: Cotton 100%Care instructionsMachine wash at 30°DescriptionBlackSolid colourPrice (MRP)Rs. 2,699 incl. of all taxesCountry of productionMyanmarCommon generic nameTrousersSize: XS/LWidth: 72 cmLength: 72 cmSize: S/LWidth: 79 cmLength: 73 cmSize: M/LWidth: 86 cmLength: 74 cmSize: L/LWidth: 93 cmLength: 75 cmSize: XL/LWidth: 100 cmLength: 76 cmSize: XXL/LWidth: 1.07 mLength: 77 cmSize: XXLWidth: 1.07 mLength: 73 cmNet quantity1 NMarketed or imported byH&M Hennes & Mauritz Retail Pvt. Ltd. A-wing, D-3, 2nd Floor District Centre Saket New Delhi -110017 IndiaDate of import04-2021Date of manufactureN/AManufactured byN/ACustomer serviceIn case of consumer complaint, write to H&M Hennes & Mauritz Retail PVT. Ltd, A Wing, D3, 2nd Floor, District Center, Saket, New Delhi 110017, India or call Telephone: 0008000501633. For online and store complaints email customerservice.in@hm.com.DisclaimerThis information is based on sample of the product displayed on website. There may be change in the information on label attached to the product delivered to the customer due to size chosen, date of import, name of manufacturer (in case of manufacturing in India), country of manufacture, etc. The exact detail relevant to the product delivered to the customer will reflect in the label attached to the product so deliveredArt. No.0606395006",
    "img1-src": "//lp2.hm.com/hmgoepprod?set=quality%5B79%5D%2Csource%5B%2Fdc%2F17%2Fdc1709026780f590e1f1088a522a764c7e1f2102.jpg%5D%2Corigin%5Bdam%5D%2Ccategory%5Bmen_trousers_joggers%5D%2Ctype%5BLOOKBOOK%5D%2Cres%5Bm%5D%2Chmver%5B1%5D&call=url[file:/product/main]",
    "img2-src": "//lp2.hm.com/hmgoepprod?set=quality%5B79%5D%2Csource%5B%2F7b%2F47%2F7b47acd9d4bb4e18c5faf1c37c5db5aeabc84a3a.jpg%5D%2Corigin%5Bdam%5D%2Ccategory%5Bmen_trousers_joggers%5D%2Ctype%5BLOOKBOOK%5D%2Cres%5Bm%5D%2Chmver%5B1%5D&call=url[file:/product/main]",
    "style": "Cargo",
    "generic name": "Trousers",
    "colors": "Black",
    "descript": null,
    "item__price": "Rs. 2,699",
    "Fit": null,
    "Composition": "Cotton 98%, Elastane 2%Pocket lining: Cotton 100%"
  },
  {
    "web-scraper-order": "1629124391-67",
    "web-scraper-start-url": "https://www2.hm.com/en_in/men/shop-by-product/trousers.html",
    "link": "Side-panel joggers",
    "link-href": "https://www2.hm.com/en_in/productpage.0936430002.html",
    "name": "Side-panel joggers",
    "description": "Joggers in soft sweatshirt fabric made from a cotton and recycled polyester blend with a nylon waistband and side panels. Covered elastication and a drawstring at the waist, welt side pockets and ribbed hems. Soft brushed inside.",
    "review_count": null,
    "details": "Details\n\t\n\t\tLengthLongStyleJoggersCompositionCotton 60%, Polyester 40%Care instructionsMachine wash at 40°DescriptionGrey marl/BlackConceptDIVIDEDPrice (MRP)Rs. 1,999 incl. of all taxesCountry of productionMyanmarCommon generic nameTrousersNet quantity1 NMarketed or imported byH&M Hennes & Mauritz Retail Pvt. Ltd. A-wing, D-3, 2nd Floor District Centre Saket New Delhi -110017 IndiaDate of import08-2021Date of manufactureN/AManufactured byN/ACustomer serviceIn case of consumer complaint, write to H&M Hennes & Mauritz Retail PVT. Ltd, A Wing, D3, 2nd Floor, District Center, Saket, New Delhi 110017, India or call Telephone: 0008000501633. For online and store complaints email customerservice.in@hm.com.DisclaimerThis information is based on sample of the product displayed on website. There may be change in the information on label attached to the product delivered to the customer due to size chosen, date of import, name of manufacturer (in case of manufacturing in India), country of manufacture, etc. The exact detail relevant to the product delivered to the customer will reflect in the label attached to the product so deliveredArt. No.0936430002",
    "img1-src": "//lp2.hm.com/hmgoepprod?set=quality%5B79%5D%2Csource%5B%2Fdb%2Fc8%2Fdbc8bb5e36b182e05445383470b9aebbf7f47010.jpg%5D%2Corigin%5Bdam%5D%2Ccategory%5Bmen_trousers_casual%5D%2Ctype%5BLOOKBOOK%5D%2Cres%5Bm%5D%2Chmver%5B1%5D&call=url[file:/product/main]",
    "img2-src": "//lp2.hm.com/hmgoepprod?set=quality%5B79%5D%2Csource%5B%2F79%2Fb9%2F79b985ec28da3c5cf0a1bde327c80171898d1d56.jpg%5D%2Corigin%5Bdam%5D%2Ccategory%5Bmen_trousers_casual%5D%2Ctype%5BLOOKBOOK%5D%2Cres%5Bm%5D%2Chmver%5B1%5D&call=url[file:/product/main]",
    "style": "Joggers",
    "generic name": "Trousers",
    "colors": "Grey marl/Black",
    "descript": null,
    "item__price": "Rs. 1,999",
    "Fit": null,
    "Composition": "Cotton 60%, Polyester 40%"
  },
  {
    "web-scraper-order": "1629124303-39",
    "web-scraper-start-url": "https://www2.hm.com/en_in/men/shop-by-product/trousers.html",
    "link": "Merino wool joggers",
    "link-href": "https://www2.hm.com/en_in/productpage.0937669001.html",
    "name": "Merino wool joggers",
    "description": "Joggers in soft, fine-knit merino wool with covered elastication and a drawstring at the waist. Side pockets, an open back pocket, a low crotch and ribbed hems.",
    "review_count": null,
    "details": "Details\n\t\n\t\tSizeInside leg: Length: 77.0 cm (Size L/L)LengthLongStyleJoggersCompositionMerino wool 100%Care instructionsWash on a wool cycle at 30°MaterialWoolMerinoDescriptionGrey marlSolid colourNice to knowPremium SelectionPrice (MRP)Rs. 4,499 incl. of all taxesCountry of productionChinaCommon generic nameTrousersNet quantity1 NMarketed or imported byH&M Hennes & Mauritz Retail Pvt. Ltd. A-wing, D-3, 2nd Floor District Centre Saket New Delhi -110017 IndiaDate of import08-2021Date of manufactureN/AManufactured byN/ACustomer serviceIn case of consumer complaint, write to H&M Hennes & Mauritz Retail PVT. Ltd, A Wing, D3, 2nd Floor, District Center, Saket, New Delhi 110017, India or call Telephone: 0008000501633. For online and store complaints email customerservice.in@hm.com.DisclaimerThis information is based on sample of the product displayed on website. There may be change in the information on label attached to the product delivered to the customer due to size chosen, date of import, name of manufacturer (in case of manufacturing in India), country of manufacture, etc. The exact detail relevant to the product delivered to the customer will reflect in the label attached to the product so deliveredArt. No.0937669001",
    "img1-src": "//lp2.hm.com/hmgoepprod?set=quality%5B79%5D%2Csource%5B%2Fb3%2F6e%2Fb36e64d9b24a6aa16fe492f887bf3d1839de255d.jpg%5D%2Corigin%5Bdam%5D%2Ccategory%5B%5D%2Ctype%5BDESCRIPTIVESTILLLIFE%5D%2Cres%5Bm%5D%2Chmver%5B1%5D&call=url[file:/product/main]",
    "img2-src": "//lp2.hm.com/hmgoepprod?set=quality%5B79%5D%2Csource%5B%2F00%2F83%2F0083fffb2d7a8dd2912adfe589b95e274caa83d7.jpg%5D%2Corigin%5Bdam%5D%2Ccategory%5B%5D%2Ctype%5BDESCRIPTIVEDETAIL%5D%2Cres%5Bm%5D%2Chmver%5B1%5D&call=url[file:/product/main]",
    "style": "Joggers",
    "generic name": "Trousers",
    "colors": "Grey marl",
    "descript": "Merino",
    "item__price": "Rs. 4,499",
    "Fit": null,
    "Composition": "Merino wool 100%"
  },
  {
    "web-scraper-order": "1629124337-50",
    "web-scraper-start-url": "https://www2.hm.com/en_in/men/shop-by-product/trousers.html",
    "link": "Printed joggers",
    "link-href": "https://www2.hm.com/en_in/productpage.0991949001.html",
    "name": "Printed joggers",
    "description": "Joggers in sweatshirt fabric made from a cotton blend with small print motifs. Covered elastication and a drawstring at the waist, side pockets, a back pocket with a concealed zip, and an elasticated drawstring with cord stoppers at the hems.",
    "review_count": null,
    "details": "Details\n\t\n\t\tLengthLongWaist RiseRegular waistStyleJoggersCompositionPocket lining: Cotton 100%Shell: Cotton 58%, Polyester 42%Care instructionsMachine wash at 40°DescriptionBlack/Silver-colouredPlaystationPlayStationConceptDIVIDEDPrice (MRP)Rs. 2,699 incl. of all taxesCountry of productionCambodiaCommon generic nameTrousersNet quantity1 NMarketed or imported byH&M Hennes & Mauritz Retail Pvt. Ltd. A-wing, D-3, 2nd Floor District Centre Saket New Delhi -110017 IndiaDate of import06-2021Date of manufactureN/AManufactured byN/ACustomer serviceIn case of consumer complaint, write to H&M Hennes & Mauritz Retail PVT. Ltd, A Wing, D3, 2nd Floor, District Center, Saket, New Delhi 110017, India or call Telephone: 0008000501633. For online and store complaints email customerservice.in@hm.com.DisclaimerThis information is based on sample of the product displayed on website. There may be change in the information on label attached to the product delivered to the customer due to size chosen, date of import, name of manufacturer (in case of manufacturing in India), country of manufacture, etc. The exact detail relevant to the product delivered to the customer will reflect in the label attached to the product so deliveredArt. No.0991949001",
    "img1-src": "//lp2.hm.com/hmgoepprod?set=quality%5B79%5D%2Csource%5B%2Fa8%2F48%2Fa848827d644093314b158717365e966c63a6720d.jpg%5D%2Corigin%5Bdam%5D%2Ccategory%5B%5D%2Ctype%5BDESCRIPTIVESTILLLIFE%5D%2Cres%5Bm%5D%2Chmver%5B2%5D&call=url[file:/product/main]",
    "img2-src": "//lp2.hm.com/hmgoepprod?set=quality%5B79%5D%2Csource%5B%2F78%2F45%2F7845ce830b9f90f2c54f16c73b59cdb0a00fed59.jpg%5D%2Corigin%5Bdam%5D%2Ccategory%5B%5D%2Ctype%5BDESCRIPTIVEDETAIL%5D%2Cres%5Bm%5D%2Chmver%5B2%5D&call=url[file:/product/main]",
    "style": "Joggers",
    "generic name": "Trousers",
    "colors": "Black/Silver-coloured",
    "descript": "Playstation",
    "item__price": "Rs. 2,699",
    "Fit": null,
    "Composition": "Pocket lining: Cotton 100%Shell: Cotton 58%, Polyester 42%"
  },
  {
    "web-scraper-order": "1629124395-68",
    "web-scraper-start-url": "https://www2.hm.com/en_in/men/shop-by-product/trousers.html",
    "link": "Suit trousers Skinny Fit",
    "link-href": "https://www2.hm.com/en_in/productpage.0714032023.html",
    "name": "Suit trousers Skinny Fit",
    "description": "Suit trousers in a stretch weave with a concealed hook-and-eye fastener and zip fly. Side pockets, welt back pockets and legs with creases. Skinny fit – a fit with slightly shorter legs that is close-fitting at the thighs, knees and ankles to create a completely fitted silhouette.",
    "review_count": null,
    "details": "Details\n\t\n\t\tLengthLongFitSkinny fitStyleSuit trousersCompositionPocket lining: Polyester 80%, Cotton 20%Shell: Polyester 79%, Viscose 20%, Elastane 1%Care instructionsMachine wash at 30°DescriptionDark blueSolid colourConceptH&M MANNice to knowConsciousPrice (MRP)Rs. 2,299 incl. of all taxesCountry of productionBangladeshCommon generic nameTrousersNet quantity1 NMarketed or imported byH&M Hennes & Mauritz Retail Pvt. Ltd. A-wing, D-3, 2nd Floor District Centre Saket New Delhi -110017 IndiaDate of import04-2021Date of manufactureN/AManufactured byN/ACustomer serviceIn case of consumer complaint, write to H&M Hennes & Mauritz Retail PVT. Ltd, A Wing, D3, 2nd Floor, District Center, Saket, New Delhi 110017, India or call Telephone: 0008000501633. For online and store complaints email customerservice.in@hm.com.DisclaimerThis information is based on sample of the product displayed on website. There may be change in the information on label attached to the product delivered to the customer due to size chosen, date of import, name of manufacturer (in case of manufacturing in India), country of manufacture, etc. The exact detail relevant to the product delivered to the customer will reflect in the label attached to the product so deliveredArt. No.0714032023",
    "img1-src": "//lp2.hm.com/hmgoepprod?set=quality%5B79%5D%2Csource%5B%2F2f%2F56%2F2f5623e0f34e3b59b397775efa7f7640ff157aed.jpg%5D%2Corigin%5Bdam%5D%2Ccategory%5Bmen_trousers_dressed%5D%2Ctype%5BLOOKBOOK%5D%2Cres%5Bm%5D%2Chmver%5B1%5D&call=url[file:/product/main]",
    "img2-src": "//lp2.hm.com/hmgoepprod?set=quality%5B79%5D%2Csource%5B%2F1a%2F0a%2F1a0aa86f04b7110272163be18f190fcca6f08743.jpg%5D%2Corigin%5Bdam%5D%2Ccategory%5Bmen_trousers_dressed%5D%2Ctype%5BLOOKBOOK%5D%2Cres%5Bm%5D%2Chmver%5B1%5D&call=url[file:/product/main]",
    "style": "Suit trousers",
    "generic name": "Trousers",
    "colors": "Dark blue",
    "descript": "Solid colour",
    "item__price": "Rs. 2,299",
    "Fit": "Skinny fit",
    "Composition": "Pocket lining: Polyester 80%, Cotton 20%Shell: Polyester 79%, Viscose 20%, Elastane 1%"
  },
  {
    "web-scraper-order": "1629124334-49",
    "web-scraper-start-url": "https://www2.hm.com/en_in/men/shop-by-product/trousers.html",
    "link": "Twill trousers Skinny Fit",
    "link-href": "https://www2.hm.com/en_in/productpage.0732188005.html",
    "name": "Twill trousers Skinny Fit",
    "description": "5-pocket trousers in washed, slightly stretchy twill with a regular waist, zip fly and skinny legs. Skinny fit.",
    "review_count": "(165)",
    "details": "Details\n\t\n\t\tLengthLongWaist RiseRegular waistFitSkinny fitCompositionCotton 98%, Elastane 2%Care instructionsMachine wash at 40°DescriptionLight moleSolid colourConceptH&M MANPrice (MRP)Rs. 1,499 incl. of all taxesCountry of productionBangladeshCommon generic nameTrousersSize: 27/30Width: 74 cmLength: 71 cmSize: 30/32Width: 82 cmLength: 80 cmSize: 31/32Width: 85 cmLength: 81 cmSize: 32/32Width: 87 cmLength: 81 cmSize: 34/32Width: 92 cmLength: 82 cmSize: 36/32Width: 97 cmLength: 83 cmNet quantity1 NMarketed or imported byH&M Hennes & Mauritz Retail Pvt. Ltd. A-wing, D-3, 2nd Floor District Centre Saket New Delhi -110017 IndiaDate of import01-2021Date of manufactureN/AManufactured byN/ACustomer serviceIn case of consumer complaint, write to H&M Hennes & Mauritz Retail PVT. Ltd, A Wing, D3, 2nd Floor, District Center, Saket, New Delhi 110017, India or call Telephone: 0008000501633. For online and store complaints email customerservice.in@hm.com.DisclaimerThis information is based on sample of the product displayed on website. There may be change in the information on label attached to the product delivered to the customer due to size chosen, date of import, name of manufacturer (in case of manufacturing in India), country of manufacture, etc. The exact detail relevant to the product delivered to the customer will reflect in the label attached to the product so deliveredArt. No.0732188005",
    "img1-src": "//lp2.hm.com/hmgoepprod?set=quality%5B79%5D%2Csource%5B%2F06%2F13%2F06132643388bf9caba2e33f1d9e989e71f4ee436.jpg%5D%2Corigin%5Bdam%5D%2Ccategory%5Bmen_trousers_trousers_skinny_all%5D%2Ctype%5BDESCRIPTIVESTILLLIFE%5D%2Cres%5Bm%5D%2Chmver%5B1%5D&call=url[file:/product/main]",
    "img2-src": "//lp2.hm.com/hmgoepprod?set=quality%5B79%5D%2Csource%5B%2F51%2F15%2F51150b7c8343012bd8cee697347da326c9919958.jpg%5D%2Corigin%5Bdam%5D%2Ccategory%5Bmen_trousers_trousers_skinny_all%5D%2Ctype%5BDESCRIPTIVEDETAIL%5D%2Cres%5Bm%5D%2Chmver%5B1%5D&call=url[file:/product/main]",
    "style": null,
    "generic name": "Trousers",
    "colors": "Light mole",
    "descript": "Solid colour",
    "item__price": "Rs. 1,499",
    "Fit": "Skinny fit",
    "Composition": "Cotton 98%, Elastane 2%"
  },
  {
    "web-scraper-order": "1629124559-118",
    "web-scraper-start-url": "https://www2.hm.com/en_in/men/shop-by-product/trousers.html",
    "link": "Slim Fit Joggers",
    "link-href": "https://www2.hm.com/en_in/productpage.0988366001.html",
    "name": "Slim Fit Joggers",
    "description": "Dressy joggers in woven fabric with covered elastication and a drawstring at the waist, side pockets, a welt back pocket and legs with creases. Slim Fit – a fit that is close-fitting at the thighs, knees and ankles to create a fitted silhouette.",
    "review_count": null,
    "details": "Details\n\t\n\t\tSizeInside leg: Length: 76.5 cm (Size L/L)LengthLongWaist RiseRegular waistFitSlim fitStyleJoggersCompositionShell: Polyester 77%, Viscose 21%, Elastane 2%Pocket lining: Polyester 65%, Cotton 35%Care instructionsMachine wash at 30°DescriptionBlackSolid colourNice to knowConsciousPrice (MRP)Rs. 1,499 incl. of all taxesCountry of productionBangladeshCommon generic nameTrousersNet quantity1 NMarketed or imported byH&M Hennes & Mauritz Retail Pvt. Ltd. A-wing, D-3, 2nd Floor District Centre Saket New Delhi -110017 IndiaDate of import06-2021Date of manufactureN/AManufactured byN/ACustomer serviceIn case of consumer complaint, write to H&M Hennes & Mauritz Retail PVT. Ltd, A Wing, D3, 2nd Floor, District Center, Saket, New Delhi 110017, India or call Telephone: 0008000501633. For online and store complaints email customerservice.in@hm.com.DisclaimerThis information is based on sample of the product displayed on website. There may be change in the information on label attached to the product delivered to the customer due to size chosen, date of import, name of manufacturer (in case of manufacturing in India), country of manufacture, etc. The exact detail relevant to the product delivered to the customer will reflect in the label attached to the product so deliveredArt. No.0988366001",
    "img1-src": "//lp2.hm.com/hmgoepprod?set=quality%5B79%5D%2Csource%5B%2Fbf%2Fd2%2Fbfd246ee49c3744bf009383475de0a46a626dbe9.jpg%5D%2Corigin%5Bdam%5D%2Ccategory%5B%5D%2Ctype%5BLOOKBOOK%5D%2Cres%5Bm%5D%2Chmver%5B1%5D&call=url[file:/product/main]",
    "img2-src": "//lp2.hm.com/hmgoepprod?set=quality%5B79%5D%2Csource%5B%2F1e%2F62%2F1e628ddbb632de8e6901b842c5a4c1af9bbdcf24.jpg%5D%2Corigin%5Bdam%5D%2Ccategory%5B%5D%2Ctype%5BLOOKBOOK%5D%2Cres%5Bm%5D%2Chmver%5B1%5D&call=url[file:/product/main]",
    "style": "Joggers",
    "generic name": "Trousers",
    "colors": "Black",
    "descript": "Pocket lining: Polyester 65%, Cotton 35%",
    "item__price": "Rs. 1,499",
    "Fit": "Slim fit",
    "Composition": "Shell: Polyester 77%, Viscose 21%, Elastane 2%Pocket lining: Polyester 65%, Cotton 35%"
  },
  {
    "web-scraper-order": "1629124585-126",
    "web-scraper-start-url": "https://www2.hm.com/en_in/men/shop-by-product/trousers.html",
    "link": "Regular Fit Joggers",
    "link-href": "https://www2.hm.com/en_in/productpage.0970817001.html",
    "name": "Regular Fit Joggers",
    "description": "Joggers in sweatshirt fabric made from a cotton blend. Covered elastication and a drawstring at the waist, pockets in the side seams and ribbed hems. Soft brushed inside.",
    "review_count": null,
    "details": "Details\n\t\n\t\tLengthLongWaist RiseRegular waistFitRegular fitStyleJoggersCompositionCotton 60%, Polyester 40%Care instructionsMachine wash at 40°DescriptionBlackSolid colourPrice (MRP)Rs. 1,299 incl. of all taxesCountry of productionIndonesiaCommon generic nameTrousersNet quantity1 NMarketed or imported byH&M Hennes & Mauritz Retail Pvt. Ltd. A-wing, D-3, 2nd Floor District Centre Saket New Delhi -110017 IndiaDate of import06-2021Date of manufactureN/AManufactured byN/ACustomer serviceIn case of consumer complaint, write to H&M Hennes & Mauritz Retail PVT. Ltd, A Wing, D3, 2nd Floor, District Center, Saket, New Delhi 110017, India or call Telephone: 0008000501633. For online and store complaints email customerservice.in@hm.com.DisclaimerThis information is based on sample of the product displayed on website. There may be change in the information on label attached to the product delivered to the customer due to size chosen, date of import, name of manufacturer (in case of manufacturing in India), country of manufacture, etc. The exact detail relevant to the product delivered to the customer will reflect in the label attached to the product so deliveredArt. No.0970817001",
    "img1-src": "//lp2.hm.com/hmgoepprod?set=quality%5B79%5D%2Csource%5B%2Fa5%2F2a%2Fa52a15b89f19bc7993fd32abaea340410e1e37cc.jpg%5D%2Corigin%5Bdam%5D%2Ccategory%5B%5D%2Ctype%5BLOOKBOOK%5D%2Cres%5Bm%5D%2Chmver%5B1%5D&call=url[file:/product/main]",
    "img2-src": "//lp2.hm.com/hmgoepprod?set=quality%5B79%5D%2Csource%5B%2Fe1%2F6f%2Fe16fbe3bb59bee86ef451ba3abb86fe5eb4eae0f.jpg%5D%2Corigin%5Bdam%5D%2Ccategory%5B%5D%2Ctype%5BLOOKBOOK%5D%2Cres%5Bm%5D%2Chmver%5B1%5D&call=url[file:/product/main]",
    "style": "Joggers",
    "generic name": "Trousers",
    "colors": "Black",
    "descript": null,
    "item__price": "Rs. 1,299",
    "Fit": "Regular fit",
    "Composition": "Cotton 60%, Polyester 40%"
  },
  {
    "web-scraper-order": "1629124539-111",
    "web-scraper-start-url": "https://www2.hm.com/en_in/men/shop-by-product/trousers.html",
    "link": "Side-panel joggers",
    "link-href": "https://www2.hm.com/en_in/productpage.0936430001.html",
    "name": "Side-panel joggers",
    "description": "Joggers in soft sweatshirt fabric made from a cotton and recycled polyester blend with a nylon waistband and side panels. Covered elastication and a drawstring at the waist, welt side pockets and ribbed hems. Soft brushed inside.",
    "review_count": null,
    "details": "Details\n\t\n\t\tLengthLongStyleJoggersCompositionCotton 60%, Polyester 40%Care instructionsMachine wash at 40°DescriptionBlackSolid colourConceptDIVIDEDPrice (MRP)Rs. 1,999 incl. of all taxesCountry of productionMyanmarCommon generic nameTrousersNet quantity1 NMarketed or imported byH&M Hennes & Mauritz Retail Pvt. Ltd. A-wing, D-3, 2nd Floor District Centre Saket New Delhi -110017 IndiaDate of import06-2021Date of manufactureN/AManufactured byN/ACustomer serviceIn case of consumer complaint, write to H&M Hennes & Mauritz Retail PVT. Ltd, A Wing, D3, 2nd Floor, District Center, Saket, New Delhi 110017, India or call Telephone: 0008000501633. For online and store complaints email customerservice.in@hm.com.DisclaimerThis information is based on sample of the product displayed on website. There may be change in the information on label attached to the product delivered to the customer due to size chosen, date of import, name of manufacturer (in case of manufacturing in India), country of manufacture, etc. The exact detail relevant to the product delivered to the customer will reflect in the label attached to the product so deliveredArt. No.0936430001",
    "img1-src": "//lp2.hm.com/hmgoepprod?set=quality%5B79%5D%2Csource%5B%2F7e%2Fc0%2F7ec0cf508ec2484806bb2edcbef7adadbd0a0ce2.jpg%5D%2Corigin%5Bdam%5D%2Ccategory%5Bmen_trousers_casual%5D%2Ctype%5BLOOKBOOK%5D%2Cres%5Bm%5D%2Chmver%5B1%5D&call=url[file:/product/main]",
    "img2-src": "//lp2.hm.com/hmgoepprod?set=quality%5B79%5D%2Csource%5B%2Ff5%2Fd1%2Ff5d1336cdf88c0ce6bc6278b3d596486103c093f.jpg%5D%2Corigin%5Bdam%5D%2Ccategory%5Bmen_trousers_casual%5D%2Ctype%5BLOOKBOOK%5D%2Cres%5Bm%5D%2Chmver%5B1%5D&call=url[file:/product/main]",
    "style": "Joggers",
    "generic name": "Trousers",
    "colors": "Black",
    "descript": null,
    "item__price": "Rs. 1,999",
    "Fit": null,
    "Composition": "Cotton 60%, Polyester 40%"
  },
  {
    "web-scraper-order": "1629124404-71",
    "web-scraper-start-url": "https://www2.hm.com/en_in/men/shop-by-product/trousers.html",
    "link": "Linen suit trousers Slim Fit",
    "link-href": "https://www2.hm.com/en_in/productpage.0761501013.html",
    "name": "Linen suit trousers Slim Fit",
    "description": "Ankle-length suit trousers in airy linen with a hook-and-eye fastening and zip fly. Side pockets, welt back pockets and tapered legs with creases. Slim Fit – a fit that is close-fitting at the thighs, knees and ankles to create a fitted silhouette.",
    "review_count": null,
    "details": "Details\n\t\n\t\tSizeWaist: Circumference: 93.5 cm (Size 52L)Inside leg: Length: 77.0 cm (Size 52L)LengthAnkle lengthWaist RiseRegular waistFitSlim fitStyleSuit trousersCompositionPocket lining: Polyester 80%, Cotton 20%Linen 100%Care instructionsMachine wash at 30°MaterialLinenDescriptionDark greigeSolid colourConceptH&M MANNice to knowPremium SelectionPrice (MRP)Rs. 2,299 incl. of all taxesCountry of productionMyanmarCommon generic nameTrousersNet quantity1 NMarketed or imported byH&M Hennes & Mauritz Retail Pvt. Ltd. A-wing, D-3, 2nd Floor District Centre Saket New Delhi -110017 IndiaDate of import05-2021Date of manufactureN/AManufactured byN/ACustomer serviceIn case of consumer complaint, write to H&M Hennes & Mauritz Retail PVT. Ltd, A Wing, D3, 2nd Floor, District Center, Saket, New Delhi 110017, India or call Telephone: 0008000501633. For online and store complaints email customerservice.in@hm.com.DisclaimerThis information is based on sample of the product displayed on website. There may be change in the information on label attached to the product delivered to the customer due to size chosen, date of import, name of manufacturer (in case of manufacturing in India), country of manufacture, etc. The exact detail relevant to the product delivered to the customer will reflect in the label attached to the product so deliveredArt. No.0761501013",
    "img1-src": "//lp2.hm.com/hmgoepprod?set=quality%5B79%5D%2Csource%5B%2F3b%2F46%2F3b4661a876a011bd4ebc9c9daa576271146e0ccf.jpg%5D%2Corigin%5Bdam%5D%2Ccategory%5Bmen_blazerssuits_trousers%5D%2Ctype%5BLOOKBOOK%5D%2Cres%5Bm%5D%2Chmver%5B1%5D&call=url[file:/product/main]",
    "img2-src": "//lp2.hm.com/hmgoepprod?set=quality%5B79%5D%2Csource%5B%2F71%2Fbc%2F71bc02c3c1cedc4c0ddb5ad68ce6270f06471012.jpg%5D%2Corigin%5Bdam%5D%2Ccategory%5Bmen_blazerssuits_trousers%5D%2Ctype%5BLOOKBOOK%5D%2Cres%5Bm%5D%2Chmver%5B1%5D&call=url[file:/product/main]",
    "style": "Suit trousers",
    "generic name": "Trousers",
    "colors": "Dark greige",
    "descript": "Linen 100%",
    "item__price": "Rs. 2,299",
    "Fit": "Slim fit",
    "Composition": "Pocket lining: Polyester 80%, Cotton 20%Linen 100%"
  },
  {
    "web-scraper-order": "1629124436-80",
    "web-scraper-start-url": "https://www2.hm.com/en_in/men/shop-by-product/trousers.html",
    "link": "Track pants",
    "link-href": "https://www2.hm.com/en_in/productpage.0696125001.html",
    "name": "Track pants",
    "description": "Track pants in fast-drying functional fabric made from recycled polyester with covered elastication and a concealed drawstring at the waist, pockets in the side seams and cuffed hems.",
    "review_count": "(88)",
    "details": "Details\n\t\n\t\tLengthLongStyleJoggersFunctionsQuick dryCompositionPolyester 100%More sustainable materialsRecycled polyester 100%Care instructionsMachine wash at 40°Sports activityTrainingDescriptionBlackSolid colourNice to knowConsciousPrice (MRP)Rs. 1,499 incl. of all taxesCountry of productionChinaCommon generic nameTrousersSize: XS/LWidth: 64 cmLength: 69 cmSize: S/LWidth: 72 cmLength: 70 cmSize: M/LWidth: 80 cmLength: 71 cmSize: L/LWidth: 88 cmLength: 72 cmSize: XL/LWidth: 96 cmLength: 73 cmSize: XXL/LWidth: 1.04 mLength: 74 cmNet quantity1 NMarketed or imported byH&M Hennes & Mauritz Retail Pvt. Ltd. A-wing, D-3, 2nd Floor District Centre Saket New Delhi -110017 IndiaDate of import02-2021Date of manufactureN/AManufactured byN/ACustomer serviceIn case of consumer complaint, write to H&M Hennes & Mauritz Retail PVT. Ltd, A Wing, D3, 2nd Floor, District Center, Saket, New Delhi 110017, India or call Telephone: 0008000501633. For online and store complaints email customerservice.in@hm.com.DisclaimerThis information is based on sample of the product displayed on website. There may be change in the information on label attached to the product delivered to the customer due to size chosen, date of import, name of manufacturer (in case of manufacturing in India), country of manufacture, etc. The exact detail relevant to the product delivered to the customer will reflect in the label attached to the product so deliveredArt. No.0696125001",
    "img1-src": "//lp2.hm.com/hmgoepprod?set=quality%5B79%5D%2Csource%5B%2Fa7%2F95%2Fa7959aa3aadf05e012f9fe6b87bf5616f4716816.jpg%5D%2Corigin%5Bdam%5D%2Ccategory%5Bmen_sport_bottoms%5D%2Ctype%5BLOOKBOOK%5D%2Cres%5Bm%5D%2Chmver%5B1%5D&call=url[file:/product/main]",
    "img2-src": "//lp2.hm.com/hmgoepprod?set=quality%5B79%5D%2Csource%5B%2Fcc%2F64%2Fcc64c81614c08e773f5d2d234a7ad19f736b6673.jpg%5D%2Corigin%5Bdam%5D%2Ccategory%5Bmen_sport_bottoms%5D%2Ctype%5BLOOKBOOK%5D%2Cres%5Bm%5D%2Chmver%5B1%5D&call=url[file:/product/main]",
    "style": "Joggers",
    "generic name": "Trousers",
    "colors": "Black",
    "descript": null,
    "item__price": "Rs. 1,499",
    "Fit": null,
    "Composition": "Polyester 100%"
  },
  {
    "web-scraper-order": "1629124591-128",
    "web-scraper-start-url": "https://www2.hm.com/en_in/men/shop-by-product/trousers.html",
    "link": "2-pack Regular Fit Joggers",
    "link-href": "https://www2.hm.com/en_in/productpage.0970816001.html",
    "name": "2-pack Regular Fit Joggers",
    "description": "Joggers in sweatshirt fabric made from a cotton blend. Covered elastication and a drawstring at the waist, pockets in the side seams and ribbed hems. Soft brushed inside.",
    "review_count": null,
    "details": "Details\n\t\n\t\tPieces2LengthLongWaist RiseRegular waistFitRegular fitStyleJoggersCompositionCotton 75%, Polyester 20%, Viscose 5%Cotton 60%, Polyester 40%Care instructionsMachine wash at 40°DescriptionBlack/Light grey marlSolid colourConceptBASICSPrice (MRP)Rs. 2,299 incl. of all taxesCountry of productionBangladeshCommon generic nameTrousersNet quantity2 NMarketed or imported byH&M Hennes & Mauritz Retail Pvt. Ltd. A-wing, D-3, 2nd Floor District Centre Saket New Delhi -110017 IndiaDate of import06-2021Date of manufactureN/AManufactured byN/ACustomer serviceIn case of consumer complaint, write to H&M Hennes & Mauritz Retail PVT. Ltd, A Wing, D3, 2nd Floor, District Center, Saket, New Delhi 110017, India or call Telephone: 0008000501633. For online and store complaints email customerservice.in@hm.com.DisclaimerThis information is based on sample of the product displayed on website. There may be change in the information on label attached to the product delivered to the customer due to size chosen, date of import, name of manufacturer (in case of manufacturing in India), country of manufacture, etc. The exact detail relevant to the product delivered to the customer will reflect in the label attached to the product so deliveredArt. No.0970816001",
    "img1-src": "//lp2.hm.com/hmgoepprod?set=quality%5B79%5D%2Csource%5B%2F6f%2Fca%2F6fca85f1bf408e96582a166fd43e9687d5793094.jpg%5D%2Corigin%5Bdam%5D%2Ccategory%5B%5D%2Ctype%5BLOOKBOOK%5D%2Cres%5Bm%5D%2Chmver%5B1%5D&call=url[file:/product/main]",
    "img2-src": "//lp2.hm.com/hmgoepprod?set=quality%5B79%5D%2Csource%5B%2F8c%2F3f%2F8c3f9a557460971ca8aeaccfb27e899c1d08782f.jpg%5D%2Corigin%5Bdam%5D%2Ccategory%5B%5D%2Ctype%5BLOOKBOOK%5D%2Cres%5Bm%5D%2Chmver%5B1%5D&call=url[file:/product/main]",
    "style": "Joggers",
    "generic name": "Trousers",
    "colors": "Black/Light grey marl",
    "descript": "Cotton 60%, Polyester 40%",
    "item__price": "Rs. 2,299",
    "Fit": "Regular fit",
    "Composition": "Cotton 75%, Polyester 20%, Viscose 5%Cotton 60%, Polyester 40%"
  },
  {
    "web-scraper-order": "1629124411-73",
    "web-scraper-start-url": "https://www2.hm.com/en_in/men/shop-by-product/trousers.html",
    "link": "Slim Fit Cropped chinos",
    "link-href": "https://www2.hm.com/en_in/productpage.0978273004.html",
    "name": null,
    "description": null,
    "review_count": null,
    "details": null,
    "img1-src": "",
    "img2-src": "",
    "style": null,
    "generic name": null,
    "colors": null,
    "descript": null,
    "item__price": null,
    "Fit": null,
    "Composition": null
  },
  {
    "web-scraper-order": "1629124419-75",
    "web-scraper-start-url": "https://www2.hm.com/en_in/men/shop-by-product/trousers.html",
    "link": "Regular Fit Twill joggers",
    "link-href": "https://www2.hm.com/en_in/productpage.0975244001.html",
    "name": "Regular Fit Twill joggers",
    "description": "Joggers in stretch cotton twill with covered elastication and a drawstring at the waist and a fake fly. Side pockets, back pockets with a button and covered elastication at the hems. Regular Fit – a classic fit with good room for movement over the thighs and knees to create a comfortable, straight silhouette.",
    "review_count": null,
    "details": "Details\n\t\n\t\tSizeInside leg: Length: 76.0 cm (Size L/L)LengthLongWaist RiseRegular waistFitRegular fitStyleJoggersCompositionPocket lining: Cotton 100%Shell: Cotton 98%, Elastane 2%Care instructionsMachine wash at 40°MaterialCottonDescriptionBeigeSolid colourNice to knowConsciousPrice (MRP)Rs. 1,499 incl. of all taxesCountry of productionBangladeshCommon generic nameTrousersNet quantity1 NMarketed or imported byH&M Hennes & Mauritz Retail Pvt. Ltd. A-wing, D-3, 2nd Floor District Centre Saket New Delhi -110017 IndiaDate of import05-2021Date of manufactureN/AManufactured byN/ACustomer serviceIn case of consumer complaint, write to H&M Hennes & Mauritz Retail PVT. Ltd, A Wing, D3, 2nd Floor, District Center, Saket, New Delhi 110017, India or call Telephone: 0008000501633. For online and store complaints email customerservice.in@hm.com.DisclaimerThis information is based on sample of the product displayed on website. There may be change in the information on label attached to the product delivered to the customer due to size chosen, date of import, name of manufacturer (in case of manufacturing in India), country of manufacture, etc. The exact detail relevant to the product delivered to the customer will reflect in the label attached to the product so deliveredArt. No.0975244001",
    "img1-src": "//lp2.hm.com/hmgoepprod?set=quality%5B79%5D%2Csource%5B%2Fa7%2Fc5%2Fa7c58de58a41c80fccb31b30a8ee52f28bede4ba.jpg%5D%2Corigin%5Bdam%5D%2Ccategory%5B%5D%2Ctype%5BLOOKBOOK%5D%2Cres%5Bm%5D%2Chmver%5B1%5D&call=url[file:/product/main]",
    "img2-src": "//lp2.hm.com/hmgoepprod?set=quality%5B79%5D%2Csource%5B%2Fe3%2F3d%2Fe33d454ea73868b24550d50488e0927dc15a4f25.jpg%5D%2Corigin%5Bdam%5D%2Ccategory%5B%5D%2Ctype%5BLOOKBOOK%5D%2Cres%5Bm%5D%2Chmver%5B1%5D&call=url[file:/product/main]",
    "style": "Joggers",
    "generic name": "Trousers",
    "colors": "Beige",
    "descript": "Shell: Cotton 98%, Elastane 2%",
    "item__price": "Rs. 1,499",
    "Fit": "Regular fit",
    "Composition": "Pocket lining: Cotton 100%Shell: Cotton 98%, Elastane 2%"
  },
  {
    "web-scraper-order": "1629124323-46",
    "web-scraper-start-url": "https://www2.hm.com/en_in/men/shop-by-product/trousers.html",
    "link": "Sports joggers",
    "link-href": "https://www2.hm.com/en_in/productpage.0862106001.html",
    "name": "Sports joggers",
    "description": "Sports joggers in heavy jersey with taped details. Elasticated, drawstring waist and zipped side pockets. Tapered legs with shaping seams at the knees for added mobility and wide ribbing at the hems. The polyester content of the joggers is recycled.",
    "review_count": null,
    "details": "Details\n\t\n\t\tLengthLongStyleTaperedJoggersCompositionShell: Polyester 58%, Cotton 42%Pocket lining: Polyester 100%More sustainable materialsRecycled polyester 58%Care instructionsMachine wash at 40°Sports activityTrainingDescriptionBlackSolid colourNice to knowConsciousPrice (MRP)Rs. 2,299 incl. of all taxesCountry of productionChinaCommon generic nameTrousersNet quantity1 NMarketed or imported byH&M Hennes & Mauritz Retail Pvt. Ltd. A-wing, D-3, 2nd Floor District Centre Saket New Delhi -110017 IndiaDate of import02-2021Date of manufactureN/AManufactured byN/ACustomer serviceIn case of consumer complaint, write to H&M Hennes & Mauritz Retail PVT. Ltd, A Wing, D3, 2nd Floor, District Center, Saket, New Delhi 110017, India or call Telephone: 0008000501633. For online and store complaints email customerservice.in@hm.com.DisclaimerThis information is based on sample of the product displayed on website. There may be change in the information on label attached to the product delivered to the customer due to size chosen, date of import, name of manufacturer (in case of manufacturing in India), country of manufacture, etc. The exact detail relevant to the product delivered to the customer will reflect in the label attached to the product so deliveredArt. No.0862106001",
    "img1-src": "//lp2.hm.com/hmgoepprod?set=quality%5B79%5D%2Csource%5B%2F6a%2F5d%2F6a5dc400eafc67cd87140dede52748a85c37c4c6.jpg%5D%2Corigin%5Bdam%5D%2Ccategory%5Bmen_sport_bottoms%5D%2Ctype%5BLOOKBOOK%5D%2Cres%5Bm%5D%2Chmver%5B1%5D&call=url[file:/product/main]",
    "img2-src": "//lp2.hm.com/hmgoepprod?set=quality%5B79%5D%2Csource%5B%2F80%2Fff%2F80ff1672973f7a1f47f13c8ffd50df9d6b31faca.jpg%5D%2Corigin%5Bdam%5D%2Ccategory%5Bmen_sport_bottoms%5D%2Ctype%5BLOOKBOOK%5D%2Cres%5Bm%5D%2Chmver%5B1%5D&call=url[file:/product/main]",
    "style": "Tapered",
    "generic name": "Trousers",
    "colors": "Black",
    "descript": null,
    "item__price": "Rs. 2,299",
    "Fit": null,
    "Composition": "Shell: Polyester 58%, Cotton 42%Pocket lining: Polyester 100%"
  },
  {
    "web-scraper-order": "1629124290-35",
    "web-scraper-start-url": "https://www2.hm.com/en_in/men/shop-by-product/trousers.html",
    "link": "Cotton chinos Skinny Fit",
    "link-href": "https://www2.hm.com/en_in/productpage.0710876047.html",
    "name": "Cotton chinos Skinny Fit",
    "description": "Chinos in stretch cotton twill with a zip fly and button, diagonal side pockets and welt back pockets with a button. Skinny Fit – a fit with slightly shorter legs that is close-fitting at the thighs, knees and ankles to create a completely fitted silhouette.",
    "review_count": "(515)",
    "details": "Details\n\t\n\t\tLengthAnkle lengthWaist RiseRegular waistFitSkinny fitStyleChinosCompositionPocket: Cotton 100%Cotton 98%, Elastane 2%Care instructionsMachine wash at 40°MaterialCottonDescriptionGrey-greenSolid colourPrice (MRP)Rs. 1,999 incl. of all taxesCountry of productionBangladeshCommon generic nameTrousersSize: 28/30Width: 77 cmLength: 75 cmSize: 28/32Width: 77 cmLength: 79 cmSize: 29/30Width: 80 cmLength: 76 cmSize: 29/32Width: 80 cmLength: 80 cmSize: 30/30Width: 82 cmLength: 76 cmSize: 30/32Width: 82 cmLength: 80 cmSize: 31/30Width: 85 cmLength: 76 cmSize: 31/32Width: 85 cmLength: 80 cmSize: 32/30Width: 87 cmLength: 77 cmSize: 32/32Width: 87 cmLength: 81 cmSize: 33/30Width: 90 cmLength: 77 cmSize: 33/32Width: 90 cmLength: 81 cmSize: 34/30Width: 92 cmLength: 78 cmSize: 34/32Width: 92 cmLength: 82 cmSize: 36/32Width: 97 cmLength: 82 cmSize: 38/32Width: 1.02 mLength: 83 cmNet quantity1 NMarketed or imported byH&M Hennes & Mauritz Retail Pvt. Ltd. A-wing, D-3, 2nd Floor District Centre Saket New Delhi -110017 IndiaDate of import08-2020Date of manufactureN/AManufactured byN/ACustomer serviceIn case of consumer complaint, write to H&M Hennes & Mauritz Retail PVT. Ltd, A Wing, D3, 2nd Floor, District Center, Saket, New Delhi 110017, India or call Telephone: 0008000501633. For online and store complaints email customerservice.in@hm.com.DisclaimerThis information is based on sample of the product displayed on website. There may be change in the information on label attached to the product delivered to the customer due to size chosen, date of import, name of manufacturer (in case of manufacturing in India), country of manufacture, etc. The exact detail relevant to the product delivered to the customer will reflect in the label attached to the product so deliveredArt. No.0710876047",
    "img1-src": "//lp2.hm.com/hmgoepprod?set=quality%5B79%5D%2Csource%5B%2F36%2F8d%2F368d3a20d8af320af360ab4574c6b985b7dd5ba5.jpg%5D%2Corigin%5Bdam%5D%2Ccategory%5Bmen_trousers_chinos_skinny_all%5D%2Ctype%5BDESCRIPTIVESTILLLIFE%5D%2Cres%5Bm%5D%2Chmver%5B1%5D&call=url[file:/product/main]",
    "img2-src": "//lp2.hm.com/hmgoepprod?set=quality%5B79%5D%2Csource%5B%2F9c%2F2e%2F9c2e8538ea67176650fcef187cfd2c044e70d3b7.jpg%5D%2Corigin%5Bdam%5D%2Ccategory%5Bmen_trousers_chinos_skinny_all%5D%2Ctype%5BDESCRIPTIVEDETAIL%5D%2Cres%5Bm%5D%2Chmver%5B1%5D&call=url[file:/product/main]",
    "style": "Chinos",
    "generic name": "Trousers",
    "colors": "Grey-green",
    "descript": null,
    "item__price": "Rs. 1,999",
    "Fit": "Skinny fit",
    "Composition": "Pocket: Cotton 100%Cotton 98%, Elastane 2%"
  },
  {
    "web-scraper-order": "1629124354-56",
    "web-scraper-start-url": "https://www2.hm.com/en_in/men/shop-by-product/trousers.html",
    "link": "Sports trousers",
    "link-href": "https://www2.hm.com/en_in/productpage.0890677001.html",
    "name": "Sports trousers",
    "description": "Sports trousers in fast-drying functional fabric with an elasticated, drawstring waist, diagonal side pockets with a zip, and slim, tapered legs with cuffed hems.",
    "review_count": null,
    "details": "Details\n\t\n\t\tLengthLongWaist RiseRegular waistStyleTaperedFunctionsQuick dryCompositionPolyester 92%, Elastane 8%Care instructionsMachine wash at 40°Sports activityTrainingDescriptionDark grey marlSolid colourPrice (MRP)Rs. 1,999 incl. of all taxesCountry of productionChinaCommon generic nameTrousersNet quantity1 NMarketed or imported byH&M Hennes & Mauritz Retail Pvt. Ltd. A-wing, D-3, 2nd Floor District Centre Saket New Delhi -110017 IndiaDate of import02-2021Date of manufactureN/AManufactured byN/ACustomer serviceIn case of consumer complaint, write to H&M Hennes & Mauritz Retail PVT. Ltd, A Wing, D3, 2nd Floor, District Center, Saket, New Delhi 110017, India or call Telephone: 0008000501633. For online and store complaints email customerservice.in@hm.com.DisclaimerThis information is based on sample of the product displayed on website. There may be change in the information on label attached to the product delivered to the customer due to size chosen, date of import, name of manufacturer (in case of manufacturing in India), country of manufacture, etc. The exact detail relevant to the product delivered to the customer will reflect in the label attached to the product so deliveredArt. No.0890677001",
    "img1-src": "//lp2.hm.com/hmgoepprod?set=quality%5B79%5D%2Csource%5B%2F37%2F91%2F3791ac510b5741cd0a77c3ce034f323e304c086d.jpg%5D%2Corigin%5Bdam%5D%2Ccategory%5B%5D%2Ctype%5BDESCRIPTIVESTILLLIFE%5D%2Cres%5Bm%5D%2Chmver%5B1%5D&call=url[file:/product/main]",
    "img2-src": "//lp2.hm.com/hmgoepprod?set=quality%5B79%5D%2Csource%5B%2Fcd%2F6d%2Fcd6dc7635016948f63e2c2fd6c963225fdab01cf.jpg%5D%2Corigin%5Bdam%5D%2Ccategory%5B%5D%2Ctype%5BDESCRIPTIVEDETAIL%5D%2Cres%5Bm%5D%2Chmver%5B1%5D&call=url[file:/product/main]",
    "style": "Tapered",
    "generic name": "Trousers",
    "colors": "Dark grey marl",
    "descript": null,
    "item__price": "Rs. 1,999",
    "Fit": null,
    "Composition": "Polyester 92%, Elastane 8%"
  },
  {
    "web-scraper-order": "1629124472-91",
    "web-scraper-start-url": "https://www2.hm.com/en_in/men/shop-by-product/trousers.html",
    "link": "Slim Fit Sports joggers",
    "link-href": "https://www2.hm.com/en_in/productpage.0995680003.html",
    "name": "Slim Fit Sports joggers",
    "description": "Jersey joggers for indoor and outdoor workouts. Covered elastication and a drawstring at the waist, zipped side pockets for safe storage of valuables and a mesh panel at the crotch for increased air permeability. Cuffed hems.",
    "review_count": null,
    "details": "Details\n\t\n\t\tSizeInside leg: Length: 73.5 cm (Size L/L)LengthLongWaist RiseRegular waistFitSlim fitStyleJoggersCompositionMesh: Polyester 100%Shell: Cotton 58%, Polyester 38%, Elastane 4%Care instructionsMachine wash at 40°Sports activityTrainingDescriptionKhaki greenSolid colourNice to knowConsciousPrice (MRP)Rs. 1,999 incl. of all taxesCountry of productionCambodiaCommon generic nameTrousersNet quantity1 NMarketed or imported byH&M Hennes & Mauritz Retail Pvt. Ltd. A-wing, D-3, 2nd Floor District Centre Saket New Delhi -110017 IndiaDate of import06-2021Date of manufactureN/AManufactured byN/ACustomer serviceIn case of consumer complaint, write to H&M Hennes & Mauritz Retail PVT. Ltd, A Wing, D3, 2nd Floor, District Center, Saket, New Delhi 110017, India or call Telephone: 0008000501633. For online and store complaints email customerservice.in@hm.com.DisclaimerThis information is based on sample of the product displayed on website. There may be change in the information on label attached to the product delivered to the customer due to size chosen, date of import, name of manufacturer (in case of manufacturing in India), country of manufacture, etc. The exact detail relevant to the product delivered to the customer will reflect in the label attached to the product so deliveredArt. No.0995680003",
    "img1-src": "//lp2.hm.com/hmgoepprod?set=quality%5B79%5D%2Csource%5B%2F94%2F09%2F9409f22e43668d5db2fe00d10f1b4fcc31e219d9.jpg%5D%2Corigin%5Bdam%5D%2Ccategory%5B%5D%2Ctype%5BLOOKBOOK%5D%2Cres%5Bm%5D%2Chmver%5B1%5D&call=url[file:/product/main]",
    "img2-src": "//lp2.hm.com/hmgoepprod?set=quality%5B79%5D%2Csource%5B%2F06%2F54%2F0654b8ba0a92ad717caf0d10bb12b9347e83ba81.jpg%5D%2Corigin%5Bdam%5D%2Ccategory%5B%5D%2Ctype%5BLOOKBOOK%5D%2Cres%5Bm%5D%2Chmver%5B1%5D&call=url[file:/product/main]",
    "style": "Joggers",
    "generic name": "Trousers",
    "colors": "Khaki green",
    "descript": "Shell: Cotton 58%, Polyester 38%, Elastane 4%",
    "item__price": "Rs. 1,999",
    "Fit": "Slim fit",
    "Composition": "Mesh: Polyester 100%Shell: Cotton 58%, Polyester 38%, Elastane 4%"
  }
]